Workbook

Sheet Phân công
A1: MSSV | B1: Họ tên SV | C1: Lớp | D1: GVHD | E1: GVPB | F1: CTHĐ | G1: TVHĐ | H1: TKHĐ | I1: Thời gian | J1: Phòng | K1: Hội đồng
A2: K224141715 | B2: Phạm Thụy Phương Dung | C2: K22414E | D2: PGS. TS Lê Đức Quang Tú | E2: TS Nguyễn Thanh Liêm | F2: TS Nguyễn Thanh Liêm | G2: TS Nguyễn Trung Hiếu | H2: ThS Ngô Phú Thanh | I2: 8h00 sáng thứ năm ngày 05/3/2026 | J2: B1.501 | K2: 01
A3: K224141738 | B3: Vũ Ngọc Thuỷ Tiên | C3: K22414E | D3: PGS. TS Lê Đức Quang Tú | E3: TS Nguyễn Trung Hiếu | F3: TS Nguyễn Thanh Liêm | G3: TS Nguyễn Trung Hiếu | H3: ThS Ngô Phú Thanh | I3: 8h00 sáng thứ năm ngày 05/3/2026 | J3: B1.501 | K3: 01
A4: K224141652 | B4: Lê Phúc Chí | C4: K22414 | D4: PGS. TS Nguyễn Anh Phong | E4: TS Nguyễn Trung Hiếu | F4: TS Nguyễn Thanh Liêm | G4: TS Nguyễn Trung Hiếu | H4: ThS Ngô Phú Thanh | I4: 8h00 sáng thứ năm ngày 05/3/2026 | J4: B1.501 | K4: 01
A5: K224141654 | B5: Đào Mỹ Duyên | C5: K22414 | D5: PGS. TS Nguyễn Anh Phong | E5: ThS Ngô Phú Thanh | F5: TS Nguyễn Thanh Liêm | G5: TS Nguyễn Trung Hiếu | H5: ThS Ngô Phú Thanh | I5: 8h00 sáng thứ năm ngày 05/3/2026 | J5: B1.501 | K5: 01
A6: K224141658 | B6: Đào Ngọc Hà | C6: K22414 | D6: PGS. TS Nguyễn Anh Phong | E6: TS Nguyễn Thanh Liêm | F6: TS Nguyễn Thanh Liêm | G6: TS Nguyễn Trung Hiếu | H6: ThS Ngô Phú Thanh | I6: 8h00 sáng thứ năm ngày 05/3/2026 | J6: B1.501 | K6: 01
A7: K224040570 | B7: Nguyễn Yến Linh | C7: K22404E | D7: PGS. TS Lê Đức Quang Tú
A8: K224040583 | B8: Tô Như Quỳnh | C8: K22404E | D8: PGS. TS Lê Đức Quang Tú
A9: K224040584 | B9: Trần Ngọc Lan Thanh | C9: K22404E | D9: PGS. TS Lê Đức Quang Tú
A10: K224040585 | B10: Ngô Nguyễn Quỳnh Thơ | C10: K22404E | D10: PGS. TS Lê Đức Quang Tú
A11: K224141659 | B11: Mai Thị Thanh Hà | C11: K22414 | D11: PGS. TS Nguyễn Anh Phong | E11: TS Nguyễn Trung Hiếu | F11: TS Nguyễn Thanh Liêm | G11: TS Nguyễn Trung Hiếu | H11: ThS Ngô Phú Thanh | I11: 8h00 sáng thứ năm ngày 05/3/2026 | J11: B1.501 | K11: 01
A12: K224141667 | B12: Lê Thị Hương | C12: K22414 | D12: PGS. TS Nguyễn Anh Phong | E12: ThS Ngô Phú Thanh | F12: TS Nguyễn Thanh Liêm | G12: TS Nguyễn Trung Hiếu | H12: ThS Ngô Phú Thanh | I12: 8h00 sáng thứ năm ngày 05/3/2026 | J12: B1.501 | K12: 01
A13: K224141714 | B13: Lê Danh Bách | C13: K22414E | D13: PGS. TS Phạm Thị Thanh Xuân | E13: TS Nguyễn Thanh Liêm | F13: TS Nguyễn Thanh Liêm | G13: TS Nguyễn Trung Hiếu | H13: ThS Ngô Phú Thanh | I13: 8h00 sáng thứ năm ngày 05/3/2026 | J13: B1.501 | K13: 01
A14: K224141730 | B14: Đoàn Tuấn Nghĩa | C14: K22414E | D14: PGS. TS Phạm Thị Thanh Xuân | E14: TS Nguyễn Trung Hiếu | F14: TS Nguyễn Thanh Liêm | G14: TS Nguyễn Trung Hiếu | H14: ThS Ngô Phú Thanh | I14: 8h00 sáng thứ năm ngày 05/3/2026 | J14: B1.501 | K14: 01
A15: K224141733 | B15: Bùi Đặng Quỳnh Như | C15: K22414E | D15: PGS. TS Phạm Thị Thanh Xuân | E15: ThS Ngô Phú Thanh | F15: TS Nguyễn Thanh Liêm | G15: TS Nguyễn Trung Hiếu | H15: ThS Ngô Phú Thanh | I15: 8h00 sáng thứ năm ngày 05/3/2026 | J15: B1.501 | K15: 01
A16: K224141711 | B16: Lê Phú An | C16: K22414E | D16: TS Nguyễn Thôn Dã | E16: TS Nguyễn Thanh Liêm | F16: TS Nguyễn Thanh Liêm | G16: TS Nguyễn Trung Hiếu | H16: ThS Ngô Phú Thanh | I16: 8h00 sáng thứ năm ngày 05/3/2026 | J16: B1.501 | K16: 01
A17: K224141655 | B17: Lê Thị Mỹ Duyên | C17: K22414 | D17: ThS Ngô Phú Thanh | E17: TS Nguyễn Thôn Dã | F17: PGS. TS Lê Đức Quang Tú | G17: TS Nguyễn Thôn Dã | H17: TS Võ Thị Ngọc Trinh | I17: 8h00 sáng thứ năm ngày 05/3/2026 | J17: B1.502 | K17: 02
A18: K224141668 | B18: Phan Vũ Đình Khang | C18: K22414 | D18: ThS Ngô Phú Thanh | E18: TS Võ Thị Ngọc Trinh | F18: PGS. TS Lê Đức Quang Tú | G18: TS Nguyễn Thôn Dã | H18: TS Võ Thị Ngọc Trinh | I18: 8h00 sáng thứ năm ngày 05/3/2026 | J18: B1.502 | K18: 02
A19: K224141703 | B19: Thông Thị Quế Trân | C19: K22414 | D19: ThS Ngô Phú Thanh | E19: PGS. TS Lê Đức Quang Tú | F19: PGS. TS Lê Đức Quang Tú | G19: TS Nguyễn Thôn Dã | H19: TS Võ Thị Ngọc Trinh | I19: 8h00 sáng thứ năm ngày 05/3/2026 | J19: B1.502 | K19: 02
A20: K224141649 | B20: Trần Lê Quang An | C20: K22414 | D20: ThS Ngô Phú Thanh | E20: TS Nguyễn Thôn Dã | F20: PGS. TS Lê Đức Quang Tú | G20: TS Nguyễn Thôn Dã | H20: TS Võ Thị Ngọc Trinh | I20: 8h00 sáng thứ năm ngày 05/3/2026 | J20: B1.502 | K20: 02
A21: K224141657 | B21: Bùi Thị Ngọc Hà | C21: K22414 | D21: ThS Ngô Phú Thanh | E21: TS Võ Thị Ngọc Trinh | F21: PGS. TS Lê Đức Quang Tú | G21: TS Nguyễn Thôn Dã | H21: TS Võ Thị Ngọc Trinh | I21: 8h00 sáng thứ năm ngày 05/3/2026 | J21: B1.502 | K21: 02
A22: K224141717 | B22: Trần Đức Duy | C22: K22414E | D22: ThS Phạm Chí Khoa | E22: PGS. TS Lê Đức Quang Tú | F22: PGS. TS Lê Đức Quang Tú | G22: TS Nguyễn Thôn Dã | H22: TS Võ Thị Ngọc Trinh | I22: 8h00 sáng thứ năm ngày 05/3/2026 | J22: B1.502 | K22: 02
... A34: K224141713 | B34: Nguyễn Thương Kỳ Anh | C34: K22414E | D34: TS Nguyễn Trung Hiếu | E34: ThS Phạm Chí Khoa | F34: PGS. TS Phạm Thị Thanh Xuân | G34: ThS Phan Huy Tâm | H34: ThS Phạm Chí Khoa | I34: 8h00 sáng thứ năm ngày 05/3/2026 | J34: B1.503 | K34: 03
A35: K224040575 | B35: Phan Quang Minh | C35: K22404E | D35: PGS. TS Nguyễn Thị Ánh Như
A36: K224040586 | B36: Đặng Hoài Minh Thư | C36: K22404E | D36: PGS. TS Nguyễn Thị Ánh Như
A37: K224040591 | B37: Nguyễn Hà Trâm | C37: K22404E | D37: PGS. TS Nguyễn Thị Ánh Như
A38: K224040593 | B38: Phạm Văn Trọng | C38: K22404E | D38: PGS. TS Nguyễn Thị Ánh Như
A39: K224040594 | B39: Nguyễn Thành Trung | C39: K22404E | D39: PGS. TS Nguyễn Thị Ánh Như
A40: K224040595 | B40: Lê Nguyễn Thanh Trúc | C40: K22404E | D40: PGS. TS Nguyễn Thị Ánh Như
A41: K224141726 | B41: Dương Thị Thuỳ Linh | C41: K22414E | D41: TS Nguyễn Trung Hiếu | E41: PGS. TS Phạm Thị Thanh Xuân | F41: PGS. TS Phạm Thị Thanh Xuân | G41: ThS Phan Huy Tâm | H41: ThS Phạm Chí Khoa | I41: 8h00 sáng thứ năm ngày 05/3/2026 | J41: B1.503 | K41: 03
A42: K224141744 | B42: Lâm Thanh Vi | C42: K22414E | D42: TS Nguyễn Trung Hiếu | E42: ThS Phan Huy Tâm | F42: PGS. TS Phạm Thị Thanh Xuân | G42: ThS Phan Huy Tâm | H42: ThS Phạm Chí Khoa | I42: 8h00 sáng thứ năm ngày 05/3/2026 | J42: B1.503 | K42: 03
A43: K224141710 | B43: Lê Hoàng Phi Yến | C43: K22414 | D43: TS Võ Thị Ngọc Trinh | E43: ThS Phạm Chí Khoa | F43: PGS. TS Phạm Thị Thanh Xuân | G43: ThS Phan Huy Tâm | H43: ThS Phạm Chí Khoa | I43: 8h00 sáng thứ năm ngày 05/3/2026 | J43: B1.503 | K43: 03
A44: K224141716 | B44: Nguyễn Quang Duy | C44: K22414E | D44: TS Võ Thị Ngọc Trinh | E44: PGS. TS Phạm Thị Thanh Xuân | F44: PGS. TS Phạm Thị Thanh Xuân | G44: ThS Phan Huy Tâm | H44: ThS Phạm Chí Khoa | I44: 8h00 sáng thứ năm ngày 05/3/2026 | J44: B1.503 | K44: 03
A45: K224141673 | B45: Phạm Gia Linh | C45: K22414 | D45: PGS. TS Nguyễn Anh Phong | E45: TS Nguyễn Thanh Liêm | F45: TS Nguyễn Thanh Liêm | G45: TS Nguyễn Trung Hiếu | H45: ThS Ngô Phú Thanh | I45: 13h00 chiều thứ năm ngày 05/3/2026 | J45: B1.501 | K45: 04
A46: K224141677 | B46: Nguyễn Bùi Kim Ngân | C46: K22414 | D46: PGS. TS Nguyễn Anh Phong | E46: TS Nguyễn Trung Hiếu | F46: TS Nguyễn Thanh Liêm | G46: TS Nguyễn Trung Hiếu | H46: ThS Ngô Phú Thanh | I46: 13h00 chiều thứ năm ngày 05/3/2026 | J46: B1.501 | K46: 04
A47: K224040550 | B47: Nguyễn Thị Hải Tiên | C47: K22404 | D47: PGS. TS Phạm Thị Thanh Xuân
A48: K224040553 | B48: Lý Bảo Trân | C48: K22404 | D48: PGS. TS Phạm Thị Thanh Xuân
A49: K224040555 | B49: Nguyễn Trần Ngọc Trúc | C49: K22404 | D49: PGS. TS Phạm Thị Thanh Xuân
A50: K224040580 | B50: Vũ Thị Hồng Phúc | C50: K22404E | D50: PGS. TS Phạm Thị Thanh Xuân
A51: K224040581 | B51: Đoàn Hà Phương | C51: K22404E | D51: PGS. TS Phạm Thị Thanh Xuân
A52: K224141679 | B52: Trần Khánh Ngọc | C52: K22414 | D52: PGS. TS Nguyễn Anh Phong | E52: ThS Ngô Phú Thanh | F52: TS Nguyễn Thanh Liêm | G52: TS Nguyễn Trung Hiếu | H52: ThS Ngô Phú Thanh | I52: 13h00 chiều thứ năm ngày 05/3/2026 | J52: B1.501 | K52: 04
A53: K224141687 | B53: Hứa Nguyễn Như Quỳnh | C53: K22414 | D53: PGS. TS Nguyễn Anh Phong | E53: TS Nguyễn Thanh Liêm | F53: TS Nguyễn Thanh Liêm | G53: TS Nguyễn Trung Hiếu | H53: ThS Ngô Phú Thanh | I53: 13h00 chiều thứ năm ngày 05/3/2026 | J53: B1.501 | K53: 04
A54: K224141688 | B54: Mai Như Quỳnh | C54: K22414 | D54: PGS. TS Nguyễn Anh Phong | E54: TS Nguyễn Trung Hiếu | F54: TS Nguyễn Thanh Liêm | G54: TS Nguyễn Trung Hiếu | H54: ThS Ngô Phú Thanh | I54: 13h00 chiều thứ năm ngày 05/3/2026 | J54: B1.501 | K54: 04
A55: K224141737 | B55: Lê Vũ Minh Thông | C55: K22414E | D55: PGS. TS Phạm Thị Thanh Xuân | E55: ThS Ngô Phú Thanh | F55: TS Nguyễn Thanh Liêm | G55: TS Nguyễn Trung Hiếu | H55: ThS Ngô Phú Thanh | I55: 13h00 chiều thứ năm ngày 05/3/2026 | J55: B1.501 | K55: 04
A56: K224141743 | B56: Lê Việt Tố Uyên | C56: K22414E | D56: PGS. TS Phạm Thị Thanh Xuân | E56: TS Nguyễn Thanh Liêm | F56: TS Nguyễn Thanh Liêm | G56: TS Nguyễn Trung Hiếu | H56: ThS Ngô Phú Thanh | I56: 13h00 chiều thứ năm ngày 05/3/2026 | J56: B1.501 | K56: 04
A57: K224040556 | B57: Đinh Quang Tuấn | C57: K22404 | D57: PGS. TS Trần Hùng Sơn
A58: K224040558 | B58: Trần Thị Trúc Uyên | C58: K22404 | D58: PGS. TS Trần Hùng Sơn
A59: K224040560 | B59: Nguyễn Thị Hà Vy | C59: K22404 | D59: PGS. TS Trần Hùng Sơn
A60: K224040569 | B60: Phạm Thị Thu Hương | C60: K22404E | D60: PGS. TS Trần Hùng Sơn
A61: K224040587 | B61: Nguyễn Thị Minh Thư | C61: K22404E | D61: PGS. TS Trần Hùng Sơn
A62: K224040589 | B62: Hồ Nguyễn Anh Thy | C62: K22404E | D62: PGS. TS Trần Hùng Sơn
A63: K224141722 | B63: Nguyễn Thị Mai Hạnh | C63: K22414E | D63: TS Nguyễn Thôn Dã | E63: TS Nguyễn Trung Hiếu | F63: TS Nguyễn Thanh Liêm | G63: TS Nguyễn Trung Hiếu | H63: ThS Ngô Phú Thanh | I63: 13h00 chiều thứ năm ngày 05/3/2026 | J63: B1.501 | K63: 04
A64: K224141729 | B64: Trần Phương Nghi | C64: K22414E | D64: TS Nguyễn Thôn Dã | E64: ThS Ngô Phú Thanh | F64: TS Nguyễn Thanh Liêm | G64: TS Nguyễn Trung Hiếu | H64: ThS Ngô Phú Thanh | I64: 13h00 chiều thứ năm ngày 05/3/2026 | J64: B1.501 | K64: 04
A65: K224141740 | B65: Phạm Hoàng Ngọc Trang | C65: K22414E | D65: TS Nguyễn Thôn Dã | E65: TS Nguyễn Thanh Liêm | F65: TS Nguyễn Thanh Liêm | G65: TS Nguyễn Trung Hiếu | H65: ThS Ngô Phú Thanh | I65: 13h00 chiều thứ năm ngày 05/3/2026 | J65: B1.501 | K65: 04
A66: K224040483 | B66: Phan Thúy Ngân | C66: K22404 | D66: ThS Hồ Thị Hồng Minh
A67: K224040484 | B67: Trần Huỳnh Phương Nghi | C67: K22404 | D67: ThS Hồ Thị Hồng Minh
A68: K224040486 | B68: Hoàng Thị Huệ Nhi | C68: K22404 | D68: ThS Hồ Thị Hồng Minh
A69: K224040488 | B69: Nguyễn Thị Thanh Nhung | C69: K22404 | D69: ThS Hồ Thị Hồng Minh
A70: K224040492 | B70: Lê Mạnh Quân | C70: K22404 | D70: ThS Hồ Thị Hồng Minh
A71: K224040561 | B71: Hà Thị Lan Anh | C71: K22404E | D71: ThS Hồ Thị Hồng Minh
A72: K224040563 | B72: Nguyễn Hồng Ánh | C72: K22404E | D72: ThS Hồ Thị Hồng Minh
A73: K224040582 | B73: Phạm Thị Phương | C73: K22404E | D73: ThS Hồ Thị Hồng Minh
A74: K224040590 | B74: Nguyễn Ngọc Thiên Trang | C74: K22404E | D74: ThS Hồ Thị Hồng Minh
A75: K224040592 | B75: Nguyễn Hoài Tuyết Trân | C75: K22404E | D75: ThS Hồ Thị Hồng Minh
A76: K224141661 | B76: Nguyễn Hạo | C76: K22414 | D76: ThS Ngô Phú Thanh | E76: TS Nguyễn Thôn Dã | F76: PGS. TS Lê Đức Quang Tú | G76: TS Nguyễn Thôn Dã | H76: TS Võ Thị Ngọc Trinh | I76: 13h00 chiều thứ năm ngày 05/3/2026 | J76: B1.502 | K76: 05
A77: K224141665 | B77: Phan Thị Thu Huyền | C77: K22414 | D77: ThS Ngô Phú Thanh | E77: TS Võ Thị Ngọc Trinh | F77: PGS. TS Lê Đức Quang Tú | G77: TS Nguyễn Thôn Dã | H77: TS Võ Thị Ngọc Trinh | I77: 13h00 chiều thứ năm ngày 05/3/2026 | J77: B1.502 | K77: 05
A78: K224141671 | B78: Bùi Ngọc Thiên Kim | C78: K22414 | D78: ThS Ngô Phú Thanh | E78: PGS. TS Lê Đức Quang Tú | F78: PGS. TS Lê Đức Quang Tú | G78: TS Nguyễn Thôn Dã | H78: TS Võ Thị Ngọc Trinh | I78: 13h00 chiều thứ năm ngày 05/3/2026 | J78: B1.502 | K78: 05
A79: K224141674 | B79: Nguyễn Đồng Mạnh | C79: K22414 | D79: ThS Ngô Phú Thanh | E79: TS Nguyễn Thôn Dã | F79: PGS. TS Lê Đức Quang Tú | G79: TS Nguyễn Thôn Dã | H79: TS Võ Thị Ngọc Trinh | I79: 13h00 chiều thứ năm ngày 05/3/2026 | J79: B1.502 | K79: 05
A80: K224141676 | B80: Nguyễn Ngọc Kim Nga | C80: K22414 | D80: ThS Ngô Phú Thanh | E80: TS Võ Thị Ngọc Trinh | F80: PGS. TS Lê Đức Quang Tú | G80: TS Nguyễn Thôn Dã | H80: TS Võ Thị Ngọc Trinh | I80: 13h00 chiều thứ năm ngày 05/3/2026 | J80: B1.502 | K80: 05
A81: K224141723 | B81: Nguyễn Thị Ngọc Huyền | C81: K22414E | D81: ThS Phạm Chí Khoa | E81: PGS. TS Lê Đức Quang Tú | F81: PGS. TS Lê Đức Quang Tú | G81: TS Nguyễn Thôn Dã | H81: TS Võ Thị Ngọc Trinh | I81: 13h00 chiều thứ năm ngày 05/3/2026 | J81: B1.502 | K81: 05
A82: K224141660 | B82: Trần Bích Hà | C82: K22414 | D82: ThS Phan Huy Tâm | E82: PGS. TS Lê Đức Quang Tú | F82: PGS. TS Lê Đức Quang Tú | G82: TS Nguyễn Thôn Dã | H82: TS Võ Thị Ngọc Trinh | I82: 13h00 chiều thứ năm ngày 05/3/2026 | J82: B1.502 | K82: 05
A83: K224141662 | B83: Nguyễn Lâm Xuân Hân | C83: K22414 | D83: ThS Phan Huy Tâm | E83: TS Nguyễn Thôn Dã | F83: PGS. TS Lê Đức Quang Tú | G83: TS Nguyễn Thôn Dã | H83: TS Võ Thị Ngọc Trinh | I83: 13h00 chiều thứ năm ngày 05/3/2026 | J83: B1.502 | K83: 05
A84: K224141666 | B84: Trần Thị Thu Huỳnh | C84: K22414 | D84: ThS Phan Huy Tâm | E84: TS Võ Thị Ngọc Trinh | F84: PGS. TS Lê Đức Quang Tú | G84: TS Nguyễn Thôn Dã | H84: TS Võ Thị Ngọc Trinh | I84: 13h00 chiều thứ năm ngày 05/3/2026 | J84: B1.502 | K84: 05
A85: K224141669 | B85: Bùi Trung Kiên | C85: K22414 | D85: ThS Phan Huy Tâm | E85: PGS. TS Lê Đức Quang Tú | F85: PGS. TS Lê Đức Quang Tú | G85: TS Nguyễn Thôn Dã | H85: TS Võ Thị Ngọc Trinh | I85: 13h00 chiều thứ năm ngày 05/3/2026 | J85: B1.502 | K85: 05
A86: K224141670 | B86: Nguyễn Hữu Kiên | C86: K22414 | D86: ThS Phan Huy Tâm | E86: TS Nguyễn Thôn Dã | F86: PGS. TS Lê Đức Quang Tú | G86: TS Nguyễn Thôn Dã | H86: TS Võ Thị Ngọc Trinh | I86: 13h00 chiều thứ năm ngày 05/3/2026 | J86: B1.502 | K86: 05
A87: K224141718 | B87: Huỳnh Thị Mỹ Duyên | C87: K22414E | D87: PGS. TS Lê Đức Quang Tú | E87: PGS. TS Phạm Thị Thanh Xuân | F87: PGS. TS Phạm Thị Thanh Xuân | G87: ThS Phan Huy Tâm | H87: ThS Phạm Chí Khoa | I87: 13h00 chiều thứ năm ngày 05/3/2026 | J87: B1.503 | K87: 06
... A100: K224141689 | B100: Trần Ngọc Như Quỳnh | C100: K22414 | D100: ThS Ngô Phú Thanh | E100: PGS. TS Lê Đức Quang Tú | F100: PGS. TS Lê Đức Quang Tú | G100: TS Nguyễn Thanh Liêm | H100: PGS. TS Phạm Thị Thanh Xuân | I100: 8h00 sáng thứ sáu ngày 06/3/2026 | J100: B1.401 | K100: 07
A101: K204041141 | B101: Nguyễn Ngọc Hoàng | C101: K20404 | D101: ThS Nguyễn Thị Diễm Hiền
A102: K214041625 | B102: Nguyễn Hoàng Tuân | C102: K21404 | D102: ThS Nguyễn Thị Diễm Hiền
A103: K224040466 | B103: Nguyễn Đình Thiên Ân | C103: K22412 | D103: ThS Nguyễn Thị Diễm Hiền
A104: K224040467 | B104: Tô Gia Bảo | C104: K22412 | D104: ThS Nguyễn Thị Diễm Hiền
A105: K224040468 | B105: Phạm Mai Chi | C105: K22412 | D105: ThS Nguyễn Thị Diễm Hiền
A106: K224040478 | B106: Nguyễn Tuấn Kiệt | C106: K22412 | D106: ThS Nguyễn Thị Diễm Hiền
A107: K224040487 | B107: Nghiêm Thùy Yến Nhi | C107: K22412 | D107: ThS Nguyễn Thị Diễm Hiền
A108: K224040489 | B108: Thiều Thị Ngọc Oanh | C108: K22412 | D108: ThS Nguyễn Thị Diễm Hiền
A109: K224040490 | B109: Nguyễn Ngọc Châu Phương | C109: K22412 | D109: ThS Nguyễn Thị Diễm Hiền
A110: K224040491 | B110: Nguyễn Duy Phúc | C110: K22412 | D110: ThS Nguyễn Thị Diễm Hiền
A111: K224040495 | B111: Hà Huy Tân | C111: K22412 | D111: ThS Nguyễn Thị Diễm Hiền
A112: K224040501 | B112: Lê Thị Thủy Tiên | C112: K22412 | D112: ThS Nguyễn Thị Diễm Hiền
... A122: K224042347 | B122: Cheemeng Vangchiaxar | C122: K22412 | D122: ThS Nguyễn Thị Diễm Hiền
A123: K224141697 | B123: Lâm Chánh Tín | C123: K22414 | D123: ThS Ngô Phú Thanh | E123: TS Nguyễn Thanh Liêm | F123: PGS. TS Lê Đức Quang Tú | G123: TS Nguyễn Thanh Liêm | H123: PGS. TS Phạm Thị Thanh Xuân | I123: 8h00 sáng thứ sáu ngày 06/3/2026 | J123: B1.401 | K123: 07
A124: K224141692 | B124: Nguyễn Thị Ngọc Thanh | C124: K22414 | D124: ThS Ngô Phú Thanh | E124: PGS. TS Lê Đức Quang Tú | F124: PGS. TS Lê Đức Quang Tú | G124: TS Nguyễn Thanh Liêm | H124: PGS. TS Phạm Thị Thanh Xuân | I124: 8h00 sáng thứ sáu ngày 06/3/2026 | J124: B1.401 | K124: 07
A125: K224141672 | B125: Phan Ánh Linh | C125: K22414 | D125: ThS Phan Huy Tâm | E125: PGS. TS Phạm Thị Thanh Xuân | F125: PGS. TS Lê Đức Quang Tú | G125: TS Nguyễn Thanh Liêm | H125: PGS. TS Phạm Thị Thanh Xuân | I125: 8h00 sáng thứ sáu ngày 06/3/2026 | J125: B1.401 | K125: 07
A126: K224040464 | B126: Phạm Vũ Tú Anh | C126: K22412 | D126: ThS Nguyễn Thị Hai Hằng
A127: K224040469 | B127: Nguyễn Thị Thúy Diễm | C127: K22412 | D127: ThS Nguyễn Thị Hai Hằng
A128: K224040482 | B128: Dương Công Nam | C128: K22412 | D128: ThS Nguyễn Thị Hai Hằng
A129: K224040485 | B129: Triệu Hoàng Kim Nguyên | C129: K22412 | D129: ThS Nguyễn Thị Hai Hằng
A130: K224040494 | B130: Huỳnh Thị Thanh Tâm | C130: K22412 | D130: ThS Nguyễn Thị Hai Hằng
A131: K224040497 | B131: Phan Như Thành | C131: K22412 | D131: ThS Nguyễn Thị Hai Hằng
A132: K224040498 | B132: Lê Hưng Thịnh | C132: K22404 | D132: ThS Nguyễn Thị Hai Hằng
...

Sheet Sheet5
A1: MSSV | B1: Họ tên | C1: Ngày sinh | D1: Mobile Phone | E1: Email | F1: CTĐT | G1: Tên CTĐT | H1: Tình trạng | I1: Điều kiện CCNN | J1: Số TC tích lũy | K1: ĐTBCTL | L1: Xếp loại tích lũy
A2: K224020262 | B2: Nguyễn Đặng Vi Bân | C2: 15/02/2004 | D2: 767551049 | E2: banndv224022c@st.uel.edu.vn | F2: 404C | G2: Tài chính - Ngân hàng Chất lượng cao | H2: Còn học | I2: Đạt CCNN | J2: 124 | K2: 8.6 | L2: Giỏi
A3: K224040464 | B3: Phạm Vũ Tú Anh | C3: 38175 | D3: 858485811 | E3: anhpvt22404a@st.uel.edu.vn | F3: 412 | G3: Ngân hàng | H3: Còn học | I3: Đạt CCNN | J3: 124 | K3: 8.51 | L3: Giỏi
A4: K224040465 | B4: Trương Thị Nhã Ái | C4: 16/04/2004 | D4: 943865399 | E4: aittn22404a@st.uel.edu.vn | F4: 404 | G4: Tài chính - Ngân hàng | H4: Còn học | I4: Đạt CCNN | J4: 128 | K4: 8.51 | L4: Giỏi
A5: K224040466 | B5: Nguyễn Đình Thiên Ân | C5: 16/07/2004 | D5: 816109429 | E5: anndt22404a@st.uel.edu.vn | F5: 412 | G5: Ngân hàng | H5: Còn học | I5: Đạt CCNN | J5: 121 | K5: 7.4 | L5: Khá
A6: K224040467 | B6: Tô Gia Bảo | C6: 38332 | D6: 911789147 | E6: baotg22404a@st.uel.edu.vn | F6: 412 | G6: Ngân hàng | H6: Còn học | I6: Đạt CCNN | J6: 124 | K6: 7.24 | L6: Khá
A7: K224040468 | B7: Phạm Mai Chi | C7: 38201 | D7: 862209865 | E7: chipm22404a@st.uel.edu.vn | F7: 412 | G7: Ngân hàng | H7: Còn học | I7: Đạt CCNN | J7: 124 | K7: 7.36 | L7: Khá
A8: K224040469 | B8: Nguyễn Thị Thúy Diễm | C8: 15/10/2004 | D8: 949271804 | E8: diemntt22404a@st.uel.edu.vn | F8: 412 | G8: Ngân hàng | H8: Còn học | I8: Đạt CCNN | J8: 124 | K8: 7.99 | L8: Khá
A9: K224040470 | B9: Đào Hồ Trúc Giang | C9: 38027 | E9: giangdht22404a@st.uel.edu.vn | F9: 404 | G9: Tài chính - Ngân hàng | H9: Còn học | I9: Đạt CCNN | J9: 122 | K9: 8.25 | L9: Giỏi
A10: K224040471 | B10: Nguyễn Thị Thu Hà | C10: 24/01/2004 | D10: 835484304 | E10: hantt22404a@st.uel.edu.vn | F10: 404 | G10: Tài chính - Ngân hàng | H10: Còn học | I10: Đạt CCNN | J10: 126 | K10: 8.46 | L10: Giỏi
A11: K224040472 | B11: Võ Thị Hồng Hạnh | C11: 25/12/2004 | D11: 794563867 | E11: hanhvth22404a@st.uel.edu.vn | F11: 404 | G11: Tài chính - Ngân hàng | H11: Còn học | I11: Đạt CCNN | J11: 126 | K11: 8.09 | L11: Giỏi
A12: K224040473 | B12: Trần Thị Thu Hằng | C12: 37842 | D12: 363954822 | E12: hangttt22404a@st.uel.edu.vn | F12: 404 | G12: Tài chính - Ngân hàng | H12: Còn học | I12: Đạt CCNN | J12: 126 | K12: 8.05 | L12: Giỏi
A13: K224040474 | B13: Phan Thanh Thanh Hiền | C13: 38328 | E13: hienptt22404a@st.uel.edu.vn | F13: 404 | G13: Tài chính - Ngân hàng | H13: Còn học | I13: Đạt CCNN | J13: 126 | K13: 7.96 | L13: Khá
A14: K224040475 | B14: Lý Nhật Huy | C14: 36861 | E14: huyln22404a@st.uel.edu.vn | F14: 404 | G14: Tài chính - Ngân hàng | H14: Còn học | I14: Đạt CCNN | J14: 126 | K14: 7.69 | L14: Khá
A15: K224040476 | B15: Lê Huỳnh Khánh Huyền | C15: 30/04/2004 | D15: 901669495 | E15: huyenlhk22404a@st.uel.edu.vn | F15: 404 | G15: Tài chính - Ngân hàng | H15: Còn học | I15: Đạt CCNN | J15: 126 | K15: 8.29 | L15: Giỏi
A16: K224040477 | B16: Nguyễn Trần Vũ Hùng | C16: 31/07/2004 | D16: 867050070 | E16: hungntv22404a@st.uel.edu.vn | F16: 404 | G16: Tài chính - Ngân hàng | H16: Còn học | I16: Đạt CCNN | J16: 126 | K16: 8.49 | L16: Giỏi
A17: K224040478 | B17: Nguyễn Tuấn Kiệt | C17: 38267 | D17: 394377963 | E17: kietnt22404a@st.uel.edu.vn | F17: 412 | G17: Ngân hàng | H17: Còn học | I17: Đạt CCNN | J17: 124 | K17: 7.06 | L17: Khá
A18: K224040479 | B18: Nguyễn Thị Hạnh Linh | C18: 27/11/2004 | D18: 787300568 | E18: linhnth22404a@st.uel.edu.vn | F18: 404 | G18: Tài chính - Ngân hàng | H18: Còn học | I18: Đạt CCNN | J18: 126 | K18: 8.12 | L18: Giỏi
A19: K224040480 | B19: Hồ Thị Bích Ly | C19: 13/08/2004 | E19: lyhtb22404a@st.uel.edu.vn | F19: 404 | G19: Tài chính - Ngân hàng | H19: Còn học | I19: Đạt CCNN | J19: 124 | K19: 8.41 | L19: Giỏi
A20: K224040481 | B20: Vũ Nhật Minh | C20: 38087 | D20: 768658405 | E20: minhvn22404a@st.uel.edu.vn | F20: 404 | G20: Tài chính - Ngân hàng | H20: Còn học | I20: Đạt CCNN | J20: 122 | K20: 8.98 | L20: Giỏi
A21: K224040482 | B21: Dương Công Nam | C21: 29/05/2003 | D21: 931969308 | E21: namdc22404a@st.uel.edu.vn | F21: 412 | G21: Ngân hàng | H21: Còn học | I21: Đạt CCNN | J21: 124 | K21: 7.41 | L21: Khá
A22: K224040483 | B22: Phan Thúy Ngân | C22: 38111 | D22: 839257952 | E22: nganpt22404a@st.uel.edu.vn | F22: 404 | G22: Tài chính - Ngân hàng | H22: Còn học | I22: Đạt CCNN | J22: 126 | K22: 8.39 | L22: Giỏi
A23: K224040484 | B23: Trần Huỳnh Phương Nghi | C23: 26/10/2004 | D23: 918276265 | E23: nghithp22404a@st.uel.edu.vn | F23: 404 | G23: Tài chính - Ngân hàng | H23: Còn học | I23: Đạt CCNN | J23: 126 | K23: 8.61 | L23: Giỏi
A24: K224040485 | B24: Triệu Hoàng Kim Nguyên | C24: 15/06/2004 | D24: 589103713 | E24: nguyenthk22404a@st.uel.edu.vn | F24: 412 | G24: Ngân hàng | H24: Còn học | I24: Chưa đạt CCNN | J24: 124 | K24: 7.51 | L24: Khá
A25: K224040486 | B25: Hoàng Thị Huệ Nhi | C25: 25/12/2004 | D25: 852955447 | E25: nhihth22404a@st.uel.edu.vn | F25: 404 | G25: Tài chính - Ngân hàng | H25: Còn học | I25: Đạt CCNN | J25: 130 | K25: 7.72 | L25: Khá
A26: K224040487 | B26: Nghiêm Thùy Yến Nhi | C26: 16/05/2004 | D26: 867573703 | E26: nhinty22404a@st.uel.edu.vn | F26: 412 | G26: Ngân hàng | H26: Còn học | I26: Đạt CCNN | J26: 124 | K26: 7.62 | L26: Khá
A27: K224040488 | B27: Nguyễn Thị Thanh Nhung | C27: 28/04/2004 | E27: nhungntt22404a@st.uel.edu.vn | F27: 404 | G27: Tài chính - Ngân hàng | H27: Còn học | I27: Đạt CCNN | J27: 126 | K27: 8.64 | L27: Giỏi
A28: K224040489 | B28: Thiều Thị Ngọc Oanh | C28: 30/12/2004 | D28: 933979864 | E28: oanhttn22404a@st.uel.edu.vn | F28: 412 | G28: Ngân hàng | H28: Còn học | I28: Đạt CCNN | J28: 124 | K28: 8.18 | L28: Giỏi
A29: K224040490 | B29: Nguyễn Ngọc Châu Phương | C29: 38085 | E29: phuongnnc22404a@st.uel.edu.vn | F29: 412 | G29: Ngân hàng | H29: Còn học | I29: Đạt CCNN | J29: 124 | K29: 7.86 | L29: Khá
A30: K224040491 | B30: Nguyễn Duy Phúc | C30: 38271 | E30: phucnd22404a@st.uel.edu.vn | F30: 412 | G30: Ngân hàng | H30: Còn học | I30: Đạt CCNN | J30: 124 | K30: 8.09 | L30: Giỏi
A31: K224040492 | B31: Lê Mạnh Quân | C31: 17/10/2004 | D31: 397569520 | E31: quanlm22404a@st.uel.edu.vn | F31: 404 | G31: Tài chính - Ngân hàng | H31: Còn học | I31: Đạt CCNN | J31: 126 | K31: 8.3 | L31: Giỏi
A32: K224040493 | B32: Nguyễn Ngọc Quỳnh | C32: 20/08/2004 | D32: 949866704 | E32: quynhnn22404a@st.uel.edu.vn | F32: 404 | G32: Tài chính - Ngân hàng | H32: Còn học | I32: Đạt CCNN | J32: 122 | K32: 7.84 | L32: Khá
A33: K224040494 | B33: Huỳnh Thị Thanh Tâm | C33: 28/01/2003 | D33: 345998367 | E33: tamhtt22404a@st.uel.edu.vn | F33: 412 | G33: Ngân hàng | H33: Còn học | I33: Đạt CCNN | J33: 124 | K33: 7.51 | L33: Khá
A34: K224040495 | B34: Hà Huy Tân | C34: 15/08/2004 | D34: 902156726 | E34: tanhh22404a@st.uel.edu.vn | F34: 412 | G34: Ngân hàng | H34: Còn học | I34: Đạt CCNN | J34: 124 | K34: 7.45 | L34: Khá
A35: K224040496 | B35: Mai Công Thanh | C35: 38295 | D35: 372539123 | E35: thanhmc22404a@st.uel.edu.vn | F35: 404 | G35: Tài chính - Ngân hàng | H35: Còn học | I35: Đạt CCNN | J35: 122 | K35: 8.21 | L35: Giỏi
A36: K224040496 | B36: Mai Công Thanh | C36: 38295 | D36: 372539123 | E36: thanhmc22404a@st.uel.edu.vn | F36: 406 | G36: Hệ thống thông tin quản lý | H36: Còn học | I36: Đạt CCNN | J36: 120 | K36: 8.27 | L36: Giỏi
A37: K224040497 | B37: Phan Như Thành | C37: 21/04/2004 | E37: thanhpn22404a@st.uel.edu.vn | F37: 412 | G37: Ngân hàng | H37: Còn học | I37: Chưa đạt CCNN | J37: 121 | K37: 6.92 | L37: Trung bình khá
A38: K224040498 | B38: Lê Hưng Thịnh | C38: 38265 | D38: 912161571 | E38: thinhlh22404a@st.uel.edu.vn | F38: 404 | G38: Tài chính - Ngân hàng | H38: Còn học | I38: Đạt CCNN | J38: 126 | K38: 7.77 | L38: Khá
A39: K224040499 | B39: Bùi Anh Thư | C39: 20/08/2004 | E39: thuba22404a@st.uel.edu.vn | F39: 404 | G39: Tài chính - Ngân hàng | H39: Còn học | I39: Đạt CCNN | J39: 126 | K39: 7.93 | L39: Khá
A40: K224040500 | B40: Nguyễn Thị Thương | C40: 38058 | D40: 357501455 | E40: thuongnt22404a@st.uel.edu.vn | F40: 404 | G40: Tài chính - Ngân hàng | H40: Còn học | I40: Đạt CCNN | J40: 126 | K40: 7.81 | L40: Khá
A41: K224040501 | B41: Lê Thị Thủy Tiên | C41: 13/08/2004 | D41: 971341872 | E41: tienltt22404a@st.uel.edu.vn | F41: 412 | G41: Ngân hàng | H41: Còn học | I41: Đạt CCNN | J41: 124 | K41: 7.52 | L41: Khá
A42: K224040502 | B42: Nguyễn Thủy Tiên | C42: 38242 | E42: tiennt22404a@st.uel.edu.vn | F42: 404 | G42: Tài chính - Ngân hàng | H42: Còn học | I42: Đạt CCNN | J42: 126 | K42: 7.76 | L42: Khá
A43: K224040503 | B43: Nguyễn Thị Huyền Trang | C43: 13/02/2004 | D43: 869130247 | E43: trangnth22404a@st.uel.edu.vn | F43: 404 | G43: Tài chính - Ngân hàng | H43: Còn học | I43: Đạt CCNN | J43: 122 | K43: 8.32 | L43: Giỏi
A44: K224040504 | B44: Hồ Thị Ngọc Trâm | C44: 25/05/2004 | D44: 363234680 | E44: tramhtn22404a@st.uel.edu.vn | F44: 404 | G44: Tài chính - Ngân hàng | H44: Còn học | I44: Đạt CCNN | J44: 126 | K44: 8.17 | L44: Giỏi
A45: K224040505 | B45: Nguyễn Ngọc Huyền Trân | C45: 37987 | D45: 388654010 | E45: trannnh22404a@st.uel.edu.vn | F45: 412 | G45: Ngân hàng | H45: Còn học | I45: Đạt CCNN | J45: 124 | K45: 7.79 | L45: Khá
A46: K224040506 | B46: Nguyễn Thanh Trúc | C46: 14/01/2004 | D46: 392192023 | E46: trucnt22404a@st.uel.edu.vn | F46: 404 | G46: Tài chính - Ngân hàng | H46: Còn học | I46: Đạt CCNN | J46: 126 | K46: 8.22 | L46: Giỏi
A47: K224040507 | B47: Phạm Thị Thanh Trúc | C47: 26/04/2004 | D47: 945802361 | E47: trucptt22404a@st.uel.edu.vn | F47: 404 | G47: Tài chính - Ngân hàng | H47: Còn học | I47: Đạt CCNN | J47: 126 | K47: 8.46 | L47: Giỏi
A48: K224040508 | B48: Trần Anh Tuấn | C48: 38111 | D48: 984244204 | E48: tuanta22404a@st.uel.edu.vn | F48: 412 | G48: Ngân hàng | H48: Còn học | I48: Chưa đạt CCNN | J48: 71 | K48: 6.75 | L48: Trung bình khá
A49: K224040509 | B49: Phan Ngọc Khánh Uyên | C49: 38147 | D49: 944387099 | E49: uyenpnk22404a@st.uel.edu.vn | F49: 412 | G49: Ngân hàng | H49: Còn học | I49: Đạt CCNN | J49: 124 | K49: 6.76 | L49: Trung bình khá
A50: K224040510 | B50: Lê Trịnh Thảo Vi | C50: 21/05/2004 | D50: 702727079 | E50: viltt22404a@st.uel.edu.vn | F50: 412 | G50: Ngân hàng | H50: Còn học | I50: Đạt CCNN | J50: 124 | K50: 7.13 | L50: Khá
A51: K224040511 | B51: Đỗ Thanh Viên | C51: 14/10/2004 | D51: 386144087 | E51: viendt22404a@st.uel.edu.vn | F51: 404 | G51: Tài chính - Ngân hàng | H51: Còn học | I51: Đạt CCNN | J51: 132 | K51: 8.39 | L51: Giỏi
A52: K224040512 | B52: Nguyễn Tường Vy | C52: 28/03/2004 | D52: 384987847 | E52: vynt22404a@st.uel.edu.vn | F52: 412 | G52: Ngân hàng | H52: Còn học | I52: Đạt CCNN | J52: 124 | K52: 8.1 | L52: Giỏi
A53: K224040513 | B53: Nguyễn Vân An | C53: 29/07/2004 | D53: 886210240 | E53: annv22404b@st.uel.edu.vn | F53: 404 | G53: Tài chính - Ngân hàng | H53: Còn học | I53: Đạt CCNN | J53: 126 | K53: 8.87 | L53: Giỏi
A54: K224040515 | B54: Nguyễn Phạm Ngọc Ánh | C54: 38300 | E54: anhnpn22404b@st.uel.edu.vn | F54: 404 | G54: Tài chính - Ngân hàng | H54: Còn học | I54: Đạt CCNN | J54: 123 | K54: 8.19 | L54: Giỏi
A55: K224040516 | B55: Lương Thanh Bi | C55: 38297 | D55: 764872956 | E55: bilt22404b@st.uel.edu.vn | F55: 404 | G55: Tài chính - Ngân hàng | H55: Còn học | I55: Đạt CCNN | J55: 130 | K55: 8.66 | L55: Giỏi
A56: K224040518 | B56: Nguyễn Triệu Duy | C56: 28/01/2003 | D56: 969224240 | E56: duynt22404b@st.uel.edu.vn | F56: 404 | G56: Tài chính - Ngân hàng | H56: Còn học | I56: Đạt CCNN | J56: 126 | K56: 7.53 | L56: Khá
A57: K224040519 | B57: Hoàng Thị Đông Hà | C57: 13/03/2003 | E57: hahtd22404b@st.uel.edu.vn | F57: 412 | G57: Ngân hàng | H57: Còn học | I57: Đạt CCNN | J57: 124 | K57: 7.35 | L57: Khá
A58: K224040520 | B58: Phan Thị Mỹ Hạnh | C58: 31/10/2004 | D58: 943760557 | E58: hanhptm22404b@st.uel.edu.vn | F58: 404 | G58: Tài chính - Ngân hàng | H58: Còn học | I58: Đạt CCNN | J58: 126 | K58: 7.92 | L58: Khá
A59: K224040521 | B59: Nguyễn Huy Thu Hằng | C59: 16/03/2004 | D59: 833867216 | E59: hangnht22404b@st.uel.edu.vn | F59: 404 | G59: Tài chính - Ngân hàng | H59: Còn học | I59: Đạt CCNN | J59: 126 | K59: 7.74 | L59: Khá
A60: K224040522 | B60: Đỗ Thu Hiền | C60: 20/10/2004 | E60: hiendt22404b@st.uel.edu.vn | F60: 412 | G60: Ngân hàng | H60: Còn học | I60: Đạt CCNN | J60: 124 | K60: 7.36 | L60: Khá
A61: K224040523 | B61: Phí Nhật Hoàng | C61: 15/10/2004 | D61: 866484704 | E61: hoangpn22404b@st.uel.edu.vn | F61: 412 | G61: Ngân hàng | H61: Còn học | I61: Đạt CCNN | J61: 126 | K61: 8 | L61: Giỏi
A62: K224040524 | B62: Võ Bảo Huy | C62: 15/03/2004 | D62: 339632366 | E62: huyvb22404b@st.uel.edu.vn | F62: 404 | G62: Tài chính - Ngân hàng | H62: Còn học | I62: Đạt CCNN | J62: 122 | K62: 8.4 | L62: Giỏi
A63: K224040525 | B63: Nguyễn Đỗ Thiên Hương | C63: 37987 | E63: huongndt22404b@st.uel.edu.vn | F63: 412 | G63: Ngân hàng | H63: Còn học | I63: Đạt CCNN | J63: 124 | K63: 8.19 | L63: Giỏi
A64: K224040526 | B64: Nguyễn Công Minh Khôi | C64: 30/03/2004 | D64: 365906961 | E64: khoincm22404b@st.uel.edu.vn | F64: 404 | G64: Tài chính - Ngân hàng | H64: Còn học | I64: Đạt CCNN | J64: 126 | K64: 8.19 | L64: Giỏi
A65: K224040527 | B65: Chu Thị Mỹ Linh | C65: 31/08/2004 | D65: 349196118 | E65: linhctm22404b@st.uel.edu.vn | F65: 412 | G65: Ngân hàng | H65: Còn học | I65: Đạt CCNN | J65: 116 | K65: 6.94 | L65: Trung bình khá
A66: K224040528 | B66: Trần Nhật Linh | C66: 38299 | D66: 975913654 | E66: linhtn22404b@st.uel.edu.vn | F66: 412 | G66: Ngân hàng | H66: Còn học | I66: Chưa đạt CCNN | J66: 112 | K66: 7.49 | L66: Khá
A67: K224040529 | B67: Hà Xuân Mai | C67: 38118 | D67: 799173732 | E67: maihx22404b@st.uel.edu.vn | F67: 404 | G67: Tài chính - Ngân hàng | H67: Còn học | I67: Đạt CCNN | J67: 126 | K67: 8.53 | L67: Giỏi
A68: K224040531 | B68: Lê Bảo Ngân | C68: 38082 | D68: 915932451 | E68: nganlb22404b@st.uel.edu.vn | F68: 412 | G68: Ngân hàng | H68: Còn học | I68: Chưa đạt CCNN | J68: 126 | K68: 7.81 | L68: Khá
A69: K224040532 | B69: Trương Ngọc Kiều Ngân | C69: 14/06/2004 | D69: 964781138 | E69: ngantnk22404b@st.uel.edu.vn | F69: 412 | G69: Ngân hàng | H69: Còn học | I69: Đạt CCNN | J69: 120 | K69: 8.34 | L69: Giỏi
A70: K224040533 | B70: Lê Hà Bảo Ngọc | C70: 37994 | D70: 349570679 | E70: ngoclhb22404b@st.uel.edu.vn | F70: 412 | G70: Ngân hàng | H70: Còn học | I70: Đạt CCNN | J70: 122 | K70: 6.78 | L70: Trung bình khá
A71: K224040534 | B71: Nguyễn Trần Ái Nguyệt | C71: 15/02/2004 | E71: nguyetnta22404b@st.uel.edu.vn | F71: 404 | G71: Tài chính - Ngân hàng | H71: Còn học | I71: Đạt CCNN | J71: 126 | K71: 8.62 | L71: Giỏi
A72: K224040535 | B72: Lê Thị Kiều Nhi | C72: 25/08/2004 | D72: 869340316 | E72: nhiltk22404b@st.uel.edu.vn | F72: 404 | G72: Tài chính - Ngân hàng | H72: Còn học | I72: Đạt CCNN | J72: 126 | K72: 7.77 | L72: Khá
A73: K224040536 | B73: Nguyễn Thị Yến Nhi | C73: 38301 | D73: 396574906 | E73: nhinty22404b@st.uel.edu.vn | F73: 404 | G73: Tài chính - Ngân hàng | H73: Còn học | I73: Đạt CCNN | J73: 122 | K73: 9.12 | L73: Xuất sắc
A74: K224040537 | B74: Đặng Kiều Oanh | C74: 38148 | D74: 972904610 | E74: oanhdk22404b@st.uel.edu.vn | F74: 404 | G74: Tài chính - Ngân hàng | H74: Còn học | I74: Đạt CCNN | J74: 126 | K74: 8.61 | L74: Giỏi
A75: K224040538 | B75: Trần Nhất Phong | C75: 17/09/2004 | D75: 968463550 | E75: phongtn22404b@st.uel.edu.vn | F75: 404 | G75: Tài chính - Ngân hàng | H75: Còn học | I75: Đạt CCNN | J75: 127 | K75: 7.61 | L75: Khá
A76: K224040539 | B76: Võ Trường Phúc | C76: 38083 | D76: 394247075 | E76: phucvt22404b@st.uel.edu.vn | F76: 404 | G76: Tài chính - Ngân hàng | H76: Còn học | I76: Đạt CCNN | J76: 122 | K76: 8.17 | L76: Giỏi
A77: K224040541 | B77: Lâm Hồng Minh Quân | C77: 30/05/2004 | D77: 931314605 | E77: quanlhm22404b@st.uel.edu.vn | F77: 404 | G77: Tài chính - Ngân hàng | H77: Còn học | I77: Chưa đạt CCNN | J77: 107 | K77: 8.22 | L77: Giỏi
A78: K224040542 | B78: Phạm Thanh Tài | C78: 38231 | D78: 376618542 | E78: taipt22404b@st.uel.edu.vn | F78: 404 | G78: Tài chính - Ngân hàng | H78: Còn học | I78: Đạt CCNN | J78: 122 | K78: 8.01 | L78: Giỏi
A79: K224040543 | B79: Nguyễn Thị Minh Tâm | C79: 28/09/2004 | D79: 386280904 | E79: tamntm22404b@st.uel.edu.vn | F79: 404 | G79: Tài chính - Ngân hàng | H79: Còn học | I79: Đạt CCNN | J79: 130 | K79: 8.59 | L79: Giỏi
A80: K224040544 | B80: Nguyễn Tấn Thành | C80: 38298 | E80: thanhnt22404b@st.uel.edu.vn | F80: 404 | G80: Tài chính - Ngân hàng | H80: Còn học | I80: Đạt CCNN | J80: 128 | K80: 7.99 | L80: Khá
A81: K224040545 | B81: Huỳnh Thị Thanh Thảo | C81: 14/11/2004 | D81: 931537156 | E81: thaohtt22404b@st.uel.edu.vn | F81: 404 | G81: Tài chính - Ngân hàng | H81: Còn học | I81: Đạt CCNN | J81: 122 | K81: 8.86 | L81: Giỏi
A82: K224040546 | B82: Hàng Quốc Thắng | C82: 14/10/2004 | E82: thanghq22404b@st.uel.edu.vn | F82: 404 | G82: Tài chính - Ngân hàng | H82: Còn học | I82: Chưa đạt CCNN | J82: 126 | K82: 7.92 | L82: Khá
A83: K224040547 | B83: Đỗ Trần Hồng Thơ | C83: 20/09/2004 | D83: 794918989 | E83: thodth22404b@st.uel.edu.vn | F83: 404 | G83: Tài chính - Ngân hàng | H83: Còn học | I83: Đạt CCNN | J83: 126 | K83: 8.59 | L83: Giỏi
A84: K224040548 | B84: Lê Hoàng Như Thủy | C84: 38240 | D84: 913665611 | E84: thuylhn22404b@st.uel.edu.vn | F84: 404 | G84: Tài chính - Ngân hàng | H84: Còn học | I84: Đạt CCNN | J84: 126 | K84: 8.48 | L84: Giỏi
A85: K224040549 | B85: Nguyễn Ngọc Anh Thư | C85: 38150 | E85: thunna22404b@st.uel.edu.vn | F85: 404 | G85: Tài chính - Ngân hàng | H85: Còn học | I85: Đạt CCNN | J85: 126 | K85: 8.38 | L85: Giỏi
A86: K224040550 | B86: Nguyễn Thị Hải Tiên | C86: 15/09/2004 | D86: 375838772 | E86: tiennth22404b@st.uel.edu.vn | F86: 404 | G86: Tài chính - Ngân hàng | H86: Còn học | I86: Đạt CCNN | J86: 126 | K86: 8.73 | L86: Giỏi
A87: K224040551 | B87: Ngô Minh Tiến | C87: 30/06/2004 | D87: 397803341 | E87: tiennm22404b@st.uel.edu.vn | F87: 404 | G87: Tài chính - Ngân hàng | H87: Còn học | I87: Đạt CCNN | J87: 124 | K87: 8.76 | L87: Giỏi
A88: K224040552 | B88: Huỳnh Mai Huyền Trang | C88: 22/08/2003 | D88: 974159819 | E88: tranghmh22404b@st.uel.edu.vn | F88: 412 | G88: Ngân hàng | H88: Còn học | I88: Đạt CCNN | J88: 124 | K88: 7.71 | L88: Khá
A89: K224040553 | B89: Lý Bảo Trân | C89: 24/05/2004 | D89: 977938908 | E89: tranlb22404b@st.uel.edu.vn | F89: 404 | G89: Tài chính - Ngân hàng | H89: Còn học | I89: Đạt CCNN | J89: 125 | K89: 8.6 | L89: Giỏi
A90: K224040554 | B90: Lê Thanh Trúc | C90: 15/01/2004 | D90: 396788267 | E90: truclt22404b@st.uel.edu.vn | F90: 412 | G90: Ngân hàng | H90: Còn học | I90: Chưa đạt CCNN | J90: 124 | K90: 7.08 | L90: Khá
A91: K224040555 | B91: Nguyễn Trần Ngọc Trúc | C91: 23/09/2004 | D91: 335358287 | E91: trucntn22404b@st.uel.edu.vn | F91: 404 | G91: Tài chính - Ngân hàng | H91: Còn học | I91: Đạt CCNN | J91: 126 | K91: 8.03 | L91: Giỏi
A92: K224040556 | B92: Đinh Quang Tuấn | C92: 14/09/2004 | D92: 332366956 | E92: tuandq22404b@st.uel.edu.vn | F92: 404 | G92: Tài chính - Ngân hàng | H92: Còn học | I92: Đạt CCNN | J92: 126 | K92: 8.43 | L92: Giỏi
A93: K224040557 | B93: Nguyễn Văn Tuyên | C93: 20/09/2004 | E93: tuyennv22404b@st.uel.edu.vn | F93: 412 | G93: Ngân hàng | H93: Còn học | I93: Đạt CCNN | J93: 126 | K93: 7.96 | L93: Khá
A94: K224040558 | B94: Trần Thị Trúc Uyên | C94: 23/01/2004 | D94: 908740992 | E94: uyenttt22404b@st.uel.edu.vn | F94: 404 | G94: Tài chính - Ngân hàng | H94: Còn học | I94: Chưa đạt CCNN | J94: 126 | K94: 7.6 | L94: Khá
A95: K224040559 | B95: Vũ Hoàng Vi | C95: 38173 | D95: 925479681 | E95: vivh22404b@st.uel.edu.vn | F95: 412 | G95: Ngân hàng | H95: Còn học | I95: Đạt CCNN | J95: 124 | K95: 7.6 | L95: Khá
A96: K224040560 | B96: Nguyễn Thị Hà Vy | C96: 38025 | D96: 867129325 | E96: vynth22404b@st.uel.edu.vn | F96: 404 | G96: Tài chính - Ngân hàng | H96: Còn học | I96: Đạt CCNN | J96: 123 | K96: 7.22 | L96: Khá
A97: K224040561 | B97: Hà Thị Lan Anh | C97: 14/09/2003 | D97: 899386831 | E97: anhhtl22404c@st.uel.edu.vn | F97: 404C | G97: Tài chính - Ngân hàng Chất lượng cao | H97: Còn học | I97: Đạt CCNN | J97: 124 | K97: 7.94 | L97: Khá
A98: K224040562 | B98: Nguyễn Đức Anh | C98: 31/08/2004 | D98: 937328308 | E98: anhnd22404c@st.uel.edu.vn | F98: 404C | G98: Tài chính - Ngân hàng Chất lượng cao | H98: Còn học | I98: Đạt CCNN | J98: 122 | K98: 8.42 | L98: Giỏi
A99: K224040563 | B99: Nguyễn Hồng Ánh | C99: 14/10/2000 | D99: 962173620 | E99: anhnh22404c@st.uel.edu.vn | F99: 404C | G99: Tài chính - Ngân hàng Chất lượng cao | H99: Còn học | I99: Đạt CCNN | J99: 124 | K99: 8.1 | L99: Giỏi
A100: K224040564 | B100: Nguyễn Vũ Bình | C100: 16/10/2004 | D100: 373746180 | E100: binhnv22404c@st.uel.edu.vn | F100: 404C | G100: Tài chính - Ngân hàng Chất lượng cao | H100: Còn học | I100: Đạt CCNN | J100: 122 | K100: 8.33 | L100: Giỏi
...

Sheet Số bài mỗi hội đồng
B1: Hội đồng | C1: Số lượng
A2: 414, 414C | B2: 1 | C2: =COUNTIF('Phân công'!#REF!,B2) -> #REF!
A3: 414, 414C | B3: 2 | C3: =COUNTIF('Phân công'!#REF!,B3) -> #REF!
A4: 414, 414C | B4: 3 | C4: =COUNTIF('Phân công'!#REF!,B4) -> #REF!
A5: 414, 414C | B5: 4 | C5: =COUNTIF('Phân công'!#REF!,B5) -> #REF!
A6: 414, 414C | B6: 5 | C6: =COUNTIF('Phân công'!#REF!,B6) -> #REF!
A7: 414, 414C | B7: 6 | C7: =COUNTIF('Phân công'!#REF!,B7) -> #REF!
A8: 414, 414C | B8: 7 | C8: =COUNTIF('Phân công'!#REF!,B8) -> #REF!
A9: 414, 414C | B9: 8 | C9: =COUNTIF('Phân công'!#REF!,B9) -> #REF!
A10: 404C | B10: 9 | C10: =COUNTIF('Phân công'!#REF!,B10) -> #REF!
A11: Đại trà | B11: 10 | C11: =COUNTIF('Phân công'!#REF!,B11) -> #REF!
A12: CA | B12: 11 | C12: =COUNTIF('Phân công'!#REF!,B12) -> #REF!
A13: CA | B13: 12 | C13: =COUNTIF('Phân công'!#REF!,B13) -> #REF!

Sheet Thù lao
B1: BCTT | J1: HD KLTN | R1: PB KLTN | Z1: CT KLTN | AH1: Ủy viên KLTN | AP1: Thư ký KLTN | AX1: HĐ | BF1: BCCĐTT | BG1: PB KLTN | BH1: CT KLTN | BI1: UV KLTN | BJ1: Tky KLTN | BK1: HD KLTN | BL1: Thù lao HD BCTT & HD KLTN (VNĐ) | BM1: Thù lao Hội đồng (VNĐ) | BN1: Thù lao HD và HĐ KLTN (VNĐ) | BO1: Tổng cộng (VNĐ)
A2: Họ và tên GV/Đơn giá | B2: 404 | C2: 412 | D2: 414 | E2: 404C | F2: 404C | G2: 414C | H2: 414C | I2: CA | J2: 404 | K2: 412 | L2: 414 | M2: 404C | N2: 404C | O2: 414C | P2: 414C | Q2: CA | R2: 404 | S2: 412 | T2: 414 | U2: 404C | V2: 404C | W2: 414C | X2: 414C | Y2: CA | Z2: 404 | AA2: 412 | AB2: 414 | AC2: 404C | AD2: 404C | AE2: 414C | AF2: 414C | AG2: CA | AH2: 404 | AI2: 412 | AJ2: 414 | AK2: 404C | AL2: 404C | AM2: 414C | AN2: 414C | AO2: CA | AP2: 404 | AQ2: 412 | AR2: 414 | AS2: 404C | AT2: 404C | AU2: 414C | AV2: 414C | AW2: CA | AX2: 404 | AY2: 412 | AZ2: 414 | BA2: 404C | BB2: 404C | BC2: 414C | BD2: 414C | BE2: CA | BF2: 420000 | BG2: 240000 | BH2: 150000 | BI2: 150000 | BJ2: 150000 | BK2: 720000
A3: Hệ số thù lao | B3: 1 | C3: 1 | D3: 1 | E3: 1.5 | F3: 3 | G3: 1.5 | H3: 3 | I3: 3 | J3: 1 | K3: 1 | L3: 1 | M3: 1.5 | N3: 3 | O3: 1.5 | P3: 3 | Q3: 3 | R3: 1 | S3: 1 | T3: 1 | U3: 1.5 | V3: 3 | W3: 1.5 | X3: 3 | Y3: 3 | Z3: 1 | AA3: 1 | AB3: 1 | AC3: 1.5 | AD3: 3 | AE3: 1.5 | AF3: 3 | AG3: 3 | AH3: 1 | AI3: 1 | AJ3: 1 | AK3: 1.5 | AL3: 3 | AM3: 1.5 | AN3: 3 | AO3: 3 | AP3: 1 | AQ3: 1 | AR3: 1 | AS3: 1.5 | AT3: 3 | AU3: 1.5 | AV3: 3 | AW3: 3 | AX3: 1 | AY3: 1 | AZ3: 1 | BA3: 1.5 | BB3: 3 | BC3: 1.5 | BD3: 3 | BE3: 3
A4: TS Nguyễn Hoàng Anh | B4: =SUMPRODUCT(('Phân công'!$D$2:$D$259=$A4)*('Phân công'!#REF!="X")*(RIGHT('Phân công'!$C$2:$C$259,3)="404")) -> #REF! | C4: =SUMPRODUCT(('Phân công'!$D$2:$D$259=$A4)*('Phân công'!#REF!="X")*(RIGHT('Phân công'!$C$2:$C$259,3)="412")) -> #REF! | D4: =SUMPRODUCT(('Phân công'!$D$2:$D$259=$A4)*('Phân công'!#REF!="X")*(RIGHT('Phân công'!$C$2:$C$259,3)="414")) -> #REF! | E4: =SUMPRODUCT(('Phân công'!$D$2:$D$259=$A4)*('Phân công'!#REF!="X")*(RIGHT('Phân công'!$C$2:$C$259,4)="404C")*('Phân công'!#REF!="Tiếng Việt")) -> #REF! | F4: =SUMPRODUCT(('Phân công'!$D$2:$D$259=$A4)*('Phân công'!#REF!="X")*(RIGHT('Phân công'!$C$2:$C$259,4)="404C")*('Phân công'!#REF!="Tiếng Anh")) -> #REF! | G4: =SUMPRODUCT(('Phân công'!$D$2:$D$259=$A4)*('Phân công'!#REF!="X")*(RIGHT('Phân công'!$C$2:$C$259,4)="414C")*('Phân công'!#REF!="Tiếng Việt")) -> #REF! | H4: =SUMPRODUCT(('Phân công'!$D$2:$D$259=$A4)*('Phân công'!#REF!="X")*(RIGHT('Phân công'!$C$2:$C$259,4)="414C")*('Phân công'!#REF!="Tiếng Anh")) -> #REF! | I4: =SUMPRODUCT(('Phân công'!$D$2:$D$259=$A4)*('Phân công'!#REF!="X")*(RIGHT('Phân công'!$C$2:$C$259,5)="404CA")) -> #REF! | J4: =SUMPRODUCT(('Phân công'!$D$2:$D$259=$A4)*('Phân công'!#REF!="X")*(RIGHT('Phân công'!$C$2:$C$259,3)="404")) -> #REF! | K4: =SUMPRODUCT(('Phân công'!$D$2:$D$259=$A4)*('Phân công'!#REF!="X")*(RIGHT('Phân công'!$C$2:$C$259,3)="412")) -> #REF! | L4: =SUMPRODUCT(('Phân công'!$D$2:$D$259=$A4)*('Phân công'!#REF!="X")*(RIGHT('Phân công'!$C$2:$C$259,3)="414")) -> #REF! | M4: =SUMPRODUCT(('Phân công'!$D$2:$D$259=$A4)*('Phân công'!#REF!="X")*(RIGHT('Phân công'!$C$2:$C$259,3)="04C")*('Phân công'!#REF!="Tiếng Việt")) -> #REF! | N4: =SUMPRODUCT(('Phân công'!$D$2:$D$259=$A4)*('Phân công'!#REF!="X")*(RIGHT('Phân công'!$C$2:$C$259,3)="04C")*('Phân công'!#REF!="Tiếng Anh")) -> #REF! | O4: =SUMPRODUCT(('Phân công'!$D$2:$D$259=$A4)*('Phân công'!#REF!="X")*(RIGHT('Phân công'!$C$2:$C$259,3)="14C")*('Phân công'!#REF!="Tiếng Việt")) -> #REF! | P4: =SUMPRODUCT(('Phân công'!$D$2:$D$259=$A4)*('Phân công'!#REF!="X")*(RIGHT('Phân công'!$C$2:$C$259,3)="14C")*('Phân công'!#REF!="Tiếng Anh")) -> #REF! | Q4: =SUMPRODUCT(('Phân công'!$D$2:$D$259=$A4)*('Phân công'!#REF!="X")*(RIGHT('Phân công'!$C$2:$C$259,3)="4CA")) -> #REF! | R4: =SUMPRODUCT(('Phân công'!#REF!='Thù lao'!A4)*(RIGHT('Phân công'!$C$2:$C$259,3)="404")) -> #REF! | S4: =SUMPRODUCT(('Phân công'!#REF!='Thù lao'!A4)*(RIGHT('Phân công'!$C$2:$C$259,3)="412")) -> #REF! | T4: =SUMPRODUCT(('Phân công'!#REF!='Thù lao'!A4)*(RIGHT('Phân công'!$C$2:$C$259,3)="414")) -> #REF! | U4: =SUMPRODUCT(('Phân công'!#REF!='Thù lao'!A4)*(RIGHT('Phân công'!$C$2:$C$259,3)="04C")*('Phân công'!#REF!="Tiếng Việt")) -> #REF! | V4: =SUMPRODUCT(('Phân công'!#REF!='Thù lao'!A4)*(RIGHT('Phân công'!$C$2:$C$259,3)="04C")*('Phân công'!#REF!="Tiếng Anh")) -> #REF! | W4: =SUMPRODUCT(('Phân công'!#REF!='Thù lao'!A4)*(RIGHT('Phân công'!$C$2:$C$259,3)="14C")*('Phân công'!#REF!="Tiếng Việt")) -> #REF! | X4: =SUMPRODUCT(('Phân công'!#REF!='Thù lao'!A4)*(RIGHT('Phân công'!$C$2:$C$259,3)="14C")*('Phân công'!#REF!="Tiếng Anh")) -> #REF! | Y4: =SUMPRODUCT(('Phân công'!#REF!='Thù lao'!A4)*(RIGHT('Phân công'!$C$2:$C$259,3)="4CA")) -> #REF! | Z4: =SUMPRODUCT(('Phân công'!#REF!='Thù lao'!A4)*(RIGHT('Phân công'!$C$2:$C$259,3)="404")) -> #REF! | AA4: =SUMPRODUCT(('Phân công'!#REF!='Thù lao'!A4)*(RIGHT('Phân công'!$C$2:$C$259,3)="412")) -> #REF! | AB4: =SUMPRODUCT(('Phân công'!#REF!='Thù lao'!A4)*(RIGHT('Phân công'!$C$2:$C$259,3)="414")) -> #REF! | AC4: =SUMPRODUCT(('Phân công'!#REF!='Thù lao'!A4)*(RIGHT('Phân công'!$C$2:$C$259,3)="04C")*('Phân công'!#REF!="Tiếng Việt")) -> #REF! | AD4: =SUMPRODUCT(('Phân công'!#REF!='Thù lao'!A4)*(RIGHT('Phân công'!$C$2:$C$259,3)="04C")*('Phân công'!#REF!="Tiếng Anh")) -> #REF! | AE4: =SUMPRODUCT(('Phân công'!#REF!='Thù lao'!A4)*(RIGHT('Phân công'!$C$2:$C$259,3)="14C")*('Phân công'!#REF!="Tiếng Việt")) -> #REF! | AF4: =SUMPRODUCT(('Phân công'!#REF!='Thù lao'!A4)*(RIGHT('Phân công'!$C$2:$C$259,3)="14C")*('Phân công'!#REF!="Tiếng Anh")) -> #REF! | AG4: =SUMPRODUCT(('Phân công'!#REF!='Thù lao'!A4)*(RIGHT('Phân công'!$C$2:$C$259,3)="4CA")) -> #REF! | AH4: =SUMPRODUCT(('Phân công'!#REF!='Thù lao'!A4)*(RIGHT('Phân công'!$C$2:$C$259,3)="404")) -> #REF! | AI4: =SUMPRODUCT(('Phân công'!#REF!='Thù lao'!A4)*(RIGHT('Phân công'!$C$2:$C$259,3)="412")) -> #REF! | AJ4: =SUMPRODUCT(('Phân công'!#REF!='Thù lao'!A4)*(RIGHT('Phân công'!$C$2:$C$259,3)="414")) -> #REF! | AK4: =SUMPRODUCT(('Phân công'!#REF!='Thù lao'!A4)*(RIGHT('Phân công'!$C$2:$C$259,3)="04C")*('Phân công'!#REF!="Tiếng Việt")) -> #REF! | AL4: =SUMPRODUCT(('Phân công'!#REF!='Thù lao'!A4)*(RIGHT('Phân công'!$C$2:$C$259,3)="04C")*('Phân công'!#REF!="Tiếng Anh")) -> #REF! | AM4: =SUMPRODUCT(('Phân công'!#REF!='Thù lao'!A4)*(RIGHT('Phân công'!$C$2:$C$259,3)="14C")*('Phân công'!#REF!="Tiếng Việt")) -> #REF! | AN4: =SUMPRODUCT(('Phân công'!#REF!='Thù lao'!A4)*(RIGHT('Phân công'!$C$2:$C$259,3)="14C")*('Phân công'!#REF!="Tiếng Anh")) -> #REF! | AO4: =SUMPRODUCT(('Phân công'!#REF!='Thù lao'!A4)*(RIGHT('Phân công'!$C$2:$C$259,3)="4CA")) -> #REF! | AP4: =SUMPRODUCT(('Phân công'!#REF!='Thù lao'!A4)*(RIGHT('Phân công'!$C$2:$C$259,3)="404")) -> #REF! | AQ4: =SUMPRODUCT(('Phân công'!#REF!='Thù lao'!A4)*(RIGHT('Phân công'!$C$2:$C$259,3)="412")) -> #REF! | AR4: =SUMPRODUCT(('Phân công'!#REF!='Thù lao'!A4)*(RIGHT('Phân công'!$C$2:$C$259,3)="414")) -> #REF! | AS4: =SUMPRODUCT(('Phân công'!#REF!='Thù lao'!A4)*(RIGHT('Phân công'!$C$2:$C$259,3)="04C")*('Phân công'!#REF!="Tiếng Việt")) -> #REF! | AT4: =SUMPRODUCT(('Phân công'!#REF!='Thù lao'!A4)*(RIGHT('Phân công'!$C$2:$C$259,3)="04C")*('Phân công'!#REF!="Tiếng Anh")) -> #REF! | AU4: =SUMPRODUCT(('Phân công'!#REF!='Thù lao'!A4)*(RIGHT('Phân công'!$C$2:$C$259,3)="14C")*('Phân công'!#REF!="Tiếng Việt")) -> #REF! | AV4: =SUMPRODUCT(('Phân công'!#REF!='Thù lao'!A4)*(RIGHT('Phân công'!$C$2:$C$259,3)="14C")*('Phân công'!#REF!="Tiếng Anh")) -> #REF! | AW4: =SUMPRODUCT(('Phân công'!#REF!='Thù lao'!A4)*(RIGHT('Phân công'!$C$2:$C$259,3)="4CA")) -> #REF! | AX4: =AP4+AH4+Z4+R4 -> #REF! | AY4: =AQ4+AI4+AA4+S4 -> #REF! | AZ4: =AR4+AJ4+AB4+T4 -> #REF! | BA4: =AS4+AK4+AC4+U4 -> #REF! | BB4: =AT4+AL4+AD4+V4 -> #REF! | BC4: =AU4+AM4+AE4+W4 -> #REF! | BD4: =AV4+AN4+AF4+X4 -> #REF! | BE4: =AW4+AO4+AG4+Y4 -> #REF! | BF4: =SUMPRODUCT((B4:I4),($B$3:$I$3))*$BF$2 -> #REF! | BG4: =SUMPRODUCT(R4:Y4,$R$3:$Y$3)*$BG$2 -> #REF! | BH4: =SUMPRODUCT(Z4:AG4,$Z$3:$AG$3)*$BH$2 -> #REF! | BI4: =SUMPRODUCT(AH4:AO4,$AH$3:$AO$3)*$BI$2 -> #REF! | BJ4: =SUMPRODUCT(AP4:AW4,$AP$3:$AW$3)*$BJ$2 -> #REF! | BK4: =SUMPRODUCT((J4:Q4),($J$3:$Q$3))*$BK$2 -> #REF! | BL4: =BF4+BK4 -> #REF! | BM4: =SUM(BG4:BJ4) -> #REF! | BN4: =BM4+BK4 -> #REF! | BO4: =BL4+BM4 -> #REF!
A5: ThS Nguyễn Thị Hai Hằng | B5: =SUMPRODUCT(('Phân công'!$D$2:$D$259=$A5)*('Phân công'!#REF!="X")*(RIGHT('Phân công'!$C$2:$C$259,3)="404")) -> #REF! | C5: =SUMPRODUCT(('Phân công'!$D$2:$D$259=$A5)*('Phân công'!#REF!="X")*(RIGHT('Phân công'!$C$2:$C$259,3)="412")) -> #REF! | D5: =SUMPRODUCT(('Phân công'!$D$2:$D$259=$A5)*('Phân công'!#REF!="X")*(RIGHT('Phân công'!$C$2:$C$259,3)="414")) -> #REF! | E5: =SUMPRODUCT(('Phân công'!$D$2:$D$259=$A5)*('Phân công'!#REF!="X")*(RIGHT('Phân công'!$C$2:$C$259,4)="404C")*('Phân công'!#REF!="Tiếng Việt")) -> #REF! | F5: =SUMPRODUCT(('Phân công'!$D$2:$D$259=$A5)*('Phân công'!#REF!="X")*(RIGHT('Phân công'!$C$2:$C$259,4)="404C")*('Phân công'!#REF!="Tiếng Anh")) -> #REF! | G5: =SUMPRODUCT(('Phân công'!$D$2:$D$259=$A5)*('Phân công'!#REF!="X")*(RIGHT('Phân công'!$C$2:$C$259,4)="414C")*('Phân công'!#REF!="Tiếng Việt")) -> #REF! | H5: =SUMPRODUCT(('Phân công'!$D$2:$D$259=$A5)*('Phân công'!#REF!="X")*(RIGHT('Phân công'!$C$2:$C$259,4)="414C")*('Phân công'!#REF!="Tiếng Anh")) -> #REF! | I5: =SUMPRODUCT(('Phân công'!$D$2:$D$259=$A5)*('Phân công'!#REF!="X")*(RIGHT('Phân công'!$C$2:$C$259,5)="404CA")) -> #REF! | J5: =SUMPRODUCT(('Phân công'!$D$2:$D$259=$A5)*('Phân công'!#REF!="X")*(RIGHT('Phân công'!$C$2:$C$259,3)="404")) -> #REF! | K5: =SUMPRODUCT(('Phân công'!$D$2:$D$259=$A5)*('Phân công'!#REF!="X")*(RIGHT('Phân công'!$C$2:$C$259,3)="412")) -> #REF! | L5: =SUMPRODUCT(('Phân công'!$D$2:$D$259=$A5)*('Phân công'!#REF!="X")*(RIGHT('Phân công'!$C$2:$C$259,3)="414")) -> #REF! | M5: =SUMPRODUCT(('Phân công'!$D$2:$D$259=$A5)*('Phân công'!#REF!="X")*(RIGHT('Phân công'!$C$2:$C$259,3)="04C")*('Phân công'!#REF!="Tiếng Việt")) -> #REF! | N5: =SUMPRODUCT(('Phân công'!$D$2:$D$259=$A5)*('Phân công'!#REF!="X")*(RIGHT('Phân công'!$C$2:$C$259,3)="04C")*('Phân công'!#REF!="Tiếng Anh")) -> #REF! | O5: =SUMPRODUCT(('Phân công'!$D$2:$D$259=$A5)*('Phân công'!#REF!="X")*(RIGHT('Phân công'!$C$2:$C$259,3)="14C")*('Phân công'!#REF!="Tiếng Việt")) -> #REF! | P5: =SUMPRODUCT(('Phân công'!$D$2:$D$259=$A5)*('Phân công'!#REF!="X")*(RIGHT('Phân công'!$C$2:$C$259,3)="14C")*('Phân công'!#REF!="Tiếng Anh")) -> #REF! | Q5: =SUMPRODUCT(('Phân công'!$D$2:$D$259=$A5)*('Phân công'!#REF!="X")*(RIGHT('Phân công'!$C$2:$C$259,3)="4CA")) -> #REF! | R5: =SUMPRODUCT(('Phân công'!#REF!='Thù lao'!A5)*(RIGHT('Phân công'!$C$2:$C$259,3)="404")) -> #REF! | S5: =SUMPRODUCT(('Phân công'!#REF!='Thù lao'!A5)*(RIGHT('Phân công'!$C$2:$C$259,3)="412")) -> #REF! | T5: =SUMPRODUCT(('Phân công'!#REF!='Thù lao'!A5)*(RIGHT('Phân công'!$C$2:$C$259,3)="414")) -> #REF! | U5: =SUMPRODUCT(('Phân công'!#REF!='Thù lao'!A5)*(RIGHT('Phân công'!$C$2:$C$259,3)="04C")*('Phân công'!#REF!="Tiếng Việt")) -> #REF! | V5: =SUMPRODUCT(('Phân công'!#REF!='Thù lao'!A5)*(RIGHT('Phân công'!$C$2:$C$259,3)="04C")*('Phân công'!#REF!="Tiếng Anh")) -> #REF! | W5: =SUMPRODUCT(('Phân công'!#REF!='Thù lao'!A5)*(RIGHT('Phân công'!$C$2:$C$259,3)="14C")*('Phân công'!#REF!="Tiếng Việt")) -> #REF! | X5: =SUMPRODUCT(('Phân công'!#REF!='Thù lao'!A5)*(RIGHT('Phân công'!$C$2:$C$259,3)="14C")*('Phân công'!#REF!="Tiếng Anh")) -> #REF! | Y5: =SUMPRODUCT(('Phân công'!#REF!='Thù lao'!A5)*(RIGHT('Phân công'!$C$10:$C$259,3)="4CA")) -> #REF! | Z5: =SUMPRODUCT(('Phân công'!#REF!='Thù lao'!A5)*(RIGHT('Phân công'!$C$2:$C$259,3)="404")) -> #REF! | AA5: =SUMPRODUCT(('Phân công'!#REF!='Thù lao'!A5)*(RIGHT('Phân công'!$C$2:$C$259,3)="412")) -> #REF! | AB5: =SUMPRODUCT(('Phân công'!#REF!='Thù lao'!A5)*(RIGHT('Phân công'!$C$2:$C$259,3)="414")) -> #REF! | AC5: =SUMPRODUCT(('Phân công'!#REF!='Thù lao'!A5)*(RIGHT('Phân công'!$C$2:$C$259,3)="04C")*('Phân công'!#REF!="Tiếng Việt")) -> #REF! | AD5: =SUMPRODUCT(('Phân công'!#REF!='Thù lao'!A5)*(RIGHT('Phân công'!$C$2:$C$259,3)="04C")*('Phân công'!#REF!="Tiếng Anh")) -> #REF! | AE5: =SUMPRODUCT(('Phân công'!#REF!='Thù lao'!A5)*(RIGHT('Phân công'!$C$2:$C$259,3)="14C")*('Phân công'!#REF!="Tiếng Việt")) -> #REF! | AF5: =SUMPRODUCT(('Phân công'!#REF!='Thù lao'!A5)*(RIGHT('Phân công'!$C$2:$C$259,3)="14C")*('Phân công'!#REF!="Tiếng Anh")) -> #REF! | AG5: =SUMPRODUCT(('Phân công'!#REF!='Thù lao'!A5)*(RIGHT('Phân công'!$C$2:$C$259,3)="4CA")) -> #REF! | AH5: =SUMPRODUCT(('Phân công'!#REF!='Thù lao'!A5)*(RIGHT('Phân công'!$C$2:$C$259,3)="404")) -> #REF! | AI5: =SUMPRODUCT(('Phân công'!#REF!='Thù lao'!A5)*(RIGHT('Phân công'!$C$2:$C$259,3)="412")) -> #REF! | AJ5: =SUMPRODUCT(('Phân công'!#REF!='Thù lao'!A5)*(RIGHT('Phân công'!$C$2:$C$259,3)="414")) -> #REF! | AK5: =SUMPRODUCT(('Phân công'!#REF!='Thù lao'!A5)*(RIGHT('Phân công'!$C$2:$C$259,3)="04C")*('Phân công'!#REF!="Tiếng Việt")) -> #REF! | AL5: =SUMPRODUCT(('Phân công'!#REF!='Thù lao'!A5)*(RIGHT('Phân công'!$C$2:$C$259,3)="04C")*('Phân công'!#REF!="Tiếng Anh")) -> #REF! | AM5: =SUMPRODUCT(('Phân công'!#REF!='Thù lao'!A5)*(RIGHT('Phân công'!$C$2:$C$259,3)="14C")*('Phân công'!#REF!="Tiếng Việt")) -> #REF! | AN5: =SUMPRODUCT(('Phân công'!#REF!='Thù lao'!A5)*(RIGHT('Phân công'!$C$2:$C$259,3)="14C")*('Phân công'!#REF!="Tiếng Anh")) -> #REF! | AO5: =SUMPRODUCT(('Phân công'!#REF!='Thù lao'!A5)*(RIGHT('Phân công'!$C$2:$C$259,3)="4CA")) -> #REF! | AP5: =SUMPRODUCT(('Phân công'!#REF!='Thù lao'!A5)*(RIGHT('Phân công'!$C$2:$C$259,3)="404")) -> #REF! | AQ5: =SUMPRODUCT(('Phân công'!#REF!='Thù lao'!A5)*(RIGHT('Phân công'!$C$2:$C$259,3)="412")) -> #REF! | AR5: =SUMPRODUCT(('Phân công'!#REF!='Thù lao'!A5)*(RIGHT('Phân công'!$C$2:$C$259,3)="414")) -> #REF! | AS5: =SUMPRODUCT(('Phân công'!#REF!='Thù lao'!A5)*(RIGHT('Phân công'!$C$2:$C$259,3)="04C")*('Phân công'!#REF!="Tiếng Việt")) -> #REF! | AT5: =SUMPRODUCT(('Phân công'!#REF!='Thù lao'!A5)*(RIGHT('Phân công'!$C$2:$C$259,3)="04C")*('Phân công'!#REF!="Tiếng Anh")) -> #REF! | AU5: =SUMPRODUCT(('Phân công'!#REF!='Thù lao'!A5)*(RIGHT('Phân công'!$C$2:$C$259,3)="14C")*('Phân công'!#REF!="Tiếng Việt")) -> #REF! | AV5: =SUMPRODUCT(('Phân công'!#REF!='Thù lao'!A5)*(RIGHT('Phân công'!$C$2:$C$259,3)="14C")*('Phân công'!#REF!="Tiếng Anh")) -> #REF! | AW5: =SUMPRODUCT(('Phân công'!#REF!='Thù lao'!A5)*(RIGHT('Phân công'!$C$2:$C$259,3)="4CA")) -> #REF! | AX5: =AP5+AH5+Z5+R5 -> #REF! | AY5: =AQ5+AI5+AA5+S5 -> #REF! | AZ5: =AR5+AJ5+AB5+T5 -> #REF! | BA5: =AS5+AK5+AC5+U5 -> #REF! | BB5: =AT5+AL5+AD5+V5 -> #REF! | BC5: =AU5+AM5+AE5+W5 -> #REF! | BD5: =AV5+AN5+AF5+X5 -> #REF! | BE5: =AW5+AO5+AG5+Y5 -> #REF! | BF5: =SUMPRODUCT((B5:I5),($B$3:$I$3))*$BF$2 -> #REF! | BG5: =SUMPRODUCT(R5:Y5,$R$3:$Y$3)*$BG$2 -> #REF! | BH5: =SUMPRODUCT(Z5:AG5,$Z$3:$AG$3)*$BH$2 -> #REF! | BI5: =SUMPRODUCT(AH5:AO5,$AH$3:$AO$3)*$BI$2 -> #REF! | BJ5: =SUMPRODUCT(AP5:AW5,$AP$3:$AW$3)*$BJ$2 -> #REF! | BK5: =SUMPRODUCT((J5:Q5),($J$3:$Q$3))*$BK$2 -> #REF! | BL5: =BF5+BK5 -> #REF! | BM5: =SUM(BG5:BJ5) -> #REF! | BN5: =BM5+BK5 -> #REF! | BO5: =BL5+BM5 -> #REF!
A6: ThS Nguyễn Thị Diễm Hiền | B6: =SUMPRODUCT(('Phân công'!$D$2:$D$259=$A6)*('Phân công'!#REF!="X")*(RIGHT('Phân công'!$C$2:$C$259,3)="404")) -> #REF! | C6: =SUMPRODUCT(('Phân công'!$D$2:$D$259=$A6)*('Phân công'!#REF!="X")*(RIGHT('Phân công'!$C$2:$C$259,3)="412")) -> #REF! | D6: =SUMPRODUCT(('Phân công'!$D$2:$D$259=$A6)*('Phân công'!#REF!="X")*(RIGHT('Phân công'!$C$2:$C$259,3)="414")) -> #REF! | E6: =SUMPRODUCT(('Phân công'!$D$2:$D$259=$A6)*('Phân công'!#REF!="X")*(RIGHT('Phân công'!$C$2:$C$259,4)="404C")*('Phân công'!#REF!="Tiếng Việt")) -> #REF! | F6: =SUMPRODUCT(('Phân công'!$D$2:$D$259=$A6)*('Phân công'!#REF!="X")*(RIGHT('Phân công'!$C$2:$C$259,4)="404C")*('Phân công'!#REF!="Tiếng Anh")) -> #REF! | G6: =SUMPRODUCT(('Phân công'!$D$2:$D$259=$A6)*('Phân công'!#REF!="X")*(RIGHT('Phân công'!$C$2:$C$259,4)="414C")*('Phân công'!#REF!="Tiếng Việt")) -> #REF! | H6: =SUMPRODUCT(('Phân công'!$D$2:$D$259=$A6)*('Phân công'!#REF!="X")*(RIGHT('Phân công'!$C$2:$C$259,4)="414C")*('Phân công'!#REF!="Tiếng Anh")) -> #REF! | I6: =SUMPRODUCT(('Phân công'!$D$2:$D$259=$A6)*('Phân công'!#REF!="X")*(RIGHT('Phân công'!$C$2:$C$259,5)="404CA")) -> #REF! | J6: =SUMPRODUCT(('Phân công'!$D$2:$D$259=$A6)*('Phân công'!#REF!="X")*(RIGHT('Phân công'!$C$2:$C$259,3)="404")) -> #REF! | K6: =SUMPRODUCT(('Phân công'!$D$2:$D$259=$A6)*('Phân công'!#REF!="X")*(RIGHT('Phân công'!$C$2:$C$259,3)="412")) -> #REF! | L6: =SUMPRODUCT(('Phân công'!$D$2:$D$259=$A6)*('Phân công'!#REF!="X")*(RIGHT('Phân công'!$C$2:$C$259,3)="414")) -> #REF! | M6: =SUMPRODUCT(('Phân công'!$D$2:$D$259=$A6)*('Phân công'!#REF!="X")*(RIGHT('Phân công'!$C$2:$C$259,3)="04C")*('Phân công'!#REF!="Tiếng Việt")) -> #REF! | N6: =SUMPRODUCT(('Phân công'!$D$2:$D$259=$A6)*('Phân công'!#REF!="X")*(RIGHT('Phân công'!$C$2:$C$259,3)="04C")*('Phân công'!#REF!="Tiếng Anh")) -> #REF! | O6: =SUMPRODUCT(('Phân công'!$D$2:$D$259=$A6)*('Phân công'!#REF!="X")*(RIGHT('Phân công'!$C$2:$C$259,3)="14C")*('Phân công'!#REF!="Tiếng Việt")) -> #REF! | P6: =SUMPRODUCT(('Phân công'!$D$2:$D$259=$A6)*('Phân công'!#REF!="X")*(RIGHT('Phân công'!$C$2:$C$259,3)="14C")*('Phân công'!#REF!="Tiếng Anh")) -> #REF! | Q6: =SUMPRODUCT(('Phân công'!$D$2:$D$259=$A6)*('Phân công'!#REF!="X")*(RIGHT('Phân công'!$C$2:$C$259,3)="4CA")) -> #REF! | R6: =SUMPRODUCT(('Phân công'!#REF!='Thù lao'!A6)*(RIGHT('Phân công'!$C$2:$C$259,3)="404")) -> #REF! | S6: =SUMPRODUCT(('Phân công'!#REF!='Thù lao'!A6)*(RIGHT('Phân công'!$C$2:$C$259,3)="412")) -> #REF! | T6: =SUMPRODUCT(('Phân công'!#REF!='Thù lao'!A6)*(RIGHT('Phân công'!$C$2:$C$259,3)="414")) -> #REF! | U6: =SUMPRODUCT(('Phân công'!#REF!='Thù lao'!A6)*(RIGHT('Phân công'!$C$2:$C$259,3)="04C")*('Phân công'!#REF!="Tiếng Việt")) -> #REF! | V6: =SUMPRODUCT(('Phân công'!#REF!='Thù lao'!A6)*(RIGHT('Phân công'!$C$2:$C$259,3)="04C")*('Phân công'!#REF!="Tiếng Anh")) -> #REF! | W6: =SUMPRODUCT(('Phân công'!#REF!='Thù lao'!A6)*(RIGHT('Phân công'!$C$2:$C$259,3)="14C")*('Phân công'!#REF!="Tiếng Việt")) -> #REF! | X6: =SUMPRODUCT(('Phân công'!#REF!='Thù lao'!A6)*(RIGHT('Phân công'!$C$2:$C$259,3)="14C")*('Phân công'!#REF!="Tiếng Anh")) -> #REF! | Y6: =SUMPRODUCT(('Phân công'!#REF!='Thù lao'!A6)*(RIGHT('Phân công'!$C$10:$C$259,3)="4CA")) -> #REF! | Z6: =SUMPRODUCT(('Phân công'!#REF!='Thù lao'!A6)*(RIGHT('Phân công'!$C$2:$C$259,3)="404")) -> #REF! | AA6: =SUMPRODUCT(('Phân công'!#REF!='Thù lao'!A6)*(RIGHT('Phân công'!$C$2:$C$259,3)="412")) -> #REF! | AB6: =SUMPRODUCT(('Phân công'!#REF!='Thù lao'!A6)*(RIGHT('Phân công'!$C$2:$C$259,3)="414")) -> #REF! | AC6: =SUMPRODUCT(('Phân công'!#REF!='Thù lao'!A6)*(RIGHT('Phân công'!$C$2:$C$259,3)="04C")*('Phân công'!#REF!="Tiếng Việt")) -> #REF! | AD6: =SUMPRODUCT(('Phân công'!#REF!='Thù lao'!A6)*(RIGHT('Phân công'!$C$2:$C$259,3)="04C")*('Phân công'!#REF!="Tiếng Anh")) -> #REF! | AE6: =SUMPRODUCT(('Phân công'!#REF!='Thù lao'!A6)*(RIGHT('Phân công'!$C$2:$C$259,3)="14C")*('Phân công'!#REF!="Tiếng Việt")) -> #REF! | AF6: =SUMPRODUCT(('Phân công'!#REF!='Thù lao'!A6)*(RIGHT('Phân công'!$C$2:$C$259,3)="14C")*('Phân công'!#REF!="Tiếng Anh")) -> #REF! | AG6: =SUMPRODUCT(('Phân công'!#REF!='Thù lao'!A6)*(RIGHT('Phân công'!$C$2:$C$259,3)="4CA")) -> #REF! | AH6: =SUMPRODUCT(('Phân công'!#REF!='Thù lao'!A6)*(RIGHT('Phân công'!$C$2:$C$259,3)="404")) -> #REF! | AI6: =SUMPRODUCT(('Phân công'!#REF!='Thù lao'!A6)*(RIGHT('Phân công'!$C$2:$C$259,3)="412")) -> #REF! | AJ6: =SUMPRODUCT(('Phân công'!#REF!='Thù lao'!A6)*(RIGHT('Phân công'!$C$2:$C$259,3)="414")) -> #REF! | AK6: =SUMPRODUCT(('Phân công'!#REF!='Thù lao'!A6)*(RIGHT('Phân công'!$C$2:$C$259,3)="04C")*('Phân công'!#REF!="Tiếng Việt")) -> #REF! | AL6: =SUMPRODUCT(('Phân công'!#REF!='Thù lao'!A6)*(RIGHT('Phân công'!$C$2:$C$259,3)="04C")*('Phân công'!#REF!="Tiếng Anh")) -> #REF! | AM6: =SUMPRODUCT(('Phân công'!#REF!='Thù lao'!A6)*(RIGHT('Phân công'!$C$2:$C$259,3)="14C")*('Phân công'!#REF!="Tiếng Việt")) -> #REF! | AN6: =SUMPRODUCT(('Phân công'!#REF!='Thù lao'!A6)*(RIGHT('Phân công'!$C$2:$C$259,3)="14C")*('Phân công'!#REF!="Tiếng Anh")) -> #REF! | AO6: =SUMPRODUCT(('Phân công'!#REF!='Thù lao'!A6)*(RIGHT('Phân công'!$C$2:$C$259,3)="4CA")) -> #REF! | AP6: =SUMPRODUCT(('Phân công'!#REF!='Thù lao'!A6)*(RIGHT('Phân công'!$C$2:$C$259,3)="404")) -> #REF! | AQ6: =SUMPRODUCT(('Phân công'!#REF!='Thù lao'!A6)*(RIGHT('Phân công'!$C$2:$C$259,3)="412")) -> #REF! | AR6: =SUMPRODUCT(('Phân công'!#REF!='Thù lao'!A6)*(RIGHT('Phân công'!$C$2:$C$259,3)="414")) -> #REF! | AS6: =SUMPRODUCT(('Phân công'!#REF!='Thù lao'!A6)*(RIGHT('Phân công'!$C$2:$C$259,3)="04C")*('Phân công'!#REF!="Tiếng Việt")) -> #REF! | AT6: =SUMPRODUCT(('Phân công'!#REF!='Thù lao'!A6)*(RIGHT('Phân công'!$C$2:$C$259,3)="04C")*('Phân công'!#REF!="Tiếng Anh")) -> #REF! | AU6: =SUMPRODUCT(('Phân công'!#REF!='Thù lao'!A6)*(RIGHT('Phân công'!$C$2:$C$259,3)="14C")*('Phân công'!#REF!="Tiếng Việt")) -> #REF! | AV6: =SUMPRODUCT(('Phân công'!#REF!='Thù lao'!A6)*(RIGHT('Phân công'!$C$2:$C$259,3)="14C")*('Phân công'!#REF!="Tiếng Anh")) -> #REF! | AW6: =SUMPRODUCT(('Phân công'!#REF!='Thù lao'!A6)*(RIGHT('Phân công'!$C$2:$C$259,3)="4CA")) -> #REF! | AX6: =AP6+AH6+Z6+R6 -> #REF! | AY6: =AQ6+AI6+AA6+S6 -> #REF! | AZ6: =AR6+AJ6+AB6+T6 -> #REF! | BA6: =AS6+AK6+AC6+U6 -> #REF! | BB6: =AT6+AL6+AD6+V6 -> #REF! | BC6: =AU6+AM6+AE6+W6 -> #REF! | BD6: =AV6+AN6+AF6+X6 -> #REF! | BE6: =AW6+AO6+AG6+Y6 -> #REF! | BF6: =SUMPRODUCT((B6:I6),($B$3:$I$3))*$BF$2 -> #REF! | BG6: =SUMPRODUCT(R6:Y6,$R$3:$Y$3)*$BG$2 -> #REF! | BH6: =SUMPRODUCT(Z6:AG6,$Z$3:$AG$3)*$BH$2 -> #REF! | BI6: =SUMPRODUCT(AH6:AO6,$AH$3:$AO$3)*$BI$2 -> #REF! | BJ6: =SUMPRODUCT(AP6:AW6,$AP$3:$AW$3)*$BJ$2 -> #REF! | BK6: =SUMPRODUCT((J6:Q6),($J$3:$Q$3))*$BK$2 -> #REF! | BL6: =BF6+BK6 -> #REF! | BM6: =SUM(BG6:BJ6) -> #REF! | BN6: =BM6+BK6 -> #REF! | BO6: =BL6+BM6 -> #REF!
A7: TS Nguyễn Trung Hiếu | B7: =SUMPRODUCT(('Phân công'!$D$2:$D$259=$A7)*('Phân công'!#REF!="X")*(RIGHT('Phân công'!$C$2:$C$259,3)="404")) -> #REF! | C7: =SUMPRODUCT(('Phân công'!$D$2:$D$259=$A7)*('Phân công'!#REF!="X")*(RIGHT('Phân công'!$C$2:$C$259,3)="412")) -> #REF! | D7: =SUMPRODUCT(('Phân công'!$D$2:$D$259=$A7)*('Phân công'!#REF!="X")*(RIGHT('Phân công'!$C$2:$C$259,3)="414")) -> #REF! | E7: =SUMPRODUCT(('Phân công'!$D$2:$D$259=$A7)*('Phân công'!#REF!="X")*(RIGHT('Phân công'!$C$2:$C$259,4)="404C")*('Phân công'!#REF!="Tiếng Việt")) -> #REF! | F7: =SUMPRODUCT(('Phân công'!$D$2:$D$259=$A7)*('Phân công'!#REF!="X")*(RIGHT('Phân công'!$C$2:$C$259,4)="404C")*('Phân công'!#REF!="Tiếng Anh")) -> #REF! | G7: =SUMPRODUCT(('Phân công'!$D$2:$D$259=$A7)*('Phân công'!#REF!="X")*(RIGHT('Phân công'!$C$2:$C$259,4)="414C")*('Phân công'!#REF!="Tiếng Việt")) -> #REF! | H7: =SUMPRODUCT(('Phân công'!$D$2:$D$259=$A7)*('Phân công'!#REF!="X")*(RIGHT('Phân công'!$C$2:$C$259,4)="414C")*('Phân công'!#REF!="Tiếng Anh")) -> #REF! | I7: =SUMPRODUCT(('Phân công'!$D$2:$D$259=$A7)*('Phân công'!#REF!="X")*(RIGHT('Phân công'!$C$2:$C$259,5)="404CA")) -> #REF! | J7: =SUMPRODUCT(('Phân công'!$D$2:$D$259=$A7)*('Phân công'!#REF!="X")*(RIGHT('Phân công'!$C$2:$C$259,3)="404")) -> #REF! | K7: =SUMPRODUCT(('Phân công'!$D$2:$D$259=$A7)*('Phân công'!#REF!="X")*(RIGHT('Phân công'!$C$2:$C$259,3)="412")) -> #REF! | L7: =SUMPRODUCT(('Phân công'!$D$2:$D$259=$A7)*('Phân công'!#REF!="X")*(RIGHT('Phân công'!$C$2:$C$259,3)="414")) -> #REF! | M7: =SUMPRODUCT(('Phân công'!$D$2:$D$259=$A7)*('Phân công'!#REF!="X")*(RIGHT('Phân công'!$C$2:$C$259,3)="04C")*('Phân công'!#REF!="Tiếng Việt")) -> #REF! | N7: =SUMPRODUCT(('Phân công'!$D$2:$D$259=$A7)*('Phân công'!#REF!="X")*(RIGHT('Phân công'!$C$2:$C$259,3)="04C")*('Phân công'!#REF!="Tiếng Anh")) -> #REF! | O7: =SUMPRODUCT(('Phân công'!$D$2:$D$259=$A7)*('Phân công'!#REF!="X")*(RIGHT('Phân công'!$C$2:$C$259,3)="14C")*('Phân công'!#REF!="Tiếng Việt")) -> #REF! | P7: =SUMPRODUCT(('Phân công'!$D$2:$D$259=$A7)*('Phân công'!#REF!="X")*(RIGHT('Phân công'!$C$2:$C$259,3)="14C")*('Phân công'!#REF!="Tiếng Anh")) -> #REF! | Q7: =SUMPRODUCT(('Phân công'!$D$2:$D$259=$A7)*('Phân công'!#REF!="X")*(RIGHT('Phân công'!$C$2:$C$259,3)="4CA")) -> #REF! | R7: =SUMPRODUCT(('Phân công'!#REF!='Thù lao'!A7)*(RIGHT('Phân công'!$C$2:$C$259,3)="404")) -> #REF! | S7: =SUMPRODUCT(('Phân công'!#REF!='Thù lao'!A7)*(RIGHT('Phân công'!$C$2:$C$259,3)="412")) -> #REF! | T7: =SUMPRODUCT(('Phân công'!#REF!='Thù lao'!A7)*(RIGHT('Phân công'!$C$2:$C$259,3)="414")) -> #REF! | U7: =SUMPRODUCT(('Phân công'!#REF!='Thù lao'!A7)*(RIGHT('Phân công'!$C$2:$C$259,3)="04C")*('Phân công'!#REF!="Tiếng Việt")) -> #REF! | V7: =SUMPRODUCT(('Phân công'!#REF!='Thù lao'!A7)*(RIGHT('Phân công'!$C$2:$C$259,3)="04C")*('Phân công'!#REF!="Tiếng Anh")) -> #REF! | W7: =SUMPRODUCT(('Phân công'!#REF!='Thù lao'!A7)*(RIGHT('Phân công'!$C$2:$C$259,3)="14C")*('Phân công'!#REF!="Tiếng Việt")) -> #REF! | X7: =SUMPRODUCT(('Phân công'!#REF!='Thù lao'!A7)*(RIGHT('Phân công'!$C$2:$C$259,3)="14C")*('Phân công'!#REF!="Tiếng Anh")) -> #REF! | Y7: =SUMPRODUCT(('Phân công'!#REF!='Thù lao'!A7)*(RIGHT('Phân công'!$C$10:$C$259,3)="4CA")) -> #REF! | Z7: =SUMPRODUCT(('Phân công'!#REF!='Thù lao'!A7)*(RIGHT('Phân công'!$C$2:$C$259,3)="404")) -> #REF! | AA7: =SUMPRODUCT(('Phân công'!#REF!='Thù lao'!A7)*(RIGHT('Phân công'!$C$2:$C$259,3)="412")) -> #REF! | AB7: =SUMPRODUCT(('Phân công'!#REF!='Thù lao'!A7)*(RIGHT('Phân công'!$C$2:$C$259,3)="414")) -> #REF! | AC7: =SUMPRODUCT(('Phân công'!#REF!='Thù lao'!A7)*(RIGHT('Phân công'!$C$2:$C$259,3)="04C")*('Phân công'!#REF!="Tiếng Việt")) -> #REF! | AD7: =SUMPRODUCT(('Phân công'!#REF!='Thù lao'!A7)*(RIGHT('Phân công'!$C$2:$C$259,3)="04C")*('Phân công'!#REF!="Tiếng Anh")) -> #REF! | AE7: =SUMPRODUCT(('Phân công'!#REF!='Thù lao'!A7)*(RIGHT('Phân công'!$C$2:$C$259,3)="14C")*('Phân công'!#REF!="Tiếng Việt")) -> #REF! | AF7: =SUMPRODUCT(('Phân công'!#REF!='Thù lao'!A7)*(RIGHT('Phân công'!$C$2:$C$259,3)="14C")*('Phân công'!#REF!="Tiếng Anh")) -> #REF! | AG7: =SUMPRODUCT(('Phân công'!#REF!='Thù lao'!A7)*(RIGHT('Phân công'!$C$2:$C$259,3)="4CA")) -> #REF! | AH7: =SUMPRODUCT(('Phân công'!#REF!='Thù lao'!A7)*(RIGHT('Phân công'!$C$2:$C$259,3)="404")) -> #REF! | AI7: =SUMPRODUCT(('Phân công'!#REF!='Thù lao'!A7)*(RIGHT('Phân công'!$C$2:$C$259,3)="412")) -> #REF! | AJ7: =SUMPRODUCT(('Phân công'!#REF!='Thù lao'!A7)*(RIGHT('Phân công'!$C$2:$C$259,3)="414")) -> #REF! | AK7: =SUMPRODUCT(('Phân công'!#REF!='Thù lao'!A7)*(RIGHT('Phân công'!$C$2:$C$259,3)="04C")*('Phân công'!#REF!="Tiếng Việt")) -> #REF! | AL7: =SUMPRODUCT(('Phân công'!#REF!='Thù lao'!A7)*(RIGHT('Phân công'!$C$2:$C$259,3)="04C")*('Phân công'!#REF!="Tiếng Anh")) -> #REF! | AM7: =SUMPRODUCT(('Phân công'!#REF!='Thù lao'!A7)*(RIGHT('Phân công'!$C$2:$C$259,3)="14C")*('Phân công'!#REF!="Tiếng Việt")) -> #REF! | AN7: =SUMPRODUCT(('Phân công'!#REF!='Thù lao'!A7)*(RIGHT('Phân công'!$C$2:$C$259,3)="14C")*('Phân công'!#REF!="Tiếng Anh")) -> #REF! | AO7: =SUMPRODUCT(('Phân công'!#REF!='Thù lao'!A7)*(RIGHT('Phân công'!$C$2:$C$259,3)="4CA")) -> #REF! | AP7: =SUMPRODUCT(('Phân công'!#REF!='Thù lao'!A7)*(RIGHT('Phân công'!$C$2:$C$259,3)="404")) -> #REF! | AQ7: =SUMPRODUCT(('Phân công'!#REF!='Thù lao'!A7)*(RIGHT('Phân công'!$C$2:$C$259,3)="412")) -> #REF! | AR7: =SUMPRODUCT(('Phân công'!#REF!='Thù lao'!A7)*(RIGHT('Phân công'!$C$2:$C$259,3)="414")) -> #REF! | AS7: =SUMPRODUCT(('Phân công'!#REF!='Thù lao'!A7)*(RIGHT('Phân công'!$C$2:$C$259,3)="04C")*('Phân công'!#REF!="Tiếng Việt")) -> #REF! | AT7: =SUMPRODUCT(('Phân công'!#REF!='Thù lao'!A7)*(RIGHT('Phân công'!$C$2:$C$259,3)="04C")*('Phân công'!#REF!="Tiếng Anh")) -> #REF! | AU7: =SUMPRODUCT(('Phân công'!#REF!='Thù lao'!A7)*(RIGHT('Phân công'!$C$2:$C$259,3)="14C")*('Phân công'!#REF!="Tiếng Việt")) -> #REF! | AV7: =SUMPRODUCT(('Phân công'!#REF!='Thù lao'!A7)*(RIGHT('Phân công'!$C$2:$C$259,3)="14C")*('Phân công'!#REF!="Tiếng Anh")) -> #REF! | AW7: =SUMPRODUCT(('Phân công'!#REF!='Thù lao'!A7)*(RIGHT('Phân công'!$C$2:$C$259,3)="4CA")) -> #REF! | AX7: =AP7+AH7+Z7+R7 -> #REF! | AY7: =AQ7+AI7+AA7+S7 -> #REF! | AZ7: =AR7+AJ7+AB7+T7 -> #REF! | BA7: =AS7+AK7+AC7+U7 -> #REF! | BB7: =AT7+AL7+AD7+V7 -> #REF! | BC7: =AU7+AM7+AE7+W7 -> #REF! | BD7: =AV7+AN7+AF7+X7 -> #REF! | BE7: =AW7+AO7+AG7+Y7 -> #REF! | BF7: =SUMPRODUCT((B7:I7),($B$3:$I$3))*$BF$2 -> #REF! | BG7: =SUMPRODUCT(R7:Y7,$R$3:$Y$3)*$BG$2 -> #REF! | BH7: =SUMPRODUCT(Z7:AG7,$Z$3:$AG$3)*$BH$2 -> #REF! | BI7: =SUMPRODUCT(AH7:AO7,$AH$3:$AO$3)*$BI$2 -> #REF! | BJ7: =SUMPRODUCT(AP7:AW7,$AP$3:$AW$3)*$BJ$2 -> #REF! | BK7: =SUMPRODUCT((J7:Q7),($J$3:$Q$3))*$BK$2 -> #REF! | BL7: =BF7+BK7 -> #REF! | BM7: =SUM(BG7:BJ7) -> #REF! | BN7: =BM7+BK7 -> #REF! | BO7: =BL7+BM7 -> #REF!
A8: ThS Phạm Chí Khoa | B8: =SUMPRODUCT(('Phân công'!$D$2:$D$259=$A8)*('Phân công'!#REF!="X")*(RIGHT('Phân công'!$C$2:$C$259,3)="404")) -> #REF! | C8: =SUMPRODUCT(('Phân công'!$D$2:$D$259=$A8)*('Phân công'!#REF!="X")*(RIGHT('Phân công'!$C$2:$C$259,3)="412")) -> #REF! | D8: =SUMPRODUCT(('Phân công'!$D$2:$D$259=$A8)*('Phân công'!#REF!="X")*(RIGHT('Phân công'!$C$2:$C$259,3)="414")) -> #REF! | E8: =SUMPRODUCT(('Phân công'!$D$2:$D$259=$A8)*('Phân công'!#REF!="X")*(RIGHT('Phân công'!$C$2:$C$259,4)="404C")*('Phân công'!#REF!="Tiếng Việt")) -> #REF! | F8: =SUMPRODUCT(('Phân công'!$D$2:$D$259=$A8)*('Phân công'!#REF!="X")*(RIGHT('Phân công'!$C$2:$C$259,4)="404C")*('Phân công'!#REF!="Tiếng Anh")) -> #REF! | G8: =SUMPRODUCT(('Phân công'!$D$2:$D$259=$A8)*('Phân công'!#REF!="X")*(RIGHT('Phân công'!$C$2:$C$259,4)="414C")*('Phân công'!#REF!="Tiếng Việt")) -> #REF! | H8: =SUMPRODUCT(('Phân công'!$D$2:$D$259=$A8)*('Phân công'!#REF!="X")*(RIGHT('Phân công'!$C$2:$C$259,4)="414C")*('Phân công'!#REF!="Tiếng Anh")) -> #REF! | I8: =SUMPRODUCT(('Phân công'!$D$2:$D$259=$A8)*('Phân công'!#REF!="X")*(RIGHT('Phân công'!$C$2:$C$259,5)="404CA")) -> #REF! | J8: =SUMPRODUCT(('Phân công'!$D$2:$D$259=$A8)*('Phân công'!#REF!="X")*(RIGHT('Phân công'!$C$2:$C$259,3)="404")) -> #REF! | K8: =SUMPRODUCT(('Phân công'!$D$2:$D$259=$A8)*('Phân công'!#REF!="X")*(RIGHT('Phân công'!$C$2:$C$259,3)="412")) -> #REF! | L8: =SUMPRODUCT(('Phân công'!$D$2:$D$259=$A8)*('Phân công'!#REF!="X")*(RIGHT('Phân công'!$C$2:$C$259,3)="414")) -> #REF! | M8: =SUMPRODUCT(('Phân công'!$D$2:$D$259=$A8)*('Phân công'!#REF!="X")*(RIGHT('Phân công'!$C$2:$C$259,3)="04C")*('Phân công'!#REF!="Tiếng Việt")) -> #REF! | N8: =SUMPRODUCT(('Phân công'!$D$2:$D$259=$A8)*('Phân công'!#REF!="X")*(RIGHT('Phân công'!$C$2:$C$259,3)="04C")*('Phân công'!#REF!="Tiếng Anh")) -> #REF! | O8: =SUMPRODUCT(('Phân công'!$D$2:$D$259=$A8)*('Phân công'!#REF!="X")*(RIGHT('Phân công'!$C$2:$C$259,3)="14C")*('Phân công'!#REF!="Tiếng Việt")) -> #REF! | P8: =SUMPRODUCT(('Phân công'!$D$2:$D$259=$A8)*('Phân công'!#REF!="X")*(RIGHT('Phân công'!$C$2:$C$259,3)="14C")*('Phân công'!#REF!="Tiếng Anh")) -> #REF! | Q8: =SUMPRODUCT(('Phân công'!$D$2:$D$259=$A8)*('Phân công'!#REF!="X")*(RIGHT('Phân công'!$C$2:$C$259,3)="4CA")) -> #REF! | R8: =SUMPRODUCT(('Phân công'!#REF!='Thù lao'!A8)*(RIGHT('Phân công'!$C$2:$C$259,3)="404")) -> #REF! | S8: =SUMPRODUCT(('Phân công'!#REF!='Thù lao'!A8)*(RIGHT('Phân công'!$C$2:$C$259,3)="412")) -> #REF! | T8: =SUMPRODUCT(('Phân công'!#REF!='Thù lao'!A8)*(RIGHT('Phân công'!$C$2:$C$259,3)="414")) -> #REF! | U8: =SUMPRODUCT(('Phân công'!#REF!='Thù lao'!A8)*(RIGHT('Phân công'!$C$2:$C$259,3)="04C")*('Phân công'!#REF!="Tiếng Việt")) -> #REF! | V8: =SUMPRODUCT(('Phân công'!#REF!='Thù lao'!A8)*(RIGHT('Phân công'!$C$2:$C$259,3)="04C")*('Phân công'!#REF!="Tiếng Anh")) -> #REF! | W8: =SUMPRODUCT(('Phân công'!#REF!='Thù lao'!A8)*(RIGHT('Phân công'!$C$2:$C$259,3)="14C")*('Phân công'!#REF!="Tiếng Việt")) -> #REF! | X8: =SUMPRODUCT(('Phân công'!#REF!='Thù lao'!A8)*(RIGHT('Phân công'!$C$2:$C$259,3)="14C")*('Phân công'!#REF!="Tiếng Anh")) -> #REF! | Y8: =SUMPRODUCT(('Phân công'!#REF!='Thù lao'!A8)*(RIGHT('Phân công'!$C$10:$C$259,3)="4CA")) -> #REF! | Z8: =SUMPRODUCT(('Phân công'!#REF!='Thù lao'!A8)*(RIGHT('Phân công'!$C$2:$C$259,3)="404")) -> #REF! | AA8: =SUMPRODUCT(('Phân công'!#REF!='Thù lao'!A8)*(RIGHT('Phân công'!$C$2:$C$259,3)="412")) -> #REF! | AB8: =SUMPRODUCT(('Phân công'!#REF!='Thù lao'!A8)*(RIGHT('Phân công'!$C$2:$C$259,3)="414")) -> #REF! | AC8: =SUMPRODUCT(('Phân công'!#REF!='Thù lao'!A8)*(RIGHT('Phân công'!$C$2:$C$259,3)="04C")*('Phân công'!#REF!="Tiếng Việt")) -> #REF! | AD8: =SUMPRODUCT(('Phân công'!#REF!='Thù lao'!A8)*(RIGHT('Phân công'!$C$2:$C$259,3)="04C")*('Phân công'!#REF!="Tiếng Anh")) -> #REF! | AE8: =SUMPRODUCT(('Phân công'!#REF!='Thù lao'!A8)*(RIGHT('Phân công'!$C$2:$C$259,3)="14C")*('Phân công'!#REF!="Tiếng Việt")) -> #REF! | AF8: =SUMPRODUCT(('Phân công'!#REF!='Thù lao'!A8)*(RIGHT('Phân công'!$C$2:$C$259,3)="14C")*('Phân công'!#REF!="Tiếng Anh")) -> #REF! | AG8: =SUMPRODUCT(('Phân công'!#REF!='Thù lao'!A8)*(RIGHT('Phân công'!$C$2:$C$259,3)="4CA")) -> #REF! | AH8: =SUMPRODUCT(('Phân công'!#REF!='Thù lao'!A8)*(RIGHT('Phân công'!$C$2:$C$259,3)="404")) -> #REF! | AI8: =SUMPRODUCT(('Phân công'!#REF!='Thù lao'!A8)*(RIGHT('Phân công'!$C$2:$C$259,3)="412")) -> #REF! | AJ8: =SUMPRODUCT(('Phân công'!#REF!='Thù lao'!A8)*(RIGHT('Phân công'!$C$2:$C$259,3)="414")) -> #REF! | AK8: =SUMPRODUCT(('Phân công'!#REF!='Thù lao'!A8)*(RIGHT('Phân công'!$C$2:$C$259,3)="04C")*('Phân công'!#REF!="Tiếng Việt")) -> #REF! | AL8: =SUMPRODUCT(('Phân công'!#REF!='Thù lao'!A8)*(RIGHT('Phân công'!$C$2:$C$259,3)="04C")*('Phân công'!#REF!="Tiếng Anh")) -> #REF! | AM8: =SUMPRODUCT(('Phân công'!#REF!='Thù lao'!A8)*(RIGHT('Phân công'!$C$2:$C$259,3)="14C")*('Phân công'!#REF!="Tiếng Việt")) -> #REF! | AN8: =SUMPRODUCT(('Phân công'!#REF!='Thù lao'!A8)*(RIGHT('Phân công'!$C$2:$C$259,3)="14C")*('Phân công'!#REF!="Tiếng Anh")) -> #REF! | AO8: =SUMPRODUCT(('Phân công'!#REF!='Thù lao'!A8)*(RIGHT('Phân công'!$C$2:$C$259,3)="4CA")) -> #REF! | AP8: =SUMPRODUCT(('Phân công'!#REF!='Thù lao'!A8)*(RIGHT('Phân công'!$C$2:$C$259,3)="404")) -> #REF! | AQ8: =SUMPRODUCT(('Phân công'!#REF!='Thù lao'!A8)*(RIGHT('Phân công'!$C$2:$C$259,3)="412")) -> #REF! | AR8: =SUMPRODUCT(('Phân công'!#REF!='Thù lao'!A8)*(RIGHT('Phân công'!$C$2:$C$259,3)="414")) -> #REF! | AS8: =SUMPRODUCT(('Phân công'!#REF!='Thù lao'!A8)*(RIGHT('Phân công'!$C$2:$C$259,3)="04C")*('Phân công'!#REF!="Tiếng Việt")) -> #REF! | AT8: =SUMPRODUCT(('Phân công'!#REF!='Thù lao'!A8)*(RIGHT('Phân công'!$C$2:$C$259,3)="04C")*('Phân công'!#REF!="Tiếng Anh")) -> #REF! | AU8: =SUMPRODUCT(('Phân công'!#REF!='Thù lao'!A8)*(RIGHT('Phân công'!$C$2:$C$259,3)="14C")*('Phân công'!#REF!="Tiếng Việt")) -> #REF! | AV8: =SUMPRODUCT(('Phân công'!#REF!='Thù lao'!A8)*(RIGHT('Phân công'!$C$2:$C$259,3)="14C")*('Phân công'!#REF!="Tiếng Anh")) -> #REF! | AW8: =SUMPRODUCT(('Phân công'!#REF!='Thù lao'!A8)*(RIGHT('Phân công'!$C$2:$C$259,3)="4CA")) -> #REF! | AX8: =AP8+AH8+Z8+R8 -> #REF! | AY8: =AQ8+AI8+AA8+S8 -> #REF! | AZ8: =AR8+AJ8+AB8+T8 -> #REF! | BA8: =AS8+AK8+AC8+U8 -> #REF! | BB8: =AT8+AL8+AD8+V8 -> #REF! | BC8: =AU8+AM8+AE8+W8 -> #REF! | BD8: =AV8+AN8+AF8+X8 -> #REF! | BE8: =AW8+AO8+AG8+Y8 -> #REF! | BF8: =SUMPRODUCT((B8:I8),($B$3:$I$3))*$BF$2 -> #REF! | BG8: =SUMPRODUCT(R8:Y8,$R$3:$Y$3)*$BG$2 -> #REF! | BH8: =SUMPRODUCT(Z8:AG8,$Z$3:$AG$3)*$BH$2 -> #REF! | BI8: =SUMPRODUCT(AH8:AO8,$AH$3:$AO$3)*$BI$2 -> #REF! | BJ8: =SUMPRODUCT(AP8:AW8,$AP$3:$AW$3)*$BJ$2 -> #REF! | BK8: =SUMPRODUCT((J8:Q8),($J$3:$Q$3))*$BK$2 -> #REF! | BL8: =BF8+BK8 -> #REF! | BM8: =SUM(BG8:BJ8) -> #REF! | BN8: =BM8+BK8 -> #REF! | BO8: =BL8+BM8 -> #REF!
A9: TS Nguyễn Thanh Liêm | B9: =SUMPRODUCT(('Phân công'!$D$2:$D$259=$A9)*('Phân công'!#REF!="X")*(RIGHT('Phân công'!$C$2:$C$259,3)="404")) -> #REF! | C9: =SUMPRODUCT(('Phân công'!$D$2:$D$259=$A9)*('Phân công'!#REF!="X")*(RIGHT('Phân công'!$C$2:$C$259,3)="412")) -> #REF! | D9: =SUMPRODUCT(('Phân công'!$D$2:$D$259=$A9)*('Phân công'!#REF!="X")*(RIGHT('Phân công'!$C$2:$C$259,3)="414")) -> #REF! | E9: =SUMPRODUCT(('Phân công'!$D$2:$D$259=$A9)*('Phân công'!#REF!="X")*(RIGHT('Phân công'!$C$2:$C$259,4)="404C")*('Phân công'!#REF!="Tiếng Việt")) -> #REF! | F9: =SUMPRODUCT(('Phân công'!$D$2:$D$259=$A9)*('Phân công'!#REF!="X")*(RIGHT('Phân công'!$C$2:$C$259,4)="404C")*('Phân công'!#REF!="Tiếng Anh")) -> #REF! | G9: =SUMPRODUCT(('Phân công'!$D$2:$D$259=$A9)*('Phân công'!#REF!="X")*(RIGHT('Phân công'!$C$2:$C$259,4)="414C")*('Phân công'!#REF!="Tiếng Việt")) -> #REF! | H9: =SUMPRODUCT(('Phân công'!$D$2:$D$259=$A9)*('Phân công'!#REF!="X")*(RIGHT('Phân công'!$C$2:$C$259,4)="414C")*('Phân công'!#REF!="Tiếng Anh")) -> #REF! | I9: =SUMPRODUCT(('Phân công'!$D$2:$D$259=$A9)*('Phân công'!#REF!="X")*(RIGHT('Phân công'!$C$2:$C$259,5)="404CA")) -> #REF! | J9: =SUMPRODUCT(('Phân công'!$D$2:$D$259=$A9)*('Phân công'!#REF!="X")*(RIGHT('Phân công'!$C$2:$C$259,3)="404")) -> #REF! | K9: =SUMPRODUCT(('Phân công'!$D$2:$D$259=$A9)*('Phân công'!#REF!="X")*(RIGHT('Phân công'!$C$2:$C$259,3)="412")) -> #REF! | L9: =SUMPRODUCT(('Phân công'!$D$2:$D$259=$A9)*('Phân công'!#REF!="X")*(RIGHT('Phân công'!$C$2:$C$259,3)="414")) -> #REF! | M9: =SUMPRODUCT(('Phân công'!$D$2:$D$259=$A9)*('Phân công'!#REF!="X")*(RIGHT('Phân công'!$C$2:$C$259,3)="04C")*('Phân công'!#REF!="Tiếng Việt")) -> #REF! | N9: =SUMPRODUCT(('Phân công'!$D$2:$D$259=$A9)*('Phân công'!#REF!="X")*(RIGHT('Phân công'!$C$2:$C$259,3)="04C")*('Phân công'!#REF!="Tiếng Anh")) -> #REF! | O9: =SUMPRODUCT(('Phân công'!$D$2:$D$259=$A9)*('Phân công'!#REF!="X")*(RIGHT('Phân công'!$C$2:$C$259,3)="14C")*('Phân công'!#REF!="Tiếng Việt")) -> #REF! | P9: =SUMPRODUCT(('Phân công'!$D$2:$D$259=$A9)*('Phân công'!#REF!="X")*(RIGHT('Phân công'!$C$2:$C$259,3)="14C")*('Phân công'!#REF!="Tiếng Anh")) -> #REF! | Q9: =SUMPRODUCT(('Phân công'!$D$2:$D$259=$A9)*('Phân công'!#REF!="X")*(RIGHT('Phân công'!$C$2:$C$259,3)="4CA")) -> #REF! | R9: =SUMPRODUCT(('Phân công'!#REF!='Thù lao'!A9)*(RIGHT('Phân công'!$C$2:$C$259,3)="404")) -> #REF! | S9: =SUMPRODUCT(('Phân công'!#REF!='Thù lao'!A9)*(RIGHT('Phân công'!$C$2:$C$259,3)="412")) -> #REF! | T9: =SUMPRODUCT(('Phân công'!#REF!='Thù lao'!A9)*(RIGHT('Phân công'!$C$2:$C$259,3)="414")) -> #REF! | U9: =SUMPRODUCT(('Phân công'!#REF!='Thù lao'!A9)*(RIGHT('Phân công'!$C$2:$C$259,3)="04C")*('Phân công'!#REF!="Tiếng Việt")) -> #REF! | V9: =SUMPRODUCT(('Phân công'!#REF!='Thù lao'!A9)*(RIGHT('Phân công'!$C$2:$C$259,3)="04C")*('Phân công'!#REF!="Tiếng Anh")) -> #REF! | W9: =SUMPRODUCT(('Phân công'!#REF!='Thù lao'!A9)*(RIGHT('Phân công'!$C$2:$C$259,3)="14C")*('Phân công'!#REF!="Tiếng Việt")) -> #REF! | X9: =SUMPRODUCT(('Phân công'!#REF!='Thù lao'!A9)*(RIGHT('Phân công'!$C$2:$C$259,3)="14C")*('Phân công'!#REF!="Tiếng Anh")) -> #REF! | Y9: =SUMPRODUCT(('Phân công'!#REF!='Thù lao'!A9)*(RIGHT('Phân công'!$C$10:$C$259,3)="4CA")) -> #REF! | Z9: =SUMPRODUCT(('Phân công'!#REF!='Thù lao'!A9)*(RIGHT('Phân công'!$C$2:$C$259,3)="404")) -> #REF! | AA9: =SUMPRODUCT(('Phân công'!#REF!='Thù lao'!A9)*(RIGHT('Phân công'!$C$2:$C$259,3)="412")) -> #REF! | AB9: =SUMPRODUCT(('Phân công'!#REF!='Thù lao'!A9)*(RIGHT('Phân công'!$C$2:$C$259,3)="414")) -> #REF! | AC9: =SUMPRODUCT(('Phân công'!#REF!='Thù lao'!A9)*(RIGHT('Phân công'!$C$2:$C$259,3)="04C")*('Phân công'!#REF!="Tiếng Việt")) -> #REF! | AD9: =SUMPRODUCT(('Phân công'!#REF!='Thù lao'!A9)*(RIGHT('Phân công'!$C$2:$C$259,3)="04C")*('Phân công'!#REF!="Tiếng Anh")) -> #REF! | AE9: =SUMPRODUCT(('Phân công'!#REF!='Thù lao'!A9)*(RIGHT('Phân công'!$C$2:$C$259,3)="14C")*('Phân công'!#REF!="Tiếng Việt")) -> #REF! | AF9: =SUMPRODUCT(('Phân công'!#REF!='Thù lao'!A9)*(RIGHT('Phân công'!$C$2:$C$259,3)="14C")*('Phân công'!#REF!="Tiếng Anh")) -> #REF! | AG9: =SUMPRODUCT(('Phân công'!#REF!='Thù lao'!A9)*(RIGHT('Phân công'!$C$2:$C$259,3)="4CA")) -> #REF! | AH9: =SUMPRODUCT(('Phân công'!#REF!='Thù lao'!A9)*(RIGHT('Phân công'!$C$2:$C$259,3)="404")) -> #REF! | AI9: =SUMPRODUCT(('Phân công'!#REF!='Thù lao'!A9)*(RIGHT('Phân công'!$C$2:$C$259,3)="412")) -> #REF! | AJ9: =SUMPRODUCT(('Phân công'!#REF!='Thù lao'!A9)*(RIGHT('Phân công'!$C$2:$C$259,3)="414")) -> #REF! | AK9: =SUMPRODUCT(('Phân công'!#REF!='Thù lao'!A9)*(RIGHT('Phân công'!$C$2:$C$259,3)="04C")*('Phân công'!#REF!="Tiếng Việt")) -> #REF! | AL9: =SUMPRODUCT(('Phân công'!#REF!='Thù lao'!A9)*(RIGHT('Phân công'!$C$2:$C$259,3)="04C")*('Phân công'!#REF!="Tiếng Anh")) -> #REF! | AM9: =SUMPRODUCT(('Phân công'!#REF!='Thù lao'!A9)*(RIGHT('Phân công'!$C$2:$C$259,3)="14C")*('Phân công'!#REF!="Tiếng Việt")) -> #REF! | AN9: =SUMPRODUCT(('Phân công'!#REF!='Thù lao'!A9)*(RIGHT('Phân công'!$C$2:$C$259,3)="14C")*('Phân công'!#REF!="Tiếng Anh")) -> #REF! | AO9: =SUMPRODUCT(('Phân công'!#REF!='Thù lao'!A9)*(RIGHT('Phân công'!$C$2:$C$259,3)="4CA")) -> #REF! | AP9: =SUMPRODUCT(('Phân công'!#REF!='Thù lao'!A9)*(RIGHT('Phân công'!$C$2:$C$259,3)="404")) -> #REF! | AQ9: =SUMPRODUCT(('Phân công'!#REF!='Thù lao'!A9)*(RIGHT('Phân công'!$C$2:$C$259,3)="412")) -> #REF! | AR9: =SUMPRODUCT(('Phân công'!#REF!='Thù lao'!A9)*(RIGHT('Phân công'!$C$2:$C$259,3)="414")) -> #REF! | AS9: =SUMPRODUCT(('Phân công'!#REF!='Thù lao'!A9)*(RIGHT('Phân công'!$C$2:$C$259,3)="04C")*('Phân công'!#REF!="Tiếng Việt")) -> #REF! | AT9: =SUMPRODUCT(('Phân công'!#REF!='Thù lao'!A9)*(RIGHT('Phân công'!$C$2:$C$259,3)="04C")*('Phân công'!#REF!="Tiếng Anh")) -> #REF! | AU9: =SUMPRODUCT(('Phân công'!#REF!='Thù lao'!A9)*(RIGHT('Phân công'!$C$2:$C$259,3)="14C")*('Phân công'!#REF!="Tiếng Việt")) -> #REF! | AV9: =SUMPRODUCT(('Phân công'!#REF!='Thù lao'!A9)*(RIGHT('Phân công'!$C$2:$C$259,3)="14C")*('Phân công'!#REF!="Tiếng Anh")) -> #REF! | AW9: =SUMPRODUCT(('Phân công'!#REF!='Thù lao'!A9)*(RIGHT('Phân công'!$C$2:$C$259,3)="4CA")) -> #REF! | AX9: =AP9+AH9+Z9+R9 -> #REF! | AY9: =AQ9+AI9+AA9+S9 -> #REF! | AZ9: =AR9+AJ9+AB9+T9 -> #REF! | BA9: =AS9+AK9+AC9+U9 -> #REF! | BB9: =AT9+AL9+AD9+V9 -> #REF! | BC9: =AU9+AM9+AE9+W9 -> #REF! | BD9: =AV9+AN9+AF9+X9 -> #REF! | BE9: =AW9+AO9+AG9+Y9 -> #REF! | BF9: =SUMPRODUCT((B9:I9),($B$3:$I$3))*$BF$2 -> #REF! | BG9: =SUMPRODUCT(R9:Y9,$R$3:$Y$3)*$BG$2 -> #REF! | BH9: =SUMPRODUCT(Z9:AG9,$Z$3:$AG$3)*$BH$2 -> #REF! | BI9: =SUMPRODUCT(AH9:AO9,$AH$3:$AO$3)*$BI$2 -> #REF! | BJ9: =SUMPRODUCT(AP9:AW9,$AP$3:$AW$3)*$BJ$2 -> #REF! | BK9: =SUMPRODUCT((J9:Q9),($J$3:$Q$3))*$BK$2 -> #REF! | BL9: =BF9+BK9 -> #REF! | BM9: =SUM(BG9:BJ9) -> #REF! | BN9: =BM9+BK9 -> #REF! | BO9: =BL9+BM9 -> #REF!
A10: PGS. TS Nguyễn Thị Ánh Như | B10: =SUMPRODUCT(('Phân công'!$D$2:$D$259=$A10)*('Phân công'!#REF!="X")*(RIGHT('Phân công'!$C$2:$C$259,3)="404")) -> #REF! | C10: =SUMPRODUCT(('Phân công'!$D$2:$D$259=$A10)*('Phân công'!#REF!="X")*(RIGHT('Phân công'!$C$2:$C$259,3)="412")) -> #REF! | D10: =SUMPRODUCT(('Phân công'!$D$2:$D$259=$A10)*('Phân công'!#REF!="X")*(RIGHT('Phân công'!$C$2:$C$259,3)="414")) -> #REF! | E10: =SUMPRODUCT(('Phân công'!$D$2:$D$259=$A10)*('Phân công'!#REF!="X")*(RIGHT('Phân công'!$C$2:$C$259,4)="404C")*('Phân công'!#REF!="Tiếng Việt")) -> #REF! | F10: =SUMPRODUCT(('Phân công'!$D$2:$D$259=$A10)*('Phân công'!#REF!="X")*(RIGHT('Phân công'!$C$2:$C$259,4)="404C")*('Phân công'!#REF!="Tiếng Anh")) -> #REF! | G10: =SUMPRODUCT(('Phân công'!$D$2:$D$259=$A10)*('Phân công'!#REF!="X")*(RIGHT('Phân công'!$C$2:$C$259,4)="414C")*('Phân công'!#REF!="Tiếng Việt")) -> #REF! | H10: =SUMPRODUCT(('Phân công'!$D$2:$D$259=$A10)*('Phân công'!#REF!="X")*(RIGHT('Phân công'!$C$2:$C$259,4)="414C")*('Phân công'!#REF!="Tiếng Anh")) -> #REF! | I10: =SUMPRODUCT(('Phân công'!$D$2:$D$259=$A10)*('Phân công'!#REF!="X")*(RIGHT('Phân công'!$C$2:$C$259,5)="404CA")) -> #REF! | J10: =SUMPRODUCT(('Phân công'!$D$2:$D$259=$A10)*('Phân công'!#REF!="X")*(RIGHT('Phân công'!$C$2:$C$259,3)="404")) -> #REF! | K10: =SUMPRODUCT(('Phân công'!$D$2:$D$259=$A10)*('Phân công'!#REF!="X")*(RIGHT('Phân công'!$C$2:$C$259,3)="412")) -> #REF! | L10: =SUMPRODUCT(('Phân công'!$D$2:$D$259=$A10)*('Phân công'!#REF!="X")*(RIGHT('Phân công'!$C$2:$C$259,3)="414")) -> #REF! | M10: =SUMPRODUCT(('Phân công'!$D$2:$D$259=$A10)*('Phân công'!#REF!="X")*(RIGHT('Phân công'!$C$2:$C$259,3)="04C")*('Phân công'!#REF!="Tiếng Việt")) -> #REF! | N10: =SUMPRODUCT(('Phân công'!$D$2:$D$259=$A10)*('Phân công'!#REF!="X")*(RIGHT('Phân công'!$C$2:$C$259,3)="04C")*('Phân công'!#REF!="Tiếng Anh")) -> #REF! | O10: =SUMPRODUCT(('Phân công'!$D$2:$D$259=$A10)*('Phân công'!#REF!="X")*(RIGHT('Phân công'!$C$2:$C$259,3)="14C")*('Phân công'!#REF!="Tiếng Việt")) -> #REF! | P10: =SUMPRODUCT(('Phân công'!$D$2:$D$259=$A10)*('Phân công'!#REF!="X")*(RIGHT('Phân công'!$C$2:$C$259,3)="14C")*('Phân công'!#REF!="Tiếng Anh")) -> #REF! | Q10: =SUMPRODUCT(('Phân công'!$D$2:$D$259=$A10)*('Phân công'!#REF!="X")*(RIGHT('Phân công'!$C$2:$C$259,3)="4CA")) -> #REF! | R10: =SUMPRODUCT(('Phân công'!#REF!='Thù lao'!A10)*(RIGHT('Phân công'!$C$2:$C$259,3)="404")) -> #REF! | S10: =SUMPRODUCT(('Phân công'!#REF!='Thù lao'!A10)*(RIGHT('Phân công'!$C$2:$C$259,3)="412")) -> #REF! | T10: =SUMPRODUCT(('Phân công'!#REF!='Thù lao'!A10)*(RIGHT('Phân công'!$C$2:$C$259,3)="414")) -> #REF! | U10: =SUMPRODUCT(('Phân công'!#REF!='Thù lao'!A10)*(RIGHT('Phân công'!$C$2:$C$259,3)="04C")*('Phân công'!#REF!="Tiếng Việt")) -> #REF! | V10: =SUMPRODUCT(('Phân công'!#REF!='Thù lao'!A10)*(RIGHT('Phân công'!$C$2:$C$259,3)="04C")*('Phân công'!#REF!="Tiếng Anh")) -> #REF! | W10: =SUMPRODUCT(('Phân công'!#REF!='Thù lao'!A10)*(RIGHT('Phân công'!$C$2:$C$259,3)="14C")*('Phân công'!#REF!="Tiếng Việt")) -> #REF! | X10: =SUMPRODUCT(('Phân công'!#REF!='Thù lao'!A10)*(RIGHT('Phân công'!$C$2:$C$259,3)="14C")*('Phân công'!#REF!="Tiếng Anh")) -> #REF! | Y10: =SUMPRODUCT(('Phân công'!#REF!='Thù lao'!A10)*(RIGHT('Phân công'!$C$10:$C$259,3)="4CA")) -> #REF! | Z10: =SUMPRODUCT(('Phân công'!#REF!='Thù lao'!A10)*(RIGHT('Phân công'!$C$2:$C$259,3)="404")) -> #REF! | AA10: =SUMPRODUCT(('Phân công'!#REF!='Thù lao'!A10)*(RIGHT('Phân công'!$C$2:$C$259,3)="412")) -> #REF! | AB10: =SUMPRODUCT(('Phân công'!#REF!='Thù lao'!A10)*(RIGHT('Phân công'!$C$2:$C$259,3)="414")) -> #REF! | AC10: =SUMPRODUCT(('Phân công'!#REF!='Thù lao'!A10)*(RIGHT('Phân công'!$C$2:$C$259,3)="04C")*('Phân công'!#REF!="Tiếng Việt")) -> #REF! | AD10: =SUMPRODUCT(('Phân công'!#REF!='Thù lao'!A10)*(RIGHT('Phân công'!$C$2:$C$259,3)="04C")*('Phân công'!#REF!="Tiếng Anh")) -> #REF! | AE10: =SUMPRODUCT(('Phân công'!#REF!='Thù lao'!A10)*(RIGHT('Phân công'!$C$2:$C$259,3)="14C")*('Phân công'!#REF!="Tiếng Việt")) -> #REF! | AF10: =SUMPRODUCT(('Phân công'!#REF!='Thù lao'!A10)*(RIGHT('Phân công'!$C$2:$C$259,3)="14C")*('Phân công'!#REF!="Tiếng Anh")) -> #REF! | AG10: =SUMPRODUCT(('Phân công'!#REF!='Thù lao'!A10)*(RIGHT('Phân công'!$C$2:$C$259,3)="4CA")) -> #REF! | AH10: =SUMPRODUCT(('Phân công'!#REF!='Thù lao'!A10)*(RIGHT('Phân công'!$C$2:$C$259,3)="404")) -> #REF! | AI10: =SUMPRODUCT(('Phân công'!#REF!='Thù lao'!A10)*(RIGHT('Phân công'!$C$2:$C$259,3)="412")) -> #REF! | AJ10: =SUMPRODUCT(('Phân công'!#REF!='Thù lao'!A10)*(RIGHT('Phân công'!$C$2:$C$259,3)="414")) -> #REF! | AK10: =SUMPRODUCT(('Phân công'!#REF!='Thù lao'!A10)*(RIGHT('Phân công'!$C$2:$C$259,3)="04C")*('Phân công'!#REF!="Tiếng Việt")) -> #REF! | AL10: =SUMPRODUCT(('Phân công'!#REF!='Thù lao'!A10)*(RIGHT('Phân công'!$C$2:$C$259,3)="04C")*('Phân công'!#REF!="Tiếng Anh")) -> #REF! | AM10: =SUMPRODUCT(('Phân công'!#REF!='Thù lao'!A10)*(RIGHT('Phân công'!$C$2:$C$259,3)="14C")*('Phân công'!#REF!="Tiếng Việt")) -> #REF! | AN10: =SUMPRODUCT(('Phân công'!#REF!='Thù lao'!A10)*(RIGHT('Phân công'!$C$2:$C$259,3)="14C")*('Phân công'!#REF!="Tiếng Anh")) -> #REF! | AO10: =SUMPRODUCT(('Phân công'!#REF!='Thù lao'!A10)*(RIGHT('Phân công'!$C$2:$C$259,3)="4CA")) -> #REF! | AP10: =SUMPRODUCT(('Phân công'!#REF!='Thù lao'!A10)*(RIGHT('Phân công'!$C$2:$C$259,3)="404")) -> #REF! | AQ10: =SUMPRODUCT(('Phân công'!#REF!='Thù lao'!A10)*(RIGHT('Phân công'!$C$2:$C$259,3)="412")) -> #REF! | AR10: =SUMPRODUCT(('Phân công'!#REF!='Thù lao'!A10)*(RIGHT('Phân công'!$C$2:$C$259,3)="414")) -> #REF! | AS10: =SUMPRODUCT(('Phân công'!#REF!='Thù lao'!A10)*(RIGHT('Phân công'!$C$2:$C$259,3)="04C")*('Phân công'!#REF!="Tiếng Việt")) -> #REF! | AT10: =SUMPRODUCT(('Phân công'!#REF!='Thù lao'!A10)*(RIGHT('Phân công'!$C$2:$C$259,3)="04C")*('Phân công'!#REF!="Tiếng Anh")) -> #REF! | AU10: =SUMPRODUCT(('Phân công'!#REF!='Thù lao'!A10)*(RIGHT('Phân công'!$C$2:$C$259,3)="14C")*('Phân công'!#REF!="Tiếng Việt")) -> #REF! | AV10: =SUMPRODUCT(('Phân công'!#REF!='Thù lao'!A10)*(RIGHT('Phân công'!$C$2:$C$259,3)="14C")*('Phân công'!#REF!="Tiếng Anh")) -> #REF! | AW10: =SUMPRODUCT(('Phân công'!#REF!='Thù lao'!A10)*(RIGHT('Phân công'!$C$2:$C$259,3)="4CA")) -> #REF! | AX10: =AP10+AH10+Z10+R10 -> #REF! | AY10: =AQ10+AI10+AA10+S10 -> #REF! | AZ10: =AR10+AJ10+AB10+T10 -> #REF! | BA10: =AS10+AK10+AC10+U10 -> #REF! | BB10: =AT10+AL10+AD10+V10 -> #REF! | BC10: =AU10+AM10+AE10+W10 -> #REF! | BD10: =AV10+AN10+AF10+X10 -> #REF! | BE10: =AW10+AO10+AG10+Y10 -> #REF! | BF10: =SUMPRODUCT((B10:I10),($B$3:$I$3))*$BF$2 -> #REF! | BG10: =SUMPRODUCT(R10:Y10,$R$3:$Y$3)*$BG$2 -> #REF! | BH10: =SUMPRODUCT(Z10:AG10,$Z$3:$AG$3)*$BH$2 -> #REF! | BI10: =SUMPRODUCT(AH10:AO10,$AH$3:$AO$3)*$BI$2 -> #REF! | BJ10: =SUMPRODUCT(AP10:AW10,$AP$3:$AW$3)*$BJ$2 -> #REF! | BK10: =SUMPRODUCT((J10:Q10),($J$3:$Q$3))*$BK$2 -> #REF! | BL10: =BF10+BK10 -> #REF! | BM10: =SUM(BG10:BJ10) -> #REF! | BN10: =BM10+BK10 -> #REF! | BO10: =BL10+BM10 -> #REF!
A11: ThS Phan Huy Tâm | B11: =SUMPRODUCT(('Phân công'!$D$2:$D$259=$A11)*('Phân công'!#REF!="X")*(RIGHT('Phân công'!$C$2:$C$259,3)="404")) -> #REF! | C11: =SUMPRODUCT(('Phân công'!$D$2:$D$259=$A11)*('Phân công'!#REF!="X")*(RIGHT('Phân công'!$C$2:$C$259,3)="412")) -> #REF! | D11: =SUMPRODUCT(('Phân công'!$D$2:$D$259=$A11)*('Phân công'!#REF!="X")*(RIGHT('Phân công'!$C$2:$C$259,3)="414")) -> #REF! | E11: =SUMPRODUCT(('Phân công'!$D$2:$D$259=$A11)*('Phân công'!#REF!="X")*(RIGHT('Phân công'!$C$2:$C$259,4)="404C")*('Phân công'!#REF!="Tiếng Việt")) -> #REF! | F11: =SUMPRODUCT(('Phân công'!$D$2:$D$259=$A11)*('Phân công'!#REF!="X")*(RIGHT('Phân công'!$C$2:$C$259,4)="404C")*('Phân công'!#REF!="Tiếng Anh")) -> #REF! | G11: =SUMPRODUCT(('Phân công'!$D$2:$D$259=$A11)*('Phân công'!#REF!="X")*(RIGHT('Phân công'!$C$2:$C$259,4)="414C")*('Phân công'!#REF!="Tiếng Việt")) -> #REF! | H11: =SUMPRODUCT(('Phân công'!$D$2:$D$259=$A11)*('Phân công'!#REF!="X")*(RIGHT('Phân công'!$C$2:$C$259,4)="414C")*('Phân công'!#REF!="Tiếng Anh")) -> #REF! | I11: =SUMPRODUCT(('Phân công'!$D$2:$D$259=$A11)*('Phân công'!#REF!="X")*(RIGHT('Phân công'!$C$2:$C$259,5)="404CA")) -> #REF! | J11: =SUMPRODUCT(('Phân công'!$D$2:$D$259=$A11)*('Phân công'!#REF!="X")*(RIGHT('Phân công'!$C$2:$C$259,3)="404")) -> #REF! | K11: =SUMPRODUCT(('Phân công'!$D$2:$D$259=$A11)*('Phân công'!#REF!="X")*(RIGHT('Phân công'!$C$2:$C$259,3)="412")) -> #REF! | L11: =SUMPRODUCT(('Phân công'!$D$2:$D$259=$A11)*('Phân công'!#REF!="X")*(RIGHT('Phân công'!$C$2:$C$259,3)="414")) -> #REF! | M11: =SUMPRODUCT(('Phân công'!$D$2:$D$259=$A11)*('Phân công'!#REF!="X")*(RIGHT('Phân công'!$C$2:$C$259,3)="04C")*('Phân công'!#REF!="Tiếng Việt")) -> #REF! | N11: =SUMPRODUCT(('Phân công'!$D$2:$D$259=$A11)*('Phân công'!#REF!="X")*(RIGHT('Phân công'!$C$2:$C$259,3)="04C")*('Phân công'!#REF!="Tiếng Anh")) -> #REF! | O11: =SUMPRODUCT(('Phân công'!$D$2:$D$259=$A11)*('Phân công'!#REF!="X")*(RIGHT('Phân công'!$C$2:$C$259,3)="14C")*('Phân công'!#REF!="Tiếng Việt")) -> #REF! | P11: =SUMPRODUCT(('Phân công'!$D$2:$D$259=$A11)*('Phân công'!#REF!="X")*(RIGHT('Phân công'!$C$2:$C$259,3)="14C")*('Phân công'!#REF!="Tiếng Anh")) -> #REF! | Q11: =SUMPRODUCT(('Phân công'!$D$2:$D$259=$A11)*('Phân công'!#REF!="X")*(RIGHT('Phân công'!$C$2:$C$259,3)="4CA")) -> #REF! | R11: =SUMPRODUCT(('Phân công'!#REF!='Thù lao'!A11)*(RIGHT('Phân công'!$C$2:$C$259,3)="404")) -> #REF! | S11: =SUMPRODUCT(('Phân công'!#REF!='Thù lao'!A11)*(RIGHT('Phân công'!$C$2:$C$259,3)="412")) -> #REF! | T11: =SUMPRODUCT(('Phân công'!#REF!='Thù lao'!A11)*(RIGHT('Phân công'!$C$2:$C$259,3)="414")) -> #REF! | U11: =SUMPRODUCT(('Phân công'!#REF!='Thù lao'!A11)*(RIGHT('Phân công'!$C$2:$C$259,3)="04C")*('Phân công'!#REF!="Tiếng Việt")) -> #REF! | V11: =SUMPRODUCT(('Phân công'!#REF!='Thù lao'!A11)*(RIGHT('Phân công'!$C$2:$C$259,3)="04C")*('Phân công'!#REF!="Tiếng Anh")) -> #REF! | W11: =SUMPRODUCT(('Phân công'!#REF!='Thù lao'!A11)*(RIGHT('Phân công'!$C$2:$C$259,3)="14C")*('Phân công'!#REF!="Tiếng Việt")) -> #REF! | X11: =SUMPRODUCT(('Phân công'!#REF!='Thù lao'!A11)*(RIGHT('Phân công'!$C$2:$C$259,3)="14C")*('Phân công'!#REF!="Tiếng Anh")) -> #REF! | Y11: =SUMPRODUCT(('Phân công'!#REF!='Thù lao'!A11)*(RIGHT('Phân công'!$C$10:$C$259,3)="4CA")) -> #REF! | Z11: =SUMPRODUCT(('Phân công'!#REF!='Thù lao'!A11)*(RIGHT('Phân công'!$C$2:$C$259,3)="404")) -> #REF! | AA11: =SUMPRODUCT(('Phân công'!#REF!='Thù lao'!A11)*(RIGHT('Phân công'!$C$2:$C$259,3)="412")) -> #REF! | AB11: =SUMPRODUCT(('Phân công'!#REF!='Thù lao'!A11)*(RIGHT('Phân công'!$C$2:$C$259,3)="414")) -> #REF! | AC11: =SUMPRODUCT(('Phân công'!#REF!='Thù lao'!A11)*(RIGHT('Phân công'!$C$2:$C$259,3)="04C")*('Phân công'!#REF!="Tiếng Việt")) -> #REF! | AD11: =SUMPRODUCT(('Phân công'!#REF!='Thù lao'!A11)*(RIGHT('Phân công'!$C$2:$C$259,3)="04C")*('Phân công'!#REF!="Tiếng Anh")) -> #REF! | AE11: =SUMPRODUCT(('Phân công'!#REF!='Thù lao'!A11)*(RIGHT('Phân công'!$C$2:$C$259,3)="14C")*('Phân công'!#REF!="Tiếng Việt")) -> #REF! | AF11: =SUMPRODUCT(('Phân công'!#REF!='Thù lao'!A11)*(RIGHT('Phân công'!$C$2:$C$259,3)="14C")*('Phân công'!#REF!="Tiếng Anh")) -> #REF! | AG11: =SUMPRODUCT(('Phân công'!#REF!='Thù lao'!A11)*(RIGHT('Phân công'!$C$2:$C$259,3)="4CA")) -> #REF! | AH11: =SUMPRODUCT(('Phân công'!#REF!='Thù lao'!A11)*(RIGHT('Phân công'!$C$2:$C$259,3)="404")) -> #REF! | AI11: =SUMPRODUCT(('Phân công'!#REF!='Thù lao'!A11)*(RIGHT('Phân công'!$C$2:$C$259,3)="412")) -> #REF! | AJ11: =SUMPRODUCT(('Phân công'!#REF!='Thù lao'!A11)*(RIGHT('Phân công'!$C$2:$C$259,3)="414")) -> #REF! | AK11: =SUMPRODUCT(('Phân công'!#REF!='Thù lao'!A11)*(RIGHT('Phân công'!$C$2:$C$259,3)="04C")*('Phân công'!#REF!="Tiếng Việt")) -> #REF! | AL11: =SUMPRODUCT(('Phân công'!#REF!='Thù lao'!A11)*(RIGHT('Phân công'!$C$2:$C$259,3)="04C")*('Phân công'!#REF!="Tiếng Anh")) -> #REF! | AM11: =SUMPRODUCT(('Phân công'!#REF!='Thù lao'!A11)*(RIGHT('Phân công'!$C$2:$C$259,3)="14C")*('Phân công'!#REF!="Tiếng Việt")) -> #REF! | AN11: =SUMPRODUCT(('Phân công'!#REF!='Thù lao'!A11)*(RIGHT('Phân công'!$C$2:$C$259,3)="14C")*('Phân công'!#REF!="Tiếng Anh")) -> #REF! | AO11: =SUMPRODUCT(('Phân công'!#REF!='Thù lao'!A11)*(RIGHT('Phân công'!$C$2:$C$259,3)="4CA")) -> #REF! | AP11: =SUMPRODUCT(('Phân công'!#REF!='Thù lao'!A11)*(RIGHT('Phân công'!$C$2:$C$259,3)="404")) -> #REF! | AQ11: =SUMPRODUCT(('Phân công'!#REF!='Thù lao'!A11)*(RIGHT('Phân công'!$C$2:$C$259,3)="412")) -> #REF! | AR11: =SUMPRODUCT(('Phân công'!#REF!='Thù lao'!A11)*(RIGHT('Phân công'!$C$2:$C$259,3)="414")) -> #REF! | AS11: =SUMPRODUCT(('Phân công'!#REF!='Thù lao'!A11)*(RIGHT('Phân công'!$C$2:$C$259,3)="04C")*('Phân công'!#REF!="Tiếng Việt")) -> #REF! | AT11: =SUMPRODUCT(('Phân công'!#REF!='Thù lao'!A11)*(RIGHT('Phân công'!$C$2:$C$259,3)="04C")*('Phân công'!#REF!="Tiếng Anh")) -> #REF! | AU11: =SUMPRODUCT(('Phân công'!#REF!='Thù lao'!A11)*(RIGHT('Phân công'!$C$2:$C$259,3)="14C")*('Phân công'!#REF!="Tiếng Việt")) -> #REF! | AV11: =SUMPRODUCT(('Phân công'!#REF!='Thù lao'!A11)*(RIGHT('Phân công'!$C$2:$C$259,3)="14C")*('Phân công'!#REF!="Tiếng Anh")) -> #REF! | AW11: =SUMPRODUCT(('Phân công'!#REF!='Thù lao'!A11)*(RIGHT('Phân công'!$C$2:$C$259,3)="4CA")) -> #REF! | AX11: =AP11+AH11+Z11+R11 -> #REF! | AY11: =AQ11+AI11+AA11+S11 -> #REF! | AZ11: =AR11+AJ11+AB11+T11 -> #REF! | BA11: =AS11+AK11+AC11+U11 -> #REF! | BB11: =AT11+AL11+AD11+V11 -> #REF! | BC11: =AU11+AM11+AE11+W11 -> #REF! | BD11: =AV11+AN11+AF11+X11 -> #REF! | BE11: =AW11+AO11+AG11+Y11 -> #REF! | BF11: =SUMPRODUCT((B11:I11),($B$3:$I$3))*$BF$2 -> #REF! | BG11: =SUMPRODUCT(R11:Y11,$R$3:$Y$3)*$BG$2 -> #REF! | BH11: =SUMPRODUCT(Z11:AG11,$Z$3:$AG$3)*$BH$2 -> #REF! | BI11: =SUMPRODUCT(AH11:AO11,$AH$3:$AO$3)*$BI$2 -> #REF! | BJ11: =SUMPRODUCT(AP11:AW11,$AP$3:$AW$3)*$BJ$2 -> #REF! | BK11: =SUMPRODUCT((J11:Q11),($J$3:$Q$3))*$BK$2 -> #REF! | BL11: =BF11+BK11 -> #REF! | BM11: =SUM(BG11:BJ11) -> #REF! | BN11: =BM11+BK11 -> #REF! | BO11: =BL11+BM11 -> #REF!
A12: ThS Ngô Phú Thanh | B12: =SUMPRODUCT(('Phân công'!$D$2:$D$259=$A12)*('Phân công'!#REF!="X")*(RIGHT('Phân công'!$C$2:$C$259,3)="404")) -> #REF! | C12: =SUMPRODUCT(('Phân công'!$D$2:$D$259=$A12)*('Phân công'!#REF!="X")*(RIGHT('Phân công'!$C$2:$C$259,3)="412")) -> #REF! | D12: =SUMPRODUCT(('Phân công'!$D$2:$D$259=$A12)*('Phân công'!#REF!="X")*(RIGHT('Phân công'!$C$2:$C$259,3)="414")) -> #REF! | E12: =SUMPRODUCT(('Phân công'!$D$2:$D$259=$A12)*('Phân công'!#REF!="X")*(RIGHT('Phân công'!$C$2:$C$259,4)="404C")*('Phân công'!#REF!="Tiếng Việt")) -> #REF! | F12: =SUMPRODUCT(('Phân công'!$D$2:$D$259=$A12)*('Phân công'!#REF!="X")*(RIGHT('Phân công'!$C$2:$C$259,4)="404C")*('Phân công'!#REF!="Tiếng Anh")) -> #REF! | G12: =SUMPRODUCT(('Phân công'!$D$2:$D$259=$A12)*('Phân công'!#REF!="X")*(RIGHT('Phân công'!$C$2:$C$259,4)="414C")*('Phân công'!#REF!="Tiếng Việt")) -> #REF! | H12: =SUMPRODUCT(('Phân công'!$D$2:$D$259=$A12)*('Phân công'!#REF!="X")*(RIGHT('Phân công'!$C$2:$C$259,4)="414C")*('Phân công'!#REF!="Tiếng Anh")) -> #REF! | I12: =SUMPRODUCT(('Phân công'!$D$2:$D$259=$A12)*('Phân công'!#REF!="X")*(RIGHT('Phân công'!$C$2:$C$259,5)="404CA")) -> #REF! | J12: =SUMPRODUCT(('Phân công'!$D$2:$D$259=$A12)*('Phân công'!#REF!="X")*(RIGHT('Phân công'!$C$2:$C$259,3)="404")) -> #REF! | K12: =SUMPRODUCT(('Phân công'!$D$2:$D$259=$A12)*('Phân công'!#REF!="X")*(RIGHT('Phân công'!$C$2:$C$259,3)="412")) -> #REF! | L12: =SUMPRODUCT(('Phân công'!$D$2:$D$259=$A12)*('Phân công'!#REF!="X")*(RIGHT('Phân công'!$C$2:$C$259,3)="414")) -> #REF! | M12: =SUMPRODUCT(('Phân công'!$D$2:$D$259=$A12)*('Phân công'!#REF!="X")*(RIGHT('Phân công'!$C$2:$C$259,3)="04C")*('Phân công'!#REF!="Tiếng Việt")) -> #REF! | N12: =SUMPRODUCT(('Phân công'!$D$2:$D$259=$A12)*('Phân công'!#REF!="X")*(RIGHT('Phân công'!$C$2:$C$259,3)="04C")*('Phân công'!#REF!="Tiếng Anh")) -> #REF! | O12: =SUMPRODUCT(('Phân công'!$D$2:$D$259=$A12)*('Phân công'!#REF!="X")*(RIGHT('Phân công'!$C$2:$C$259,3)="14C")*('Phân công'!#REF!="Tiếng Việt")) -> #REF! | P12: =SUMPRODUCT(('Phân công'!$D$2:$D$259=$A12)*('Phân công'!#REF!="X")*(RIGHT('Phân công'!$C$2:$C$259,3)="14C")*('Phân công'!#REF!="Tiếng Anh")) -> #REF! | Q12: =SUMPRODUCT(('Phân công'!$D$2:$D$259=$A12)*('Phân công'!#REF!="X")*(RIGHT('Phân công'!$C$2:$C$259,3)="4CA")) -> #REF! | R12: =SUMPRODUCT(('Phân công'!#REF!='Thù lao'!A12)*(RIGHT('Phân công'!$C$2:$C$259,3)="404")) -> #REF! | S12: =SUMPRODUCT(('Phân công'!#REF!='Thù lao'!A12)*(RIGHT('Phân công'!$C$2:$C$259,3)="412")) -> #REF! | T12: =SUMPRODUCT(('Phân công'!#REF!='Thù lao'!A12)*(RIGHT('Phân công'!$C$2:$C$259,3)="414")) -> #REF! | U12: =SUMPRODUCT(('Phân công'!#REF!='Thù lao'!A12)*(RIGHT('Phân công'!$C$2:$C$259,3)="04C")*('Phân công'!#REF!="Tiếng Việt")) -> #REF! | V12: =SUMPRODUCT(('Phân công'!#REF!='Thù lao'!A12)*(RIGHT('Phân công'!$C$2:$C$259,3)="04C")*('Phân công'!#REF!="Tiếng Anh")) -> #REF! | W12: =SUMPRODUCT(('Phân công'!#REF!='Thù lao'!A12)*(RIGHT('Phân công'!$C$2:$C$259,3)="14C")*('Phân công'!#REF!="Tiếng Việt")) -> #REF! | X12: =SUMPRODUCT(('Phân công'!#REF!='Thù lao'!A12)*(RIGHT('Phân công'!$C$2:$C$259,3)="14C")*('Phân công'!#REF!="Tiếng Anh")) -> #REF! | Y12: =SUMPRODUCT(('Phân công'!#REF!='Thù lao'!A12)*(RIGHT('Phân công'!$C$10:$C$259,3)="4CA")) -> #REF! | Z12: =SUMPRODUCT(('Phân công'!#REF!='Thù lao'!A12)*(RIGHT('Phân công'!$C$2:$C$259,3)="404")) -> #REF! | AA12: =SUMPRODUCT(('Phân công'!#REF!='Thù lao'!A12)*(RIGHT('Phân công'!$C$2:$C$259,3)="412")) -> #REF! | AB12: =SUMPRODUCT(('Phân công'!#REF!='Thù lao'!A12)*(RIGHT('Phân công'!$C$2:$C$259,3)="414")) -> #REF! | AC12: =SUMPRODUCT(('Phân công'!#REF!='Thù lao'!A12)*(RIGHT('Phân công'!$C$2:$C$259,3)="04C")*('Phân công'!#REF!="Tiếng Việt")) -> #REF! | AD12: =SUMPRODUCT(('Phân công'!#REF!='Thù lao'!A12)*(RIGHT('Phân công'!$C$2:$C$259,3)="04C")*('Phân công'!#REF!="Tiếng Anh")) -> #REF! | AE12: =SUMPRODUCT(('Phân công'!#REF!='Thù lao'!A12)*(RIGHT('Phân công'!$C$2:$C$259,3)="14C")*('Phân công'!#REF!="Tiếng Việt")) -> #REF! | AF12: =SUMPRODUCT(('Phân công'!#REF!='Thù lao'!A12)*(RIGHT('Phân công'!$C$2:$C$259,3)="14C")*('Phân công'!#REF!="Tiếng Anh")) -> #REF! | AG12: =SUMPRODUCT(('Phân công'!#REF!='Thù lao'!A12)*(RIGHT('Phân công'!$C$2:$C$259,3)="4CA")) -> #REF! | AH12: =SUMPRODUCT(('Phân công'!#REF!='Thù lao'!A12)*(RIGHT('Phân công'!$C$2:$C$259,3)="404")) -> #REF! | AI12: =SUMPRODUCT(('Phân công'!#REF!='Thù lao'!A12)*(RIGHT('Phân công'!$C$2:$C$259,3)="412")) -> #REF! | AJ12: =SUMPRODUCT(('Phân công'!#REF!='Thù lao'!A12)*(RIGHT('Phân công'!$C$2:$C$259,3)="414")) -> #REF! | AK12: =SUMPRODUCT(('Phân công'!#REF!='Thù lao'!A12)*(RIGHT('Phân công'!$C$2:$C$259,3)="04C")*('Phân công'!#REF!="Tiếng Việt")) -> #REF! | AL12: =SUMPRODUCT(('Phân công'!#REF!='Thù lao'!A12)*(RIGHT('Phân công'!$C$2:$C$259,3)="04C")*('Phân công'!#REF!="Tiếng Anh")) -> #REF! | AM12: =SUMPRODUCT(('Phân công'!#REF!='Thù lao'!A12)*(RIGHT('Phân công'!$C$2:$C$259,3)="14C")*('Phân công'!#REF!="Tiếng Việt")) -> #REF! | AN12: =SUMPRODUCT(('Phân công'!#REF!='Thù lao'!A12)*(RIGHT('Phân công'!$C$2:$C$259,3)="14C")*('Phân công'!#REF!="Tiếng Anh")) -> #REF! | AO12: =SUMPRODUCT(('Phân công'!#REF!='Thù lao'!A12)*(RIGHT('Phân công'!$C$2:$C$259,3)="4CA")) -> #REF! | AP12: =SUMPRODUCT(('Phân công'!#REF!='Thù lao'!A12)*(RIGHT('Phân công'!$C$2:$C$259,3)="404")) -> #REF! | AQ12: =SUMPRODUCT(('Phân công'!#REF!='Thù lao'!A12)*(RIGHT('Phân công'!$C$2:$C$259,3)="412")) -> #REF! | AR12: =SUMPRODUCT(('Phân công'!#REF!='Thù lao'!A12)*(RIGHT('Phân công'!$C$2:$C$259,3)="414")) -> #REF! | AS12: =SUMPRODUCT(('Phân công'!#REF!='Thù lao'!A12)*(RIGHT('Phân công'!$C$2:$C$259,3)="04C")*('Phân công'!#REF!="Tiếng Việt")) -> #REF! | AT12: =SUMPRODUCT(('Phân công'!#REF!='Thù lao'!A12)*(RIGHT('Phân công'!$C$2:$C$259,3)="04C")*('Phân công'!#REF!="Tiếng Anh")) -> #REF! | AU12: =SUMPRODUCT(('Phân công'!#REF!='Thù lao'!A12)*(RIGHT('Phân công'!$C$2:$C$259,3)="14C")*('Phân công'!#REF!="Tiếng Việt")) -> #REF! | AV12: =SUMPRODUCT(('Phân công'!#REF!='Thù lao'!A12)*(RIGHT('Phân công'!$C$2:$C$259,3)="14C")*('Phân công'!#REF!="Tiếng Anh")) -> #REF! | AW12: =SUMPRODUCT(('Phân công'!#REF!='Thù lao'!A12)*(RIGHT('Phân công'!$C$2:$C$259,3)="4CA")) -> #REF! | AX12: =AP12+AH12+Z12+R12 -> #REF! | AY12: =AQ12+AI12+AA12+S12 -> #REF! | AZ12: =AR12+AJ12+AB12+T12 -> #REF! | BA12: =AS12+AK12+AC12+U12 -> #REF! | BB12: =AT12+AL12+AD12+V12 -> #REF! | BC12: =AU12+AM12+AE12+W12 -> #REF! | BD12: =AV12+AN12+AF12+X12 -> #REF! | BE12: =AW12+AO12+AG12+Y12 -> #REF! | BF12: =SUMPRODUCT((B12:I12),($B$3:$I$3))*$BF$2 -> #REF! | BG12: =SUMPRODUCT(R12:Y12,$R$3:$Y$3)*$BG$2 -> #REF! | BH12: =SUMPRODUCT(Z12:AG12,$Z$3:$AG$3)*$BH$2 -> #REF! | BI12: =SUMPRODUCT(AH12:AO12,$AH$3:$AO$3)*$BI$2 -> #REF! | BJ12: =SUMPRODUCT(AP12:AW12,$AP$3:$AW$3)*$BJ$2 -> #REF! | BK12: =SUMPRODUCT((J12:Q12),($J$3:$Q$3))*$BK$2 -> #REF! | BL12: =BF12+BK12 -> #REF! | BM12: =SUM(BG12:BJ12) -> #REF! | BN12: =BM12+BK12 -> #REF! | BO12: =BL12+BM12 -> #REF!
A13: ThS Tô Thị Thanh Trúc | B13: =SUMPRODUCT(('Phân công'!$D$2:$D$259=$A13)*('Phân công'!#REF!="X")*(RIGHT('Phân công'!$C$2:$C$259,3)="404")) -> #REF! | C13: =SUMPRODUCT(('Phân công'!$D$2:$D$259=$A13)*('Phân công'!#REF!="X")*(RIGHT('Phân công'!$C$2:$C$259,3)="412")) -> #REF! | D13: =SUMPRODUCT(('Phân công'!$D$2:$D$259=$A13)*('Phân công'!#REF!="X")*(RIGHT('Phân công'!$C$2:$C$259,3)="414")) -> #REF! | E13: =SUMPRODUCT(('Phân công'!$D$2:$D$259=$A13)*('Phân công'!#REF!="X")*(RIGHT('Phân công'!$C$2:$C$259,4)="404C")*('Phân công'!#REF!="Tiếng Việt")) -> #REF! | F13: =SUMPRODUCT(('Phân công'!$D$2:$D$259=$A13)*('Phân công'!#REF!="X")*(RIGHT('Phân công'!$C$2:$C$259,4)="404C")*('Phân công'!#REF!="Tiếng Anh")) -> #REF! | G13: =SUMPRODUCT(('Phân công'!$D$2:$D$259=$A13)*('Phân công'!#REF!="X")*(RIGHT('Phân công'!$C$2:$C$259,4)="414C")*('Phân công'!#REF!="Tiếng Việt")) -> #REF! | H13: =SUMPRODUCT(('Phân công'!$D$2:$D$259=$A13)*('Phân công'!#REF!="X")*(RIGHT('Phân công'!$C$2:$C$259,4)="414C")*('Phân công'!#REF!="Tiếng Anh")) -> #REF! | I13: =SUMPRODUCT(('Phân công'!$D$2:$D$259=$A13)*('Phân công'!#REF!="X")*(RIGHT('Phân công'!$C$2:$C$259,5)="404CA")) -> #REF! | J13: =SUMPRODUCT(('Phân công'!$D$2:$D$259=$A13)*('Phân công'!#REF!="X")*(RIGHT('Phân công'!$C$2:$C$259,3)="404")) -> #REF! | K13: =SUMPRODUCT(('Phân công'!$D$2:$D$259=$A13)*('Phân công'!#REF!="X")*(RIGHT('Phân công'!$C$2:$C$259,3)="412")) -> #REF! | L13: =SUMPRODUCT(('Phân công'!$D$2:$D$259=$A13)*('Phân công'!#REF!="X")*(RIGHT('Phân công'!$C$2:$C$259,3)="414")) -> #REF! | M13: =SUMPRODUCT(('Phân công'!$D$2:$D$259=$A13)*('Phân công'!#REF!="X")*(RIGHT('Phân công'!$C$2:$C$259,3)="04C")*('Phân công'!#REF!="Tiếng Việt")) -> #REF! | N13: =SUMPRODUCT(('Phân công'!$D$2:$D$259=$A13)*('Phân công'!#REF!="X")*(RIGHT('Phân công'!$C$2:$C$259,3)="04C")*('Phân công'!#REF!="Tiếng Anh")) -> #REF! | O13: =SUMPRODUCT(('Phân công'!$D$2:$D$259=$A13)*('Phân công'!#REF!="X")*(RIGHT('Phân công'!$C$2:$C$259,3)="14C")*('Phân công'!#REF!="Tiếng Việt")) -> #REF! | P13: =SUMPRODUCT(('Phân công'!$D$2:$D$259=$A13)*('Phân công'!#REF!="X")*(RIGHT('Phân công'!$C$2:$C$259,3)="14C")*('Phân công'!#REF!="Tiếng Anh")) -> #REF! | Q13: =SUMPRODUCT(('Phân công'!$D$2:$D$259=$A13)*('Phân công'!#REF!="X")*(RIGHT('Phân công'!$C$2:$C$259,3)="4CA")) -> #REF! | R13: =SUMPRODUCT(('Phân công'!#REF!='Thù lao'!A13)*(RIGHT('Phân công'!$C$2:$C$259,3)="404")) -> #REF! | S13: =SUMPRODUCT(('Phân công'!#REF!='Thù lao'!A13)*(RIGHT('Phân công'!$C$2:$C$259,3)="412")) -> #REF! | T13: =SUMPRODUCT(('Phân công'!#REF!='Thù lao'!A13)*(RIGHT('Phân công'!$C$2:$C$259,3)="414")) -> #REF! | U13: =SUMPRODUCT(('Phân công'!#REF!='Thù lao'!A13)*(RIGHT('Phân công'!$C$2:$C$259,3)="04C")*('Phân công'!#REF!="Tiếng Việt")) -> #REF! | V13: =SUMPRODUCT(('Phân công'!#REF!='Thù lao'!A13)*(RIGHT('Phân công'!$C$2:$C$259,3)="04C")*('Phân công'!#REF!="Tiếng Anh")) -> #REF! | W13: =SUMPRODUCT(('Phân công'!#REF!='Thù lao'!A13)*(RIGHT('Phân công'!$C$2:$C$259,3)="14C")*('Phân công'!#REF!="Tiếng Việt")) -> #REF! | X13: =SUMPRODUCT(('Phân công'!#REF!='Thù lao'!A13)*(RIGHT('Phân công'!$C$2:$C$259,3)="14C")*('Phân công'!#REF!="Tiếng Anh")) -> #REF! | Y13: =SUMPRODUCT(('Phân công'!#REF!='Thù lao'!A13)*(RIGHT('Phân công'!$C$10:$C$259,3)="4CA")) -> #REF! | Z13: =SUMPRODUCT(('Phân công'!#REF!='Thù lao'!A13)*(RIGHT('Phân công'!$C$2:$C$259,3)="404")) -> #REF! | AA13: =SUMPRODUCT(('Phân công'!#REF!='Thù lao'!A13)*(RIGHT('Phân công'!$C$2:$C$259,3)="412")) -> #REF! | AB13: =SUMPRODUCT(('Phân công'!#REF!='Thù lao'!A13)*(RIGHT('Phân công'!$C$2:$C$259,3)="414")) -> #REF! | AC13: =SUMPRODUCT(('Phân công'!#REF!='Thù lao'!A13)*(RIGHT('Phân công'!$C$2:$C$259,3)="04C")*('Phân công'!#REF!="Tiếng Việt")) -> #REF! | AD13: =SUMPRODUCT(('Phân công'!#REF!='Thù lao'!A13)*(RIGHT('Phân công'!$C$2:$C$259,3)="04C")*('Phân công'!#REF!="Tiếng Anh")) -> #REF! | AE13: =SUMPRODUCT(('Phân công'!#REF!='Thù lao'!A13)*(RIGHT('Phân công'!$C$2:$C$259,3)="14C")*('Phân công'!#REF!="Tiếng Việt")) -> #REF! | AF13: =SUMPRODUCT(('Phân công'!#REF!='Thù lao'!A13)*(RIGHT('Phân công'!$C$2:$C$259,3)="14C")*('Phân công'!#REF!="Tiếng Anh")) -> #REF! | AG13: =SUMPRODUCT(('Phân công'!#REF!='Thù lao'!A13)*(RIGHT('Phân công'!$C$2:$C$259,3)="4CA")) -> #REF! | AH13: =SUMPRODUCT(('Phân công'!#REF!='Thù lao'!A13)*(RIGHT('Phân công'!$C$2:$C$259,3)="404")) -> #REF! | AI13: =SUMPRODUCT(('Phân công'!#REF!='Thù lao'!A13)*(RIGHT('Phân công'!$C$2:$C$259,3)="412")) -> #REF! | AJ13: =SUMPRODUCT(('Phân công'!#REF!='Thù lao'!A13)*(RIGHT('Phân công'!$C$2:$C$259,3)="414")) -> #REF! | AK13: =SUMPRODUCT(('Phân công'!#REF!='Thù lao'!A13)*(RIGHT('Phân công'!$C$2:$C$259,3)="04C")*('Phân công'!#REF!="Tiếng Việt")) -> #REF! | AL13: =SUMPRODUCT(('Phân công'!#REF!='Thù lao'!A13)*(RIGHT('Phân công'!$C$2:$C$259,3)="04C")*('Phân công'!#REF!="Tiếng Anh")) -> #REF! | AM13: =SUMPRODUCT(('Phân công'!#REF!='Thù lao'!A13)*(RIGHT('Phân công'!$C$2:$C$259,3)="14C")*('Phân công'!#REF!="Tiếng Việt")) -> #REF! | AN13: =SUMPRODUCT(('Phân công'!#REF!='Thù lao'!A13)*(RIGHT('Phân công'!$C$2:$C$259,3)="14C")*('Phân công'!#REF!="Tiếng Anh")) -> #REF! | AO13: =SUMPRODUCT(('Phân công'!#REF!='Thù lao'!A13)*(RIGHT('Phân công'!$C$2:$C$259,3)="4CA")) -> #REF! | AP13: =SUMPRODUCT(('Phân công'!#REF!='Thù lao'!A13)*(RIGHT('Phân công'!$C$2:$C$259,3)="404")) -> #REF! | AQ13: =SUMPRODUCT(('Phân công'!#REF!='Thù lao'!A13)*(RIGHT('Phân công'!$C$2:$C$259,3)="412")) -> #REF! | AR13: =SUMPRODUCT(('Phân công'!#REF!='Thù lao'!A13)*(RIGHT('Phân công'!$C$2:$C$259,3)="414")) -> #REF! | AS13: =SUMPRODUCT(('Phân công'!#REF!='Thù lao'!A13)*(RIGHT('Phân công'!$C$2:$C$259,3)="04C")*('Phân công'!#REF!="Tiếng Việt")) -> #REF! | AT13: =SUMPRODUCT(('Phân công'!#REF!='Thù lao'!A13)*(RIGHT('Phân công'!$C$2:$C$259,3)="04C")*('Phân công'!#REF!="Tiếng Anh")) -> #REF! | AU13: =SUMPRODUCT(('Phân công'!#REF!='Thù lao'!A13)*(RIGHT('Phân công'!$C$2:$C$259,3)="14C")*('Phân công'!#REF!="Tiếng Việt")) -> #REF! | AV13: =SUMPRODUCT(('Phân công'!#REF!='Thù lao'!A13)*(RIGHT('Phân công'!$C$2:$C$259,3)="14C")*('Phân công'!#REF!="Tiếng Anh")) -> #REF! | AW13: =SUMPRODUCT(('Phân công'!#REF!='Thù lao'!A13)*(RIGHT('Phân công'!$C$2:$C$259,3)="4CA")) -> #REF! | AX13: =AP13+AH13+Z13+R13 -> #REF! | AY13: =AQ13+AI13+AA13+S13 -> #REF! | AZ13: =AR13+AJ13+AB13+T13 -> #REF! | BA13: =AS13+AK13+AC13+U13 -> #REF! | BB13: =AT13+AL13+AD13+V13 -> #REF! | BC13: =AU13+AM13+AE13+W13 -> #REF! | BD13: =AV13+AN13+AF13+X13 -> #REF! | BE13: =AW13+AO13+AG13+Y13 -> #REF! | BF13: =SUMPRODUCT((B13:I13),($B$3:$I$3))*$BF$2 -> #REF! | BG13: =SUMPRODUCT(R13:Y13,$R$3:$Y$3)*$BG$2 -> #REF! | BH13: =SUMPRODUCT(Z13:AG13,$Z$3:$AG$3)*$BH$2 -> #REF! | BI13: =SUMPRODUCT(AH13:AO13,$AH$3:$AO$3)*$BI$2 -> #REF! | BJ13: =SUMPRODUCT(AP13:AW13,$AP$3:$AW$3)*$BJ$2 -> #REF! | BK13: =SUMPRODUCT((J13:Q13),($J$3:$Q$3))*$BK$2 -> #REF! | BL13: =BF13+BK13 -> #REF! | BM13: =SUM(BG13:BJ13) -> #REF! | BN13: =BM13+BK13 -> #REF! | BO13: =BL13+BM13 -> #REF!
A14: PGS. TS Nguyễn Anh Phong | B14: =SUMPRODUCT(('Phân công'!$D$2:$D$259=$A14)*('Phân công'!#REF!="X")*(RIGHT('Phân công'!$C$2:$C$259,3)="404")) -> #REF! | C14: =SUMPRODUCT(('Phân công'!$D$2:$D$259=$A14)*('Phân công'!#REF!="X")*(RIGHT('Phân công'!$C$2:$C$259,3)="412")) -> #REF! | D14: =SUMPRODUCT(('Phân công'!$D$2:$D$259=$A14)*('Phân công'!#REF!="X")*(RIGHT('Phân công'!$C$2:$C$259,3)="414")) -> #REF! | E14: =SUMPRODUCT(('Phân công'!$D$2:$D$259=$A14)*('Phân công'!#REF!="X")*(RIGHT('Phân công'!$C$2:$C$259,4)="404C")*('Phân công'!#REF!="Tiếng Việt")) -> #REF! | F14: =SUMPRODUCT(('Phân công'!$D$2:$D$259=$A14)*('Phân công'!#REF!="X")*(RIGHT('Phân công'!$C$2:$C$259,4)="404C")*('Phân công'!#REF!="Tiếng Anh")) -> #REF! | G14: =SUMPRODUCT(('Phân công'!$D$2:$D$259=$A14)*('Phân công'!#REF!="X")*(RIGHT('Phân công'!$C$2:$C$259,4)="414C")*('Phân công'!#REF!="Tiếng Việt")) -> #REF! | H14: =SUMPRODUCT(('Phân công'!$D$2:$D$259=$A14)*('Phân công'!#REF!="X")*(RIGHT('Phân công'!$C$2:$C$259,4)="414C")*('Phân công'!#REF!="Tiếng Anh")) -> #REF! | I14: =SUMPRODUCT(('Phân công'!$D$2:$D$259=$A14)*('Phân công'!#REF!="X")*(RIGHT('Phân công'!$C$2:$C$259,5)="404CA")) -> #REF! | J14: =SUMPRODUCT(('Phân công'!$D$2:$D$259=$A14)*('Phân công'!#REF!="X")*(RIGHT('Phân công'!$C$2:$C$259,3)="404")) -> #REF! | K14: =SUMPRODUCT(('Phân công'!$D$2:$D$259=$A14)*('Phân công'!#REF!="X")*(RIGHT('Phân công'!$C$2:$C$259,3)="412")) -> #REF! | L14: =SUMPRODUCT(('Phân công'!$D$2:$D$259=$A14)*('Phân công'!#REF!="X")*(RIGHT('Phân công'!$C$2:$C$259,3)="414")) -> #REF! | M14: =SUMPRODUCT(('Phân công'!$D$2:$D$259=$A14)*('Phân công'!#REF!="X")*(RIGHT('Phân công'!$C$2:$C$259,3)="04C")*('Phân công'!#REF!="Tiếng Việt")) -> #REF! | N14: =SUMPRODUCT(('Phân công'!$D$2:$D$259=$A14)*('Phân công'!#REF!="X")*(RIGHT('Phân công'!$C$2:$C$259,3)="04C")*('Phân công'!#REF!="Tiếng Anh")) -> #REF! | O14: =SUMPRODUCT(('Phân công'!$D$2:$D$259=$A14)*('Phân công'!#REF!="X")*(RIGHT('Phân công'!$C$2:$C$259,3)="14C")*('Phân công'!#REF!="Tiếng Việt")) -> #REF! | P14: =SUMPRODUCT(('Phân công'!$D$2:$D$259=$A14)*('Phân công'!#REF!="X")*(RIGHT('Phân công'!$C$2:$C$259,3)="14C")*('Phân công'!#REF!="Tiếng Anh")) -> #REF! | Q14: =SUMPRODUCT(('Phân công'!$D$2:$D$259=$A14)*('Phân công'!#REF!="X")*(RIGHT('Phân công'!$C$2:$C$259,3)="4CA")) -> #REF! | R14: =SUMPRODUCT(('Phân công'!#REF!='Thù lao'!A14)*(RIGHT('Phân công'!$C$2:$C$259,3)="404")) -> #REF! | S14: =SUMPRODUCT(('Phân công'!#REF!='Thù lao'!A14)*(RIGHT('Phân công'!$C$2:$C$259,3)="412")) -> #REF! | T14: =SUMPRODUCT(('Phân công'!#REF!='Thù lao'!A14)*(RIGHT('Phân công'!$C$2:$C$259,3)="414")) -> #REF! | U14: =SUMPRODUCT(('Phân công'!#REF!='Thù lao'!A14)*(RIGHT('Phân công'!$C$2:$C$259,3)="04C")*('Phân công'!#REF!="Tiếng Việt")) -> #REF! | V14: =SUMPRODUCT(('Phân công'!#REF!='Thù lao'!A14)*(RIGHT('Phân công'!$C$2:$C$259,3)="04C")*('Phân công'!#REF!="Tiếng Anh")) -> #REF! | W14: =SUMPRODUCT(('Phân công'!#REF!='Thù lao'!A14)*(RIGHT('Phân công'!$C$2:$C$259,3)="14C")*('Phân công'!#REF!="Tiếng Việt")) -> #REF! | X14: =SUMPRODUCT(('Phân công'!#REF!='Thù lao'!A14)*(RIGHT('Phân công'!$C$2:$C$259,3)="14C")*('Phân công'!#REF!="Tiếng Anh")) -> #REF! | Y14: =SUMPRODUCT(('Phân công'!#REF!='Thù lao'!A14)*(RIGHT('Phân công'!$C$10:$C$259,3)="4CA")) -> #REF! | Z14: =SUMPRODUCT(('Phân công'!#REF!='Thù lao'!A14)*(RIGHT('Phân công'!$C$2:$C$259,3)="404")) -> #REF! | AA14: =SUMPRODUCT(('Phân công'!#REF!='Thù lao'!A14)*(RIGHT('Phân công'!$C$2:$C$259,3)="412")) -> #REF! | AB14: =SUMPRODUCT(('Phân công'!#REF!='Thù lao'!A14)*(RIGHT('Phân công'!$C$2:$C$259,3)="414")) -> #REF! | AC14: =SUMPRODUCT(('Phân công'!#REF!='Thù lao'!A14)*(RIGHT('Phân công'!$C$2:$C$259,3)="04C")*('Phân công'!#REF!="Tiếng Việt")) -> #REF! | AD14: =SUMPRODUCT(('Phân công'!#REF!='Thù lao'!A14)*(RIGHT('Phân công'!$C$2:$C$259,3)="04C")*('Phân công'!#REF!="Tiếng Anh")) -> #REF! | AE14: =SUMPRODUCT(('Phân công'!#REF!='Thù lao'!A14)*(RIGHT('Phân công'!$C$2:$C$259,3)="14C")*('Phân công'!#REF!="Tiếng Việt")) -> #REF! | AF14: =SUMPRODUCT(('Phân công'!#REF!='Thù lao'!A14)*(RIGHT('Phân công'!$C$2:$C$259,3)="14C")*('Phân công'!#REF!="Tiếng Anh")) -> #REF! | AG14: =SUMPRODUCT(('Phân công'!#REF!='Thù lao'!A14)*(RIGHT('Phân công'!$C$2:$C$259,3)="4CA")) -> #REF! | AH14: =SUMPRODUCT(('Phân công'!#REF!='Thù lao'!A14)*(RIGHT('Phân công'!$C$2:$C$259,3)="404")) -> #REF! | AI14: =SUMPRODUCT(('Phân công'!#REF!='Thù lao'!A14)*(RIGHT('Phân công'!$C$2:$C$259,3)="412")) -> #REF! | AJ14: =SUMPRODUCT(('Phân công'!#REF!='Thù lao'!A14)*(RIGHT('Phân công'!$C$2:$C$259,3)="414")) -> #REF! | AK14: =SUMPRODUCT(('Phân công'!#REF!='Thù lao'!A14)*(RIGHT('Phân công'!$C$2:$C$259,3)="04C")*('Phân công'!#REF!="Tiếng Việt")) -> #REF! | AL14: =SUMPRODUCT(('Phân công'!#REF!='Thù lao'!A14)*(RIGHT('Phân công'!$C$2:$C$259,3)="04C")*('Phân công'!#REF!="Tiếng Anh")) -> #REF! | AM14: =SUMPRODUCT(('Phân công'!#REF!='Thù lao'!A14)*(RIGHT('Phân công'!$C$2:$C$259,3)="14C")*('Phân công'!#REF!="Tiếng Việt")) -> #REF! | AN14: =SUMPRODUCT(('Phân công'!#REF!='Thù lao'!A14)*(RIGHT('Phân công'!$C$2:$C$259,3)="14C")*('Phân công'!#REF!="Tiếng Anh")) -> #REF! | AO14: =SUMPRODUCT(('Phân công'!#REF!='Thù lao'!A14)*(RIGHT('Phân công'!$C$2:$C$259,3)="4CA")) -> #REF! | AP14: =SUMPRODUCT(('Phân công'!#REF!='Thù lao'!A14)*(RIGHT('Phân công'!$C$2:$C$259,3)="404")) -> #REF! | AQ14: =SUMPRODUCT(('Phân công'!#REF!='Thù lao'!A14)*(RIGHT('Phân công'!$C$2:$C$259,3)="412")) -> #REF! | AR14: =SUMPRODUCT(('Phân công'!#REF!='Thù lao'!A14)*(RIGHT('Phân công'!$C$2:$C$259,3)="414")) -> #REF! | AS14: =SUMPRODUCT(('Phân công'!#REF!='Thù lao'!A14)*(RIGHT('Phân công'!$C$2:$C$259,3)="04C")*('Phân công'!#REF!="Tiếng Việt")) -> #REF! | AT14: =SUMPRODUCT(('Phân công'!#REF!='Thù lao'!A14)*(RIGHT('Phân công'!$C$2:$C$259,3)="04C")*('Phân công'!#REF!="Tiếng Anh")) -> #REF! | AU14: =SUMPRODUCT(('Phân công'!#REF!='Thù lao'!A14)*(RIGHT('Phân công'!$C$2:$C$259,3)="14C")*('Phân công'!#REF!="Tiếng Việt")) -> #REF! | AV14: =SUMPRODUCT(('Phân công'!#REF!='Thù lao'!A14)*(RIGHT('Phân công'!$C$2:$C$259,3)="14C")*('Phân công'!#REF!="Tiếng Anh")) -> #REF! | AW14: =SUMPRODUCT(('Phân công'!#REF!='Thù lao'!A14)*(RIGHT('Phân công'!$C$2:$C$259,3)="4CA")) -> #REF! | AX14: =AP14+AH14+Z14+R14 -> #REF! | AY14: =AQ14+AI14+AA14+S14 -> #REF! | AZ14: =AR14+AJ14+AB14+T14 -> #REF! | BA14: =AS14+AK14+AC14+U14 -> #REF! | BB14: =AT14+AL14+AD14+V14 -> #REF! | BC14: =AU14+AM14+AE14+W14 -> #REF! | BD14: =AV14+AN14+AF14+X14 -> #REF! | BE14: =AW14+AO14+AG14+Y14 -> #REF! | BF14: =SUMPRODUCT((B14:I14),($B$3:$I$3))*$BF$2 -> #REF! | BG14: =SUMPRODUCT(R14:Y14,$R$3:$Y$3)*$BG$2 -> #REF! | BH14: =SUMPRODUCT(Z14:AG14,$Z$3:$AG$3)*$BH$2 -> #REF! | BI14: =SUMPRODUCT(AH14:AO14,$AH$3:$AO$3)*$BI$2 -> #REF! | BJ14: =SUMPRODUCT(AP14:AW14,$AP$3:$AW$3)*$BJ$2 -> #REF! | BK14: =SUMPRODUCT((J14:Q14),($J$3:$Q$3))*$BK$2 -> #REF! | BL14: =BF14+BK14 -> #REF! | BM14: =SUM(BG14:BJ14) -> #REF! | BN14: =BM14+BK14 -> #REF! | BO14: =BL14+BM14 -> #REF!
A15: TS Võ Thị Ngọc Trinh | B15: =SUMPRODUCT(('Phân công'!$D$2:$D$259=$A15)*('Phân công'!#REF!="X")*(RIGHT('Phân công'!$C$2:$C$259,3)="404")) -> #REF! | C15: =SUMPRODUCT(('Phân công'!$D$2:$D$259=$A15)*('Phân công'!#REF!="X")*(RIGHT('Phân công'!$C$2:$C$259,3)="412")) -> #REF! | D15: =SUMPRODUCT(('Phân công'!$D$2:$D$259=$A15)*('Phân công'!#REF!="X")*(RIGHT('Phân công'!$C$2:$C$259,3)="414")) -> #REF! | E15: =SUMPRODUCT(('Phân công'!$D$2:$D$259=$A15)*('Phân công'!#REF!="X")*(RIGHT('Phân công'!$C$2:$C$259,4)="404C")*('Phân công'!#REF!="Tiếng Việt")) -> #REF! | F15: =SUMPRODUCT(('Phân công'!$D$2:$D$259=$A15)*('Phân công'!#REF!="X")*(RIGHT('Phân công'!$C$2:$C$259,4)="404C")*('Phân công'!#REF!="Tiếng Anh")) -> #REF! | G15: =SUMPRODUCT(('Phân công'!$D$2:$D$259=$A15)*('Phân công'!#REF!="X")*(RIGHT('Phân công'!$C$2:$C$259,4)="414C")*('Phân công'!#REF!="Tiếng Việt")) -> #REF! | H15: =SUMPRODUCT(('Phân công'!$D$2:$D$259=$A15)*('Phân công'!#REF!="X")*(RIGHT('Phân công'!$C$2:$C$259,4)="414C")*('Phân công'!#REF!="Tiếng Anh")) -> #REF! | I15: =SUMPRODUCT(('Phân công'!$D$2:$D$259=$A15)*('Phân công'!#REF!="X")*(RIGHT('Phân công'!$C$2:$C$259,5)="404CA")) -> #REF! | J15: =SUMPRODUCT(('Phân công'!$D$2:$D$259=$A15)*('Phân công'!#REF!="X")*(RIGHT('Phân công'!$C$2:$C$259,3)="404")) -> #REF! | K15: =SUMPRODUCT(('Phân công'!$D$2:$D$259=$A15)*('Phân công'!#REF!="X")*(RIGHT('Phân công'!$C$2:$C$259,3)="412")) -> #REF! | L15: =SUMPRODUCT(('Phân công'!$D$2:$D$259=$A15)*('Phân công'!#REF!="X")*(RIGHT('Phân công'!$C$2:$C$259,3)="414")) -> #REF! | M15: =SUMPRODUCT(('Phân công'!$D$2:$D$259=$A15)*('Phân công'!#REF!="X")*(RIGHT('Phân công'!$C$2:$C$259,3)="04C")*('Phân công'!#REF!="Tiếng Việt")) -> #REF! | N15: =SUMPRODUCT(('Phân công'!$D$2:$D$259=$A15)*('Phân công'!#REF!="X")*(RIGHT('Phân công'!$C$2:$C$259,3)="04C")*('Phân công'!#REF!="Tiếng Anh")) -> #REF! | O15: =SUMPRODUCT(('Phân công'!$D$2:$D$259=$A15)*('Phân công'!#REF!="X")*(RIGHT('Phân công'!$C$2:$C$259,3)="14C")*('Phân công'!#REF!="Tiếng Việt")) -> #REF! | P15: =SUMPRODUCT(('Phân công'!$D$2:$D$259=$A15)*('Phân công'!#REF!="X")*(RIGHT('Phân công'!$C$2:$C$259,3)="14C")*('Phân công'!#REF!="Tiếng Anh")) -> #REF! | Q15: =SUMPRODUCT(('Phân công'!$D$2:$D$259=$A15)*('Phân công'!#REF!="X")*(RIGHT('Phân công'!$C$2:$C$259,3)="4CA")) -> #REF! | R15: =SUMPRODUCT(('Phân công'!#REF!='Thù lao'!A15)*(RIGHT('Phân công'!$C$2:$C$259,3)="404")) -> #REF! | S15: =SUMPRODUCT(('Phân công'!#REF!='Thù lao'!A15)*(RIGHT('Phân công'!$C$2:$C$259,3)="412")) -> #REF! | T15: =SUMPRODUCT(('Phân công'!#REF!='Thù lao'!A15)*(RIGHT('Phân công'!$C$2:$C$259,3)="414")) -> #REF! | U15: =SUMPRODUCT(('Phân công'!#REF!='Thù lao'!A15)*(RIGHT('Phân công'!$C$2:$C$259,3)="04C")*('Phân công'!#REF!="Tiếng Việt")) -> #REF! | V15: =SUMPRODUCT(('Phân công'!#REF!='Thù lao'!A15)*(RIGHT('Phân công'!$C$2:$C$259,3)="04C")*('Phân công'!#REF!="Tiếng Anh")) -> #REF! | W15: =SUMPRODUCT(('Phân công'!#REF!='Thù lao'!A15)*(RIGHT('Phân công'!$C$2:$C$259,3)="14C")*('Phân công'!#REF!="Tiếng Việt")) -> #REF! | X15: =SUMPRODUCT(('Phân công'!#REF!='Thù lao'!A15)*(RIGHT('Phân công'!$C$2:$C$259,3)="14C")*('Phân công'!#REF!="Tiếng Anh")) -> #REF! | Y15: =SUMPRODUCT(('Phân công'!#REF!='Thù lao'!A15)*(RIGHT('Phân công'!$C$10:$C$259,3)="4CA")) -> #REF! | Z15: =SUMPRODUCT(('Phân công'!#REF!='Thù lao'!A15)*(RIGHT('Phân công'!$C$2:$C$259,3)="404")) -> #REF! | AA15: =SUMPRODUCT(('Phân công'!#REF!='Thù lao'!A15)*(RIGHT('Phân công'!$C$2:$C$259,3)="412")) -> #REF! | AB15: =SUMPRODUCT(('Phân công'!#REF!='Thù lao'!A15)*(RIGHT('Phân công'!$C$2:$C$259,3)="414")) -> #REF! | AC15: =SUMPRODUCT(('Phân công'!#REF!='Thù lao'!A15)*(RIGHT('Phân công'!$C$2:$C$259,3)="04C")*('Phân công'!#REF!="Tiếng Việt")) -> #REF! | AD15: =SUMPRODUCT(('Phân công'!#REF!='Thù lao'!A15)*(RIGHT('Phân công'!$C$2:$C$259,3)="04C")*('Phân công'!#REF!="Tiếng Anh")) -> #REF! | AE15: =SUMPRODUCT(('Phân công'!#REF!='Thù lao'!A15)*(RIGHT('Phân công'!$C$2:$C$259,3)="14C")*('Phân công'!#REF!="Tiếng Việt")) -> #REF! | AF15: =SUMPRODUCT(('Phân công'!#REF!='Thù lao'!A15)*(RIGHT('Phân công'!$C$2:$C$259,3)="14C")*('Phân công'!#REF!="Tiếng Anh")) -> #REF! | AG15: =SUMPRODUCT(('Phân công'!#REF!='Thù lao'!A15)*(RIGHT('Phân công'!$C$2:$C$259,3)="4CA")) -> #REF! | AH15: =SUMPRODUCT(('Phân công'!#REF!='Thù lao'!A15)*(RIGHT('Phân công'!$C$2:$C$259,3)="404")) -> #REF! | AI15: =SUMPRODUCT(('Phân công'!#REF!='Thù lao'!A15)*(RIGHT('Phân công'!$C$2:$C$259,3)="412")) -> #REF! | AJ15: =SUMPRODUCT(('Phân công'!#REF!='Thù lao'!A15)*(RIGHT('Phân công'!$C$2:$C$259,3)="414")) -> #REF! | AK15: =SUMPRODUCT(('Phân công'!#REF!='Thù lao'!A15)*(RIGHT('Phân công'!$C$2:$C$259,3)="04C")*('Phân công'!#REF!="Tiếng Việt")) -> #REF! | AL15: =SUMPRODUCT(('Phân công'!#REF!='Thù lao'!A15)*(RIGHT('Phân công'!$C$2:$C$259,3)="04C")*('Phân công'!#REF!="Tiếng Anh")) -> #REF! | AM15: =SUMPRODUCT(('Phân công'!#REF!='Thù lao'!A15)*(RIGHT('Phân công'!$C$2:$C$259,3)="14C")*('Phân công'!#REF!="Tiếng Việt")) -> #REF! | AN15: =SUMPRODUCT(('Phân công'!#REF!='Thù lao'!A15)*(RIGHT('Phân công'!$C$2:$C$259,3)="14C")*('Phân công'!#REF!="Tiếng Anh")) -> #REF! | AO15: =SUMPRODUCT(('Phân công'!#REF!='Thù lao'!A15)*(RIGHT('Phân công'!$C$2:$C$259,3)="4CA")) -> #REF! | AP15: =SUMPRODUCT(('Phân công'!#REF!='Thù lao'!A15)*(RIGHT('Phân công'!$C$2:$C$259,3)="404")) -> #REF! | AQ15: =SUMPRODUCT(('Phân công'!#REF!='Thù lao'!A15)*(RIGHT('Phân công'!$C$2:$C$259,3)="412")) -> #REF! | AR15: =SUMPRODUCT(('Phân công'!#REF!='Thù lao'!A15)*(RIGHT('Phân công'!$C$2:$C$259,3)="414")) -> #REF! | AS15: =SUMPRODUCT(('Phân công'!#REF!='Thù lao'!A15)*(RIGHT('Phân công'!$C$2:$C$259,3)="04C")*('Phân công'!#REF!="Tiếng Việt")) -> #REF! | AT15: =SUMPRODUCT(('Phân công'!#REF!='Thù lao'!A15)*(RIGHT('Phân công'!$C$2:$C$259,3)="04C")*('Phân công'!#REF!="Tiếng Anh")) -> #REF! | AU15: =SUMPRODUCT(('Phân công'!#REF!='Thù lao'!A15)*(RIGHT('Phân công'!$C$2:$C$259,3)="14C")*('Phân công'!#REF!="Tiếng Việt")) -> #REF! | AV15: =SUMPRODUCT(('Phân công'!#REF!='Thù lao'!A15)*(RIGHT('Phân công'!$C$2:$C$259,3)="14C")*('Phân công'!#REF!="Tiếng Anh")) -> #REF! | AW15: =SUMPRODUCT(('Phân công'!#REF!='Thù lao'!A15)*(RIGHT('Phân công'!$C$2:$C$259,3)="4CA")) -> #REF! | AX15: =AP15+AH15+Z15+R15 -> #REF! | AY15: =AQ15+AI15+AA15+S15 -> #REF! | AZ15: =AR15+AJ15+AB15+T15 -> #REF! | BA15: =AS15+AK15+AC15+U15 -> #REF! | BB15: =AT15+AL15+AD15+V15 -> #REF! | BC15: =AU15+AM15+AE15+W15 -> #REF! | BD15: =AV15+AN15+AF15+X15 -> #REF! | BE15: =AW15+AO15+AG15+Y15 -> #REF! | BF15: =SUMPRODUCT((B15:I15),($B$3:$I$3))*$BF$2 -> #REF! | BG15: =SUMPRODUCT(R15:Y15,$R$3:$Y$3)*$BG$2 -> #REF! | BH15: =SUMPRODUCT(Z15:AG15,$Z$3:$AG$3)*$BH$2 -> #REF! | BI15: =SUMPRODUCT(AH15:AO15,$AH$3:$AO$3)*$BI$2 -> #REF! | BJ15: =SUMPRODUCT(AP15:AW15,$AP$3:$AW$3)*$BJ$2 -> #REF! | BK15: =SUMPRODUCT((J15:Q15),($J$3:$Q$3))*$BK$2 -> #REF! | BL15: =BF15+BK15 -> #REF! | BM15: =SUM(BG15:BJ15) -> #REF! | BN15: =BM15+BK15 -> #REF! | BO15: =BL15+BM15 -> #REF!
A16: TS Nguyễn Tiến Trung | B16: =SUMPRODUCT(('Phân công'!$D$2:$D$259=$A16)*('Phân công'!#REF!="X")*(RIGHT('Phân công'!$C$2:$C$259,3)="404")) -> #REF! | C16: =SUMPRODUCT(('Phân công'!$D$2:$D$259=$A16)*('Phân công'!#REF!="X")*(RIGHT('Phân công'!$C$2:$C$259,3)="412")) -> #REF! | D16: =SUMPRODUCT(('Phân công'!$D$2:$D$259=$A16)*('Phân công'!#REF!="X")*(RIGHT('Phân công'!$C$2:$C$259,3)="414")) -> #REF! | E16: =SUMPRODUCT(('Phân công'!$D$2:$D$259=$A16)*('Phân công'!#REF!="X")*(RIGHT('Phân công'!$C$2:$C$259,4)="404C")*('Phân công'!#REF!="Tiếng Việt")) -> #REF! | F16: =SUMPRODUCT(('Phân công'!$D$2:$D$259=$A16)*('Phân công'!#REF!="X")*(RIGHT('Phân công'!$C$2:$C$259,4)="404C")*('Phân công'!#REF!="Tiếng Anh")) -> #REF! | G16: =SUMPRODUCT(('Phân công'!$D$2:$D$259=$A16)*('Phân công'!#REF!="X")*(RIGHT('Phân công'!$C$2:$C$259,4)="414C")*('Phân công'!#REF!="Tiếng Việt")) -> #REF! | H16: =SUMPRODUCT(('Phân công'!$D$2:$D$259=$A16)*('Phân công'!#REF!="X")*(RIGHT('Phân công'!$C$2:$C$259,4)="414C")*('Phân công'!#REF!="Tiếng Anh")) -> #REF! | I16: =SUMPRODUCT(('Phân công'!$D$2:$D$259=$A16)*('Phân công'!#REF!="X")*(RIGHT('Phân công'!$C$2:$C$259,5)="404CA")) -> #REF! | J16: =SUMPRODUCT(('Phân công'!$D$2:$D$259=$A16)*('Phân công'!#REF!="X")*(RIGHT('Phân công'!$C$2:$C$259,3)="404")) -> #REF! | K16: =SUMPRODUCT(('Phân công'!$D$2:$D$259=$A16)*('Phân công'!#REF!="X")*(RIGHT('Phân công'!$C$2:$C$259,3)="412")) -> #REF! | L16: =SUMPRODUCT(('Phân công'!$D$2:$D$259=$A16)*('Phân công'!#REF!="X")*(RIGHT('Phân công'!$C$2:$C$259,3)="414")) -> #REF! | M16: =SUMPRODUCT(('Phân công'!$D$2:$D$259=$A16)*('Phân công'!#REF!="X")*(RIGHT('Phân công'!$C$2:$C$259,3)="04C")*('Phân công'!#REF!="Tiếng Việt")) -> #REF! | N16: =SUMPRODUCT(('Phân công'!$D$2:$D$259=$A16)*('Phân công'!#REF!="X")*(RIGHT('Phân công'!$C$2:$C$259,3)="04C")*('Phân công'!#REF!="Tiếng Anh")) -> #REF! | O16: =SUMPRODUCT(('Phân công'!$D$2:$D$259=$A16)*('Phân công'!#REF!="X")*(RIGHT('Phân công'!$C$2:$C$259,3)="14C")*('Phân công'!#REF!="Tiếng Việt")) -> #REF! | P16: =SUMPRODUCT(('Phân công'!$D$2:$D$259=$A16)*('Phân công'!#REF!="X")*(RIGHT('Phân công'!$C$2:$C$259,3)="14C")*('Phân công'!#REF!="Tiếng Anh")) -> #REF! | Q16: =SUMPRODUCT(('Phân công'!$D$2:$D$259=$A16)*('Phân công'!#REF!="X")*(RIGHT('Phân công'!$C$2:$C$259,3)="4CA")) -> #REF! | R16: =SUMPRODUCT(('Phân công'!#REF!='Thù lao'!A16)*(RIGHT('Phân công'!$C$2:$C$259,3)="404")) -> #REF! | S16: =SUMPRODUCT(('Phân công'!#REF!='Thù lao'!A16)*(RIGHT('Phân công'!$C$2:$C$259,3)="412")) -> #REF! | T16: =SUMPRODUCT(('Phân công'!#REF!='Thù lao'!A16)*(RIGHT('Phân công'!$C$2:$C$259,3)="414")) -> #REF! | U16: =SUMPRODUCT(('Phân công'!#REF!='Thù lao'!A16)*(RIGHT('Phân công'!$C$2:$C$259,3)="04C")*('Phân công'!#REF!="Tiếng Việt")) -> #REF! | V16: =SUMPRODUCT(('Phân công'!#REF!='Thù lao'!A16)*(RIGHT('Phân công'!$C$2:$C$259,3)="04C")*('Phân công'!#REF!="Tiếng Anh")) -> #REF! | W16: =SUMPRODUCT(('Phân công'!#REF!='Thù lao'!A16)*(RIGHT('Phân công'!$C$2:$C$259,3)="14C")*('Phân công'!#REF!="Tiếng Việt")) -> #REF! | X16: =SUMPRODUCT(('Phân công'!#REF!='Thù lao'!A16)*(RIGHT('Phân công'!$C$2:$C$259,3)="14C")*('Phân công'!#REF!="Tiếng Anh")) -> #REF! | Y16: =SUMPRODUCT(('Phân công'!#REF!='Thù lao'!A16)*(RIGHT('Phân công'!$C$10:$C$259,3)="4CA")) -> #REF! | Z16: =SUMPRODUCT(('Phân công'!#REF!='Thù lao'!A16)*(RIGHT('Phân công'!$C$2:$C$259,3)="404")) -> #REF! | AA16: =SUMPRODUCT(('Phân công'!#REF!='Thù lao'!A16)*(RIGHT('Phân công'!$C$2:$C$259,3)="412")) -> #REF! | AB16: =SUMPRODUCT(('Phân công'!#REF!='Thù lao'!A16)*(RIGHT('Phân công'!$C$2:$C$259,3)="414")) -> #REF! | AC16: =SUMPRODUCT(('Phân công'!#REF!='Thù lao'!A16)*(RIGHT('Phân công'!$C$2:$C$259,3)="04C")*('Phân công'!#REF!="Tiếng Việt")) -> #REF! | AD16: =SUMPRODUCT(('Phân công'!#REF!='Thù lao'!A16)*(RIGHT('Phân công'!$C$2:$C$259,3)="04C")*('Phân công'!#REF!="Tiếng Anh")) -> #REF! | AE16: =SUMPRODUCT(('Phân công'!#REF!='Thù lao'!A16)*(RIGHT('Phân công'!$C$2:$C$259,3)="14C")*('Phân công'!#REF!="Tiếng Việt")) -> #REF! | AF16: =SUMPRODUCT(('Phân công'!#REF!='Thù lao'!A16)*(RIGHT('Phân công'!$C$2:$C$259,3)="14C")*('Phân công'!#REF!="Tiếng Anh")) -> #REF! | AG16: =SUMPRODUCT(('Phân công'!#REF!='Thù lao'!A16)*(RIGHT('Phân công'!$C$2:$C$259,3)="4CA")) -> #REF! | AH16: =SUMPRODUCT(('Phân công'!#REF!='Thù lao'!A16)*(RIGHT('Phân công'!$C$2:$C$259,3)="404")) -> #REF! | AI16: =SUMPRODUCT(('Phân công'!#REF!='Thù lao'!A16)*(RIGHT('Phân công'!$C$2:$C$259,3)="412")) -> #REF! | AJ16: =SUMPRODUCT(('Phân công'!#REF!='Thù lao'!A16)*(RIGHT('Phân công'!$C$2:$C$259,3)="414")) -> #REF! | AK16: =SUMPRODUCT(('Phân công'!#REF!='Thù lao'!A16)*(RIGHT('Phân công'!$C$2:$C$259,3)="04C")*('Phân công'!#REF!="Tiếng Việt")) -> #REF! | AL16: =SUMPRODUCT(('Phân công'!#REF!='Thù lao'!A16)*(RIGHT('Phân công'!$C$2:$C$259,3)="04C")*('Phân công'!#REF!="Tiếng Anh")) -> #REF! | AM16: =SUMPRODUCT(('Phân công'!#REF!='Thù lao'!A16)*(RIGHT('Phân công'!$C$2:$C$259,3)="14C")*('Phân công'!#REF!="Tiếng Việt")) -> #REF! | AN16: =SUMPRODUCT(('Phân công'!#REF!='Thù lao'!A16)*(RIGHT('Phân công'!$C$2:$C$259,3)="14C")*('Phân công'!#REF!="Tiếng Anh")) -> #REF! | AO16: =SUMPRODUCT(('Phân công'!#REF!='Thù lao'!A16)*(RIGHT('Phân công'!$C$2:$C$259,3)="4CA")) -> #REF! | AP16: =SUMPRODUCT(('Phân công'!#REF!='Thù lao'!A16)*(RIGHT('Phân công'!$C$2:$C$259,3)="404")) -> #REF! | AQ16: =SUMPRODUCT(('Phân công'!#REF!='Thù lao'!A16)*(RIGHT('Phân công'!$C$2:$C$259,3)="412")) -> #REF! | AR16: =SUMPRODUCT(('Phân công'!#REF!='Thù lao'!A16)*(RIGHT('Phân công'!$C$2:$C$259,3)="414")) -> #REF! | AS16: =SUMPRODUCT(('Phân công'!#REF!='Thù lao'!A16)*(RIGHT('Phân công'!$C$2:$C$259,3)="04C")*('Phân công'!#REF!="Tiếng Việt")) -> #REF! | AT16: =SUMPRODUCT(('Phân công'!#REF!='Thù lao'!A16)*(RIGHT('Phân công'!$C$2:$C$259,3)="04C")*('Phân công'!#REF!="Tiếng Anh")) -> #REF! | AU16: =SUMPRODUCT(('Phân công'!#REF!='Thù lao'!A16)*(RIGHT('Phân công'!$C$2:$C$259,3)="14C")*('Phân công'!#REF!="Tiếng Việt")) -> #REF! | AV16: =SUMPRODUCT(('Phân công'!#REF!='Thù lao'!A16)*(RIGHT('Phân công'!$C$2:$C$259,3)="14C")*('Phân công'!#REF!="Tiếng Anh")) -> #REF! | AW16: =SUMPRODUCT(('Phân công'!#REF!='Thù lao'!A16)*(RIGHT('Phân công'!$C$2:$C$259,3)="4CA")) -> #REF! | AX16: =AP16+AH16+Z16+R16 -> #REF! | AY16: =AQ16+AI16+AA16+S16 -> #REF! | AZ16: =AR16+AJ16+AB16+T16 -> #REF! | BA16: =AS16+AK16+AC16+U16 -> #REF! | BB16: =AT16+AL16+AD16+V16 -> #REF! | BC16: =AU16+AM16+AE16+W16 -> #REF! | BD16: =AV16+AN16+AF16+X16 -> #REF! | BE16: =AW16+AO16+AG16+Y16 -> #REF! | BF16: =SUMPRODUCT((B16:I16),($B$3:$I$3))*$BF$2 -> #REF! | BG16: =SUMPRODUCT(R16:Y16,$R$3:$Y$3)*$BG$2 -> #REF! | BH16: =SUMPRODUCT(Z16:AG16,$Z$3:$AG$3)*$BH$2 -> #REF! | BI16: =SUMPRODUCT(AH16:AO16,$AH$3:$AO$3)*$BI$2 -> #REF! | BJ16: =SUMPRODUCT(AP16:AW16,$AP$3:$AW$3)*$BJ$2 -> #REF! | BK16: =SUMPRODUCT((J16:Q16),($J$3:$Q$3))*$BK$2 -> #REF! | BL16: =BF16+BK16 -> #REF! | BM16: =SUM(BG16:BJ16) -> #REF! | BN16: =BM16+BK16 -> #REF! | BO16: =BL16+BM16 -> #REF!
... A22: ThS Hồ Thị Hồng Minh | B22: =SUMPRODUCT(('Phân công'!$D$2:$D$259=$A22)*('Phân công'!#REF!="X")*(RIGHT('Phân công'!$C$2:$C$259,3)="404")) -> #REF! | C22: =SUMPRODUCT(('Phân công'!$D$2:$D$259=$A22)*('Phân công'!#REF!="X")*(RIGHT('Phân công'!$C$2:$C$259,3)="412")) -> #REF! | D22: =SUMPRODUCT(('Phân công'!$D$2:$D$259=$A22)*('Phân công'!#REF!="X")*(RIGHT('Phân công'!$C$2:$C$259,3)="414")) -> #REF! | E22: =SUMPRODUCT(('Phân công'!$D$2:$D$259=$A22)*('Phân công'!#REF!="X")*(RIGHT('Phân công'!$C$2:$C$259,4)="404C")*('Phân công'!#REF!="Tiếng Việt")) -> #REF! | F22: =SUMPRODUCT(('Phân công'!$D$2:$D$259=$A22)*('Phân công'!#REF!="X")*(RIGHT('Phân công'!$C$2:$C$259,4)="404C")*('Phân công'!#REF!="Tiếng Anh")) -> #REF! | G22: =SUMPRODUCT(('Phân công'!$D$2:$D$259=$A22)*('Phân công'!#REF!="X")*(RIGHT('Phân công'!$C$2:$C$259,4)="414C")*('Phân công'!#REF!="Tiếng Việt")) -> #REF! | H22: =SUMPRODUCT(('Phân công'!$D$2:$D$259=$A22)*('Phân công'!#REF!="X")*(RIGHT('Phân công'!$C$2:$C$259,4)="414C")*('Phân công'!#REF!="Tiếng Anh")) -> #REF! | I22: =SUMPRODUCT(('Phân công'!$D$2:$D$259=$A22)*('Phân công'!#REF!="X")*(RIGHT('Phân công'!$C$2:$C$259,5)="404CA")) -> #REF! | J22: =SUMPRODUCT(('Phân công'!$D$2:$D$259=$A22)*('Phân công'!#REF!="X")*(RIGHT('Phân công'!$C$2:$C$259,3)="404")) -> #REF! | K22: =SUMPRODUCT(('Phân công'!$D$2:$D$259=$A22)*('Phân công'!#REF!="X")*(RIGHT('Phân công'!$C$2:$C$259,3)="412")) -> #REF! | L22: =SUMPRODUCT(('Phân công'!$D$2:$D$259=$A22)*('Phân công'!#REF!="X")*(RIGHT('Phân công'!$C$2:$C$259,3)="414")) -> #REF! | M22: =SUMPRODUCT(('Phân công'!$D$2:$D$259=$A22)*('Phân công'!#REF!="X")*(RIGHT('Phân công'!$C$2:$C$259,3)="04C")*('Phân công'!#REF!="Tiếng Việt")) -> #REF! | N22: =SUMPRODUCT(('Phân công'!$D$2:$D$259=$A22)*('Phân công'!#REF!="X")*(RIGHT('Phân công'!$C$2:$C$259,3)="04C")*('Phân công'!#REF!="Tiếng Anh")) -> #REF! | O22: =SUMPRODUCT(('Phân công'!$D$2:$D$259=$A22)*('Phân công'!#REF!="X")*(RIGHT('Phân công'!$C$2:$C$259,3)="14C")*('Phân công'!#REF!="Tiếng Việt")) -> #REF! | P22: =SUMPRODUCT(('Phân công'!$D$2:$D$259=$A22)*('Phân công'!#REF!="X")*(RIGHT('Phân công'!$C$2:$C$259,3)="14C")*('Phân công'!#REF!="Tiếng Anh")) -> #REF! | Q22: =SUMPRODUCT(('Phân công'!$D$2:$D$259=$A22)*('Phân công'!#REF!="X")*(RIGHT('Phân công'!$C$2:$C$259,3)="4CA")) -> #REF! | R22: =SUMPRODUCT(('Phân công'!#REF!='Thù lao'!A22)*(RIGHT('Phân công'!$C$2:$C$259,3)="404")) -> #REF! | S22: =SUMPRODUCT(('Phân công'!#REF!='Thù lao'!A22)*(RIGHT('Phân công'!$C$2:$C$259,3)="412")) -> #REF! | T22: =SUMPRODUCT(('Phân công'!#REF!='Thù lao'!A22)*(RIGHT('Phân công'!$C$2:$C$259,3)="414")) -> #REF! | U22: =SUMPRODUCT(('Phân công'!#REF!='Thù lao'!A22)*(RIGHT('Phân công'!$C$2:$C$259,3)="04C")*('Phân công'!#REF!="Tiếng Việt")) -> #REF! | V22: =SUMPRODUCT(('Phân công'!#REF!='Thù lao'!A22)*(RIGHT('Phân công'!$C$2:$C$259,3)="04C")*('Phân công'!#REF!="Tiếng Anh")) -> #REF! | W22: =SUMPRODUCT(('Phân công'!#REF!='Thù lao'!A22)*(RIGHT('Phân công'!$C$2:$C$259,3)="14C")*('Phân công'!#REF!="Tiếng Việt")) -> #REF! | X22: =SUMPRODUCT(('Phân công'!#REF!='Thù lao'!A22)*(RIGHT('Phân công'!$C$2:$C$259,3)="14C")*('Phân công'!#REF!="Tiếng Anh")) -> #REF! | Y22: =SUMPRODUCT(('Phân công'!#REF!='Thù lao'!A22)*(RIGHT('Phân công'!$C$10:$C$259,3)="4CA")) -> #REF! | Z22: =SUMPRODUCT(('Phân công'!#REF!='Thù lao'!A22)*(RIGHT('Phân công'!$C$2:$C$259,3)="404")) -> #REF! | AA22: =SUMPRODUCT(('Phân công'!#REF!='Thù lao'!A22)*(RIGHT('Phân công'!$C$2:$C$259,3)="412")) -> #REF! | AB22: =SUMPRODUCT(('Phân công'!#REF!='Thù lao'!A22)*(RIGHT('Phân công'!$C$2:$C$259,3)="414")) -> #REF! | AC22: =SUMPRODUCT(('Phân công'!#REF!='Thù lao'!A22)*(RIGHT('Phân công'!$C$2:$C$259,3)="04C")*('Phân công'!#REF!="Tiếng Việt")) -> #REF! | AD22: =SUMPRODUCT(('Phân công'!#REF!='Thù lao'!A22)*(RIGHT('Phân công'!$C$2:$C$259,3)="04C")*('Phân công'!#REF!="Tiếng Anh")) -> #REF! | AE22: =SUMPRODUCT(('Phân công'!#REF!='Thù lao'!A22)*(RIGHT('Phân công'!$C$2:$C$259,3)="14C")*('Phân công'!#REF!="Tiếng Việt")) -> #REF! | AF22: =SUMPRODUCT(('Phân công'!#REF!='Thù lao'!A22)*(RIGHT('Phân công'!$C$2:$C$259,3)="14C")*('Phân công'!#REF!="Tiếng Anh")) -> #REF! | AG22: =SUMPRODUCT(('Phân công'!#REF!='Thù lao'!A22)*(RIGHT('Phân công'!$C$2:$C$259,3)="4CA")) -> #REF! | AH22: =SUMPRODUCT(('Phân công'!#REF!='Thù lao'!A22)*(RIGHT('Phân công'!$C$2:$C$259,3)="404")) -> #REF! | AI22: =SUMPRODUCT(('Phân công'!#REF!='Thù lao'!A22)*(RIGHT('Phân công'!$C$2:$C$259,3)="412")) -> #REF! | AJ22: =SUMPRODUCT(('Phân công'!#REF!='Thù lao'!A22)*(RIGHT('Phân công'!$C$2:$C$259,3)="414")) -> #REF! | AK22: =SUMPRODUCT(('Phân công'!#REF!='Thù lao'!A22)*(RIGHT('Phân công'!$C$2:$C$259,3)="04C")*('Phân công'!#REF!="Tiếng Việt")) -> #REF! | AL22: =SUMPRODUCT(('Phân công'!#REF!='Thù lao'!A22)*(RIGHT('Phân công'!$C$2:$C$259,3)="04C")*('Phân công'!#REF!="Tiếng Anh")) -> #REF! | AM22: =SUMPRODUCT(('Phân công'!#REF!='Thù lao'!A22)*(RIGHT('Phân công'!$C$2:$C$259,3)="14C")*('Phân công'!#REF!="Tiếng Việt")) -> #REF! | AN22: =SUMPRODUCT(('Phân công'!#REF!='Thù lao'!A22)*(RIGHT('Phân công'!$C$2:$C$259,3)="14C")*('Phân công'!#REF!="Tiếng Anh")) -> #REF! | AO22: =SUMPRODUCT(('Phân công'!#REF!='Thù lao'!A22)*(RIGHT('Phân công'!$C$2:$C$259,3)="4CA")) -> #REF! | AP22: =SUMPRODUCT(('Phân công'!#REF!='Thù lao'!A22)*(RIGHT('Phân công'!$C$2:$C$259,3)="404")) -> #REF! | AQ22: =SUMPRODUCT(('Phân công'!#REF!='Thù lao'!A22)*(RIGHT('Phân công'!$C$2:$C$259,3)="412")) -> #REF! | AR22: =SUMPRODUCT(('Phân công'!#REF!='Thù lao'!A22)*(RIGHT('Phân công'!$C$2:$C$259,3)="414")) -> #REF! | AS22: =SUMPRODUCT(('Phân công'!#REF!='Thù lao'!A22)*(RIGHT('Phân công'!$C$2:$C$259,3)="04C")*('Phân công'!#REF!="Tiếng Việt")) -> #REF! | AT22: =SUMPRODUCT(('Phân công'!#REF!='Thù lao'!A22)*(RIGHT('Phân công'!$C$2:$C$259,3)="04C")*('Phân công'!#REF!="Tiếng Anh")) -> #REF! | AU22: =SUMPRODUCT(('Phân công'!#REF!='Thù lao'!A22)*(RIGHT('Phân công'!$C$2:$C$259,3)="14C")*('Phân công'!#REF!="Tiếng Việt")) -> #REF! | AV22: =SUMPRODUCT(('Phân công'!#REF!='Thù lao'!A22)*(RIGHT('Phân công'!$C$2:$C$259,3)="14C")*('Phân công'!#REF!="Tiếng Anh")) -> #REF! | AW22: =SUMPRODUCT(('Phân công'!#REF!='Thù lao'!A22)*(RIGHT('Phân công'!$C$2:$C$259,3)="4CA")) -> #REF! | AX22: =AP22+AH22+Z22+R22 -> #REF! | AY22: =AQ22+AI22+AA22+S22 -> #REF! | AZ22: =AR22+AJ22+AB22+T22 -> #REF! | BA22: =AS22+AK22+AC22+U22 -> #REF! | BB22: =AT22+AL22+AD22+V22 -> #REF! | BC22: =AU22+AM22+AE22+W22 -> #REF! | BD22: =AV22+AN22+AF22+X22 -> #REF! | BE22: =AW22+AO22+AG22+Y22 -> #REF! | BF22: =SUMPRODUCT((B22:I22),($B$3:$I$3))*$BF$2 -> #REF! | BG22: =SUMPRODUCT(R22:Y22,$R$3:$Y$3)*$BG$2 -> #REF! | BH22: =SUMPRODUCT(Z22:AG22,$Z$3:$AG$3)*$BH$2 -> #REF! | BI22: =SUMPRODUCT(AH22:AO22,$AH$3:$AO$3)*$BI$2 -> #REF! | BJ22: =SUMPRODUCT(AP22:AW22,$AP$3:$AW$3)*$BJ$2 -> #REF! | BK22: =SUMPRODUCT((J22:Q22),($J$3:$Q$3))*$BK$2 -> #REF! | BL22: =BF22+BK22 -> #REF! | BM22: =SUM(BG22:BJ22) -> #REF! | BN22: =BM22+BK22 -> #REF! | BO22: =BL22+BM22 -> #REF!
B23: =SUM(B4:B22) -> #REF! | C23: =SUM(C4:C22) -> #REF! | D23: =SUM(D4:D22) -> #REF! | E23: =SUM(E4:E22) -> #REF! | F23: =SUM(F4:F22) -> #REF! | G23: =SUM(G4:G22) -> #REF! | H23: =SUM(H4:H22) -> #REF! | I23: =SUM(I4:I22) -> #REF! | ... BO23: =SUM(BO4:BO22) -> #REF!

Sheet Bài nộp
A1: Timestamp | B1: Email Address | C1: Họ và tên | D1: MSSV | E1: Lớp | F1: Lựa chọn học phần | G1: Tên đề tài BCTT | H1: Ngôn ngữ viết | I1: bản scan Nhật ký thực tập | J1: bản scan Phiếu nhận xét của DN | K1: Báo cáo thực tập | L1: Ngôn ngữ viết BCTT [BCTT] | M1: Ngôn ngữ viết BCTT [KLTN] | N1: Tên đề tài BCTT 2 | O1: bản scan Nhật ký thực tập 2 | P1: bản scan Phiếu nhận xét của DN 2 | Q1: Báo cáo thực tập 2 | R1: Tên đề tài KLTN | S1: Khóa luận tốt nghiệp | T1: File check đạo văn | U1: Data (file excel hoặc csv) | V1: File code (nếu có) | W1: Giấy xác nhận cho phép sử dụng dữ liệu từ doanh nghiệp (nếu có)
A2: 46060.58 | B2: ducla20415@st.uel.edu.vn | C2: Lê Anh Đức | D2: K204151943 | E2: K20404C | F2: Chỉ nộp bài học phần Báo cáo thực tập | G2: PHÂN TÍCH TÌNH HÌNH TÀI CHÍNH NGÂN HÀNG TMCP ĐÔNG NAM Á (SEABANK) GIAI ĐOẠN 2021 - 2024 | H2: Tiếng Việt | I2: https://drive.google.com/open?id=1bPpj-Szm61CClB5Hoyogs-_fX2Zwfb5E | J2: https://drive.google.com/open?id=1gNHqS2p65BiUpAAVfBk_yQTxR18tevxC | K2: https://drive.google.com/open?id=1bYO9J67tZoSNvzA3hxF2HfQuDErGybRO
A3: 46073.412 | B3: anhdk22404b@st.uel.edu.vn | C3: Đỗ Kim Anh | D3: K224042344 | E3: K22412 | F3: Chỉ nộp bài học phần Báo cáo thực tập | G3: THE IMPACT OF INCOME DIVERSIFICATION ON PERFORMANCE AND RISK: EVIDENCE FROM VIETNAMESE COMMERCIAL BANKS | H3: Tiếng Anh | I3: https://drive.google.com/open?id=19BStCQrxpqV0NFxEUcH6AljNQBT5c5DE | J3: https://drive.google.com/open?id=1rTYXk6FN2wGnozy0PX_ciHE9ImO4l1oZ | K3: https://drive.google.com/open?id=1_lCAoLSpgcpsod6exHtYDXomFSr2aW_d
A4: 46077.356 | B4: vangchiaxarc22404b@st.uel.edu.vn | C4: Cheemeng Vangchixar | D4: K224042347 | E4: K22412 | F4: Chỉ nộp bài học phần Báo cáo thực tập | G4: Hoạt động cho vay tại NH TMCP Công thương Việt Nam chi nhánh Thủ Đức | H4: Tiếng Việt | I4: https://drive.google.com/open?id=1Sm0bJ34ecuYGoZsf4UMF1BS4cNCbCdWA | J4: https://drive.google.com/open?id=10BCu_IYNITbJahzxTU_xGod7QWZH1IiB | K4: https://drive.google.com/open?id=1UOQGB8o8XQtMOSGAtLHLXue5fXMF813M
A5: 46077.796 | B5: thuba22404a@st.uel.edu.vn | C5: Bùi Anh Thư | D5: K224040499 | E5: K22404 | F5: Chỉ nộp bài học phần Báo cáo thực tập | G5: CHIẾN LƯỢC PHÁT TRIỂN TIỀN GỬI KHÔNG KỲ HẠN TRONG HOẠT ĐỘNG HUY ĐỘNG VỐN TẠI NGÂN HÀNG THƯƠNG MẠI CỔ PHẦN NGOẠI THƯƠNG VIỆT NAM | H5: Tiếng Việt | I5: https://drive.google.com/open?id=1rqJz1EoC93nx1MIcNLhtYglfQcnI9_i2 | J5: https://drive.google.com/open?id=1yBqDdL_X3NgnZSwZOH2CQDhtX9dQR-UG | K5: https://drive.google.com/open?id=1J4xtBy9QNVmPhDRPx7qpwctHocEbS20u
A6: 46077.835 | B6: thyhna22404c@st.uel.edu.vn | C6: Hồ Nguyễn Anh Thy | D6: K224040589 | E6: K22404C | F6: Chỉ nộp bài học phần Báo cáo thực tập | G6: An Analysis of the Effectiveness of Working Capital Management at Thanh Cong Textile Garment Investment Trading Joint Stock Company during the period 2020–2024 | H6: Tiếng Anh | I6: https://drive.google.com/open?id=1F1ZqGXopONy6CtTPeVtZ68vufJxrLHyY | J6: https://drive.google.com/open?id=1IcVHLLKUxeuCDygohZCut6KkkQl__HN8 | K6: https://drive.google.com/open?id=1ksCUg-CceSoaqIlWIlh-9KeUQJmeZJ7V
A7: 46078.944 | B7: huyln22404a@st.uel.edu.vn | C7: Lý Nhật Huy | D7: K224040475 | E7: K22404 | F7: Chỉ nộp bài học phần Báo cáo thực tập | G7: PHÂN TÍCH TÌNH HÌNH TÀI CHÍNH VÀ ĐỊNH GIÁ CỔ PHIẾU CÔNG TY CỔ PHẦN ĐẦU TƯ THẾ GIỚI DI ĐỘNG 2025 (MWG) | H7: Tiếng Việt | I7: https://drive.google.com/open?id=1olYjQ593-zRhsnaveWHSSo4FD8sB1MUs | J7: https://drive.google.com/open?id=1gPBTU0tr5RF3KELuMnzeS8PiuQi7LJux | K7: https://drive.google.com/open?id=1SFZ2gXIfydpYWM5Z6zHuB5S99MPKqyws
A8: 46079.4 | B8: phandolakm22404b@st.uel.edu.vn | C8: PHANDOLAK MONA | D8: K224042345 | E8: K22412 | F8: Chỉ nộp bài học phần Báo cáo thực tập | G8: ĐÁNH GIÁ HOẠT ĐỘNG PHÁT HÀNH VÀ THANH TOÁN BẰNG PHƯƠNG THỨC TÍN DỤNG CHỨNG TỪ TẠI NGÂN HÀNG TMCP ĐẦU TƯ VÀ PHÁT TRIỂN VIỆT NAM – CHI NHÁNH BẾN NGHÉ | H8: Tiếng Việt | I8: https://drive.google.com/open?id=1dxPGWja7awTvQtuMPvabUpgHGUayNGYo | J8: https://drive.google.com/open?id=1XLr3L5U77iY2vkkKxLq8C7_JM40Y1dnG | K8: https://drive.google.com/open?id=1dwtSoFMFtYCuFLdFEC0j-Z-2XlyuOnkZ
A9: 46079.436 | B9: hungntv22404a@st.uel.edu.vn | C9: Nguyễn Trần Vũ Hùng | D9: K224040477 | E9: K22404 | F9: Chỉ nộp bài học phần Báo cáo thực tập | G9: HOẠT ĐỘNG CHO VAY KHÁCH HÀNG CÁ NHÂN TẠI NGÂN HÀNG THƯƠNG MẠI CỔ PHẦN ĐẦU TƯ VÀ PHÁT TRIỂN VIỆT NAM - CHI NHÁNH ĐÔNG SÀI GÒN | H9: Tiếng Việt | I9: https://drive.google.com/open?id=1nXBM2S34usx6sTXWpmwdOX8-n6O0Gbyh | J9: https://drive.google.com/open?id=1aPd9e0ckgGvh8QsqgjQaE0jQXdn4c-pO | K9: https://drive.google.com/open?id=1BInodur7Z5z0B9Lw5TfPgMKVfBZdqE9Y
A10: 46079.518 | B10: toanlm22414@st.uel.edu.vn | C10: Lê Minh Toàn | D10: K224141698 | E10: K22414 | F10: Chỉ nộp bài học phần Báo cáo thực tập | G10: HIỆU QUẢ TRONG CHIẾN LƯỢC ĐẦU TƯ VÀO CÔNG NGHỆ CỦA CÁC CÔNG TY CHỨNG KHOÁN VIỆT NAM | H10: Tiếng Việt | I10: https://drive.google.com/open?id=1TqEvj-_xzHEqxS2ZEpTVOmSYQhoNoZWi | J10: https://drive.google.com/open?id=1nL_MdriRxvIGzWw4NGH7YZj2XiIp4Rmu | K10: https://drive.google.com/open?id=1cd0lSvNiTAv6j8toFgLq_KptbDsi3U0O
A11: 46079.548 | B11: thinhlh22404a@st.uel.edu.vn | C11: Lê Hưng Thịnh | D11: K224040498 | E11: K22404 | F11: Chỉ nộp bài học phần Báo cáo thực tập | G11: ỨNG DỤNG MÔ HÌNH CAMEL ĐỂ PHÂN TÍCH HIỆU QUẢ HOẠT ĐỘNG CỦA NGÂN HÀNG THƯƠNG MẠI CỔ PHẦN CÔNG THƯƠNG VIỆT NAM | H11: Tiếng Việt | I11: https://drive.google.com/open?id=1c5rIJfwjjMXXtfsZUrh5kpXNqHxjjBZD | J11: https://drive.google.com/open?id=1BVeSmiY_DZdNm4bq2PI7OkOZ6MxZ7Pm1 | K11: https://drive.google.com/open?id=1sczyMmMeHwOPJ8jN2_L35fVikL4tz7h3
A12: 46079.588 | B12: nguyetnta22404b@st.uel.edu.vn | C12: Nguyễn Trần Ái Nguyệt | D12: K224040534 | E12: K22404 | F12: Chỉ nộp bài học phần Báo cáo thực tập | G12: ĐÁNH GIÁ HIỆU QUẢ HOẠT ĐỘNG TÀI CHÍNH CỦA CÔNG TY CỔ PHẦN CHỨNG KHOÁN FPT TRONG GIAI ĐOẠN 2020 – 2024 | H12: Tiếng Việt | I12: https://drive.google.com/open?id=1FGElvJ2-BJ-baRGIkbgo9-QbvIpGYql2 | J12: https://drive.google.com/open?id=1sj6Joq101SF0xpq64DlIsoYxgLlEiN6T | K12: https://drive.google.com/open?id=1fRHRJTGjqD8YGngs8LKjIdGQUS1O8Iib
A13: 46079.608 | B13: thuongnt22404a@st.uel.edu.vn | C13: Nguyễn Thị Thương | D13: K224040500 | E13: K22404 | F13: Chỉ nộp bài học phần Báo cáo thực tập | G13: Đánh giá hiệu quả hoạt động Telesales tại Trung tâm tư vấn Giải pháp Tài chính trực tuyến miền Nam - Ngân hàng TMCP Kỹ Thương Việt Nam | H13: Tiếng Việt | I13: https://drive.google.com/open?id=1bxf5upHbPfSkvvjoGvnjoAojLHHuWakh | J13: https://drive.google.com/open?id=1tr2wMa5YJt4VCShrY0uHebO-IP3XidpP | K13: https://drive.google.com/open?id=1y-JsJvuead8YKe8H7TrJyu7Icte0-op2
A14: 46079.609 | B14: thudhm22404c@st.uel.edu.vn | C14: Đặng Hoài Minh Thư | D14: K224040586 | E14: K22404C | F14: Chỉ nộp bài học phần Báo cáo thực tập | G14: PRELIMINARY FINANCIAL STATEMENT ANALYSIS IN AUDIT PLANNING CONDUCTED BY VACO AUDITING COMPANY LIMITED | H14: Tiếng Anh | I14: https://drive.google.com/open?id=1OiZxkYvW9eNfNtoGbvePXVD1lyYXUo8y | J14: https://drive.google.com/open?id=1WhP-83xm-CNp2GmmwryGA-uzIaV-0Gxe | K14: https://drive.google.com/open?id=1HgQguP2dpHt_7f15LJZfjlF-GZIYHAB-
A15: 46079.625 | B15: mrnnaamm@gmail.com | C15: Dương Công Nam | D15: K224040482 | E15: 414 | F15: Chỉ nộp bài học phần Báo cáo thực tập | G15: ĐÁNH GIÁ NĂNG LỰC TÀI CHÍNH CỦA NGÂN HÀNG THƯƠNG MẠI CỔ PHẦN TIÊN PHONG THÔNG QUA MÔ HÌNH CAMELS | H15: Tiếng Việt | I15: https://drive.google.com/open?id=10hHE6c4hJL9lv3U7T-AfCmxrm16MIfQ_ | J15: https://drive.google.com/open?id=1PGJIqK7yu3AXnxS49gVVUCFDMuJIZi5N | K15: https://drive.google.com/open?id=1JNliL4ujxwOAKYjnW5wKtqBINm1EqJYe
A16: 46079.629 | B16: phuongpt22404c@st.uel.edu.vn | C16: Phạm Thị Phương | D16: K224040582 | E16: K22404C | F16: Chỉ nộp bài học phần Báo cáo thực tập | G16: THU NHẬP NGOÀI LÃI TÁC ĐỘNG ĐẾN HIỆU QUẢ HOẠT ĐỘNG CỦA NGÂN HÀNG VIỆT NAM TRONG BỐI CẢNH CHUYỂN ĐỔI SỐ | H16: Tiếng Việt | I16: https://drive.google.com/open?id=1BKye8uTXhr4UsHEWN-wvYnf0pM2-TFSf | J16: https://drive.google.com/open?id=1mjjP_dyZHqAfVKCtQQoeHS4uo4ETLqQT | K16: https://drive.google.com/open?id=1jptUsxqwS_H3ny2LKQmNPK_orRsn5J_Z
A17: 46079.66 | B17: duynt22404b@st.uel.edu.vn | C17: Nguyễn Triệu Duy | D17: K224040518 | E17: K22404 | F17: Chỉ nộp bài học phần Báo cáo thực tập | G17: Phân tích hiệu quả hoạt động kinh doanh của Công ty Cổ phần Đầu tư và Kinh doanh Nhà Khang Điền | H17: Tiếng Việt | I17: https://drive.google.com/open?id=1NfJYUhD6vu9nHpH_RKdwLn5Viip3ZwP5 | J17: https://drive.google.com/open?id=1m-lAE-7eKa5RAn2XlWToZIg33ieDGnkt | K17: https://drive.google.com/open?id=1uJ2Tnz1IAtov7rg2Zy8ssFFLF_cpaHHm
A18: 46079.688 | B18: tranlb22404b@st.uel.edu.vn | C18: Lý Bảo Trân | D18: K224040553 | E18: K22404 | F18: Chỉ nộp bài học phần Báo cáo thực tập | G18: Hoạt động cho vay mua nhà, mua đất đối với khách hàng cá nhân tại Ngân hàng TMCP Công Thương Việt Nam – Chi nhánh Đông Thành phố Hồ Chí Minh | H18: Tiếng Việt | I18: https://drive.google.com/open?id=1vyx1Pi2ElMDZO-0T6LAiK0pylCbw4niS | J18: https://drive.google.com/open?id=1NNtYx1_XHeKs4RyvY8baZIYE_PLbD-1T | K18: https://drive.google.com/open?id=1vsvmJkIhYErlN-2IJ7dWVCd8HJ81Ln11
A19: 46079.8 | B19: phuongnnc22404a@st.uel.edu.vn | C19: Nguyễn Ngọc Châu Phương | D19: K224040490 | E19: K22412 | F19: Chỉ nộp bài học phần Báo cáo thực tập | G19: EVALUATING THE PERFORMANCE OF THE JOINT STOCK COMMERCIAL BANK FOR FOREIGN TRADE OF VIETNAM (VIETCOMBANK) USING THE CAMELS MODEL | H19: Tiếng Anh | I19: https://drive.google.com/open?id=1HLFTwmtcruBH3iRrMKDLtaLOU2J6N7HW | J19: https://drive.google.com/open?id=1N52108VTIhjHlbnRbY2RpdApZbj04yyV | K19: https://drive.google.com/open?id=1eFxh92GSbfyDr8T995XvcEU4mk8oCIe1
A20: 46079.815 | B20: thunna22404b@st.uel.edu.vn | C20: Nguyễn Ngọc Anh Thư | D20: K224040549 | E20: K22404 | F20: Chỉ nộp bài học phần Báo cáo thực tập | G20: CÁC YẾU TỐ TÁC ĐỘNG ĐẾN QUYẾT ĐỊNH SỬ DỤNG ĐÒN BẨY TÀI CHÍNH CỦA CÁC DOANH NGHIỆP NGÀNH VẬT LIỆU XÂY DỰNG ĐƯỢC NIÊM YẾT TRÊN SÀN HOSE GIAI ĐOẠN 2019-2024 | H20: Tiếng Việt | I20: https://drive.google.com/open?id=1kZ4GM5iE0HPJwjnTTeNtDpjuK8BwlFSt | J20: https://drive.google.com/open?id=15yxuj6DmjVeUW2NlcEdQdmvdLScRC7lz | K20: https://drive.google.com/open?id=1XXmyiUhR_oFSYottEIMoOJsKxwXx4jlI
A21: 46079.835 | B21: thuntm22404c@st.uel.edu.vn | C21: Nguyễn Thị Minh Thư | D21: K224040587 | E21: K22404C | F21: Chỉ nộp bài học phần Báo cáo thực tập | G21: ĐÁNH GIÁ TÁC ĐỘNG CỦA CHUYỂN ĐỔI SỐ LÊN RỦI RO TÍN DỤNG CỦA NGÂN HÀNG THƯƠNG MẠI TẠI VIỆT NAM | H21: Tiếng Việt | I21: https://drive.google.com/open?id=1SYEtyGYYytdzElspvxaYpzCY-ZSpYxVH | J21: https://drive.google.com/open?id=17hncmyUhPoVqZ6oT6H17LlL2ZUcST_wk | K21: https://drive.google.com/open?id=11znKl67m_2PZHfdThT2qgAufcskTJMY3
A22: 46079.854 | B22: bilt22404b@st.uel.edu.vn | C22: Lương Thanh Bi | D22: K224040516 | E22: K224040516 | F22: Chỉ nộp bài học phần Báo cáo thực tập | G22: CÁC YẾU TỐ ẢNH HƯỞNG ĐẾN QUYẾT ĐỊNH NẮM GIỮ TIỀN MẶT CỦA CÁC CÔNG TY CHẾ BIẾN THỰC PHẨM TẠI VIỆT NAM | H22: Tiếng Việt | I22: https://drive.google.com/open?id=1ETP_p9zIwV9X1V2R0wOvJol3B0ODK6RQ | J22: https://drive.google.com/open?id=19mkNqt3zxqbVVr2lWbXMI3hcSdhjz3lp | K22: https://drive.google.com/open?id=1u6F3Innl9bhfEWtOYnGhCExB3Thy8WCK
A23: 46079.878 | B23: tamntm22404b@st.uel.edu.vn | C23: Nguyễn Thị Minh Tâm | D23: K224040543 | E23: K22404 | F23: Chỉ nộp bài học phần Báo cáo thực tập | G23: Phân tích hoạt động cho vay mua căn hộ chung cư và nhà ở dự án đối với khách hàng cá nhân tại Ngân hàng TMCP Công Thương Việt Nam - Chi nhánh Đông TP. Hồ Chí Minh | H23: Tiếng Việt | I23: https://drive.google.com/open?id=1o9CAYJ7IP2TlijSGOAJOM45v_8V6izVg | J23: https://drive.google.com/open?id=1Gp22yM9A4kYW7lvvsbq0uKGSHxtrx8mO | K23: https://drive.google.com/open?id=1GRsEoRgJgOS7hhIC6mxNCBarXgho8D4R
A24: 46079.88 | B24: dangvyban2004@gmail.com | C24: Nguyễn Đặng Vi Bân | D24: K224020262 | E24: K22404C | F24: Chỉ nộp bài học phần Báo cáo thực tập | G24: FINANCIAL ANALYSIS AND STOCK VALUATION OF SONG HONG GARMENT JOINT STOCK COMPANY (MSH) | H24: Tiếng Anh | I24: https://drive.google.com/open?id=19xYL4zlbzid-cjl0Vi42MeGq0P1X6jAa | J24: https://drive.google.com/open?id=1bTPNgAlNUc0SAVKyLYK6-o9csORCRq9E | K24: https://drive.google.com/open?id=1rC2DeidS_gZ4qhktSYT902EFM59Kxjok
A25: 46079.887 | B25: nhinty22404a@st.uel.edu.vn | C25: Nghiêm Thùy Yến Nhi | D25: K224040487 | E25: K22412 | F25: Chỉ nộp bài học phần Báo cáo thực tập | G25: Hoạt động quản trị tài sản ngắn hạn tại CTCP DNP Holding | H25: Tiếng Việt | I25: https://drive.google.com/open?id=1C0Ya-YgK9PvZCw4SdHr98Vec1eqDvA8M | J25: https://drive.google.com/open?id=1B7_tsPSvNuaq1eSU9JVjd5Hhs7iofp_h | K25: https://drive.google.com/open?id=1YyHL29HnmiTj9QNnRo7Rgh2QtnbKbNJ4
A26: 46079.905 | B26: maihx22404b@st.uel.edu.vn | C26: Hà Xuân Mai | D26: K224040529 | E26: K22404 | F26: Chỉ nộp bài học phần Báo cáo thực tập | G26: PHÂN TÍCH HIỆU QUẢ TÀI CHÍNH CỦA CÔNG TY CỔ PHẦN DẦU KHÍ CÀ MAU GIAI ĐOẠN 2020-2024 | H26: Tiếng Việt | I26: https://drive.google.com/open?id=1qp-R-hVnmlNnaRvrBVSLVjACH3jMcmfD | J26: https://drive.google.com/open?id=1RztzKC3XVHp6ni2NJIQ7tJ5TkfQHiUgG | K26: https://drive.google.com/open?id=1ZgbjVCh4SBcrQR84hgrbhQfOdI1WB6fe
A27: 46079.949 | B27: thuylhn22404b@st.uel.edu.vn | C27: Lê Hoàng Như Thuỷ | D27: K224040548 | E27: K22404 | F27: Chỉ nộp bài học phần Báo cáo thực tập | G27: Giải pháp nâng cao minh bạch thông tin tài chính cho doanh nghiệp niêm yết thông qua hoạt động tư vấn của Công ty Cổ phần Chứng khoán FPT | H27: Tiếng Việt | I27: https://drive.google.com/open?id=11d8MrFEVuWRZHhl0abhcarhKeDAY2OBv | J27: https://drive.google.com/open?id=1nGcoKlQdsxkQy8hohgbnvwsRQ14jwydf | K27: https://drive.google.com/open?id=13GY-y9dNREtqCE1bboJBQYS8zrVH8yOJ
... A111: 46080.976 | B111: hoangpn22404b@st.uel.edu.vn | C111: Phí Nhật Hoàng | D111: K224040523 | E111: K22412 | F111: Chỉ nộp bài học phần Báo cáo thực tập | G111: An Assessment of Digital Transformation at Asia Commercial Joint Stock Bank | H111: Tiếng Anh | I111: https://drive.google.com/open?id=174qWnzIUwu3xhiZfD8biTJ16pOHlnNdQ | J111: https://drive.google.com/open?id=163W2WXqlFzr4shovAoFb6uMLUbe-NSq0 | K111: https://drive.google.com/open?id=1BnIVncCOcdJF6v84NxGLYeyKkujImA0X
A112: 46080.977 | B112: linhtp22404c@st.uel.edu.vn | C112: Trần Phương Linh | D112: K224040571 | E112: K22404C | F112: Chỉ nộp bài học phần Báo cáo thực tập | G112: FACTORS AFFECTING CREDIT RISK IN THE CONSUMER LOAN PORTFOLIO AT VIETNAM EXPORT IMPORT COMMERCIAL JOINT STOCK BANK (EIB) FOR THE PERIOD 2022-2024 | H112: Tiếng Anh | K112: https://drive.google.com/open?id=17BEXSfx0QKUT4_TtDuQP-LMLbs554c8d
A113: 46080.99 | B113: duyenltm22414@st.uel.edu.vn | C113: Lê Thị Mỹ Duyên | D113: K224141655 | E113: K22414 | F113: Chỉ nộp bài học phần Báo cáo thực tập | G113: Xây dựng hệ thống RAG phân tích báo cáo tài chính tự động | H113: Tiếng Việt | I113: https://drive.google.com/open?id=1Ag5D6utNIKCVxPXwweCPQCxkS7lPhB1c | J113: https://drive.google.com/open?id=1DpLlA7ntdcCv94TurUbt9tzkKJRmtR6W | K113: https://drive.google.com/open?id=1cmsLf-6_xmxl1dlYyznFpzsWa9yjYVzp
A114: 46080.993 | B114: nganlb22404b@st.uel.edu.vn | C114: LÊ BẢO NGÂN | D114: K224040531 | E114: K22412 | F114: Chỉ nộp bài học phần Báo cáo thực tập | G114: EVALUATION OF LENDING ACTIVITIES AT FORTUNE VIETNAM JOINT STOCK COMMERCIAL BANK | H114: Tiếng Anh | I114: https://drive.google.com/open?id=1Fdip9shDOGotAU6dYud5DuVjXhAE7J2V | J114: https://drive.google.com/open?id=1Irfq0QCOeafOKhtbWVaq3tXrBM-WPXUJ | K114: https://drive.google.com/open?id=1rCaXrFMUF0cCSLI0u_2dWD5Dsb76P0vE
A115: 46080.997 | B115: tienvnt22414c@st.uel.edu.vn | C115: Vũ Ngọc Thuỷ Tiên | D115: K224141738 | E115: K22414C | F115: Chỉ nộp bài học phần Báo cáo thực tập | G115: Lending activities to individual customers for home purchases at Joint Stock Commercial Bank for Investment and Development of Vietnam (BIDV) - East Saigon Branch | H115: Tiếng Anh | I115: https://drive.google.com/open?id=1XvwWo1Up79UlVSR0gkFNjLdaBtyXAztC | J115: https://drive.google.com/open?id=19m7N2P7Kz6V_Lh_mwGaHlutjXk_Ju26h | K115: https://drive.google.com/open?id=1aVJPNkyxt72OWW4oZI0YmF6HPgd6Zy1_
A116: 46081.073 | B116: uyenpnk22404a@st.uel.edu.vn | C116: Phan Ngọc Khánh Uyên | D116: K224040509 | E116: K22412 | F116: Chỉ nộp bài học phần Báo cáo thực tập | G116: ĐÁNH GIÁ QUY TRÌNH KIỂM SOÁT VÀ HOÀN THIỆN LƯU TRỮ HỒ SƠ TÍN DỤNG TẠI NGÂN HÀNG TMCP CÔNG THƯƠNG VIỆT NAM (VIETINBANK) – CHI NHÁNH THỦ ĐỨC | H116: Tiếng Việt | I116: https://drive.google.com/open?id=1oyu1JSRH08enJQtF7rSrZdieCyAIKxow | J116: https://drive.google.com/open?id=1IfcrmeGy2Iw2ygjQQOl3s97hYDiPdXrB | K116: https://drive.google.com/open?id=1Xma61F0WgO4Sg6PXa3_vX0FflQhn1xnS
A117: 46081.196 | B117: truclt22404b@st.uel.edu.vn | C117: Lê Thanh Trúc | D117: K224040554 | E117: K22412 | F117: Chỉ nộp bài học phần Báo cáo thực tập | G117: Đánh giá hiệu quả huy động vốn của Ngân hàng TMCP Đầu tư và Phát triển Việt Nam (BIDV) | H117: Tiếng Việt | I117: https://drive.google.com/open?id=1tSBKQMPAxGt2jLIhSMRiBOihgV1Ly3Xg | J117: https://drive.google.com/open?id=1v3jlv1Z8oGRnQintXpBv6AJNrvdrZ326 | K117: https://drive.google.com/open?id=1xdWm_hEkgsfxEmhh6q4r-C41nCQ2gZfO
A118: 46075.914 | B118: duattn22404ca@st.uel.edu.vn | C118: Trần Nhật Duật | D118: K224040602 | E118: K22404CA | F118: Nộp Báo cáo thực tập và Khóa luận tốt nghiệp | H118: Tiếng Anh | L118: Tiếng Anh | M118: Tiếng Anh | N118: METHODS OF VALUING LISTED ENTERPRISES: THE CASE OF BINH MINH PLASTIC JOINT STOCK COMPANY | O118: https://drive.google.com/open?id=1GZZ-i-oASBLWM_Xd12YThhxdlE5G7yCt | P118: https://drive.google.com/open?id=1V_zp4exDbaylBSD8HZfPMfGkNUYisvQm | Q118: https://drive.google.com/open?id=1teVeQvKnkxgPoK2cZ4BZQLcDbAMe9Lxv | R118: METHODS OF VALUING LISTED ENTERPRISES: THE CASE OF BINH MINH PLASTIC JOINT STOCK COMPANY | S118: https://drive.google.com/open?id=1GHkdn3sqgcwT1dyaKtr2HHdGYl5sGDfg | T118: https://drive.google.com/open?id=1vM7CE9t45D1zVKTv_nN1Sl8NgF0nvaKN | U118: https://drive.google.com/open?id=1osmXkI567a34b2AyD5AqFVQKABHH_t9_ | W118: https://drive.google.com/open?id=1wq0UPsQPRRJJi6aCaOsYlDy2iVOIzeV2
A119: 46076.915 | B119: tiennm22404b@st.uel.edu.vn | C119: Ngô Minh Tiến | D119: K224040551 | E119: K22404 | F119: Nộp Báo cáo thực tập và Khóa luận tốt nghiệp | H119: Tiếng Việt | L119: Tiếng Việt | M119: Tiếng Việt | N119: KIỂM ĐỊNH TÍNH THỰC NGHIỆM LÝ THUYẾT MÔ HÌNH FAMA-FRENCH NĂM NHÂN TỐ TẠI THỊ TRƯỜNG CHỨNG KHOÁN VIỆT NAM: TRƯỜNG HỢP VN30 | O119: https://drive.google.com/open?id=1j3VkCpHi14ZozTjXxGVtI1xsBZAEIS6H | P119: https://drive.google.com/open?id=1jmYE8Sp2ntU7UR_ZOWxu7RL1_zROlBP_ | Q119: https://drive.google.com/open?id=1kya26-NPUvOma88JNHpEfC91nIi5w3p2 | R119: KIỂM ĐỊNH TÍNH THỰC NGHIỆM LÝ THUYẾT MÔ HÌNH FAMA-FRENCH NĂM NHÂN TỐ TẠI THỊ TRƯỜNG CHỨNG KHOÁN VIỆT NAM: TRƯỜNG HỢP VN30 | S119: https://drive.google.com/open?id=1C9PPQymOOu9FxcPWy1KNGIASBoUJ1k_j | T119: https://drive.google.com/open?id=1zjmZW8vVWZ9eXIQdyqmPkMCaO2bFofKe | U119: https://drive.google.com/open?id=11L4fW4WtnDIuCshuoUdjXqKbIGEXW13h | V119: https://drive.google.com/open?id=1IaMRYSPeRnM8BPlKUZJOzUC3D2eFit66
A120: 46078.496 | B120: quipt22404ca@st.uel.edu.vn | C120: PHAN TRỌNG QUÍ | D120: K224040621 | E120: 404ca | F120: Nộp Báo cáo thực tập và Khóa luận tốt nghiệp | H120: Tiếng Việt | L120: Tiếng Việt | M120: Tiếng Anh | N120: HOẠT ĐỘNG CHO VAY SẢN XUẤT KINH DOANH ĐỐI VỚI KHÁCH HÀNG CÁ NHÂN TẠI NGÂN HÀNG THƯƠNG MẠI CỔ PHẦN PHÁT TRIỂN THÀNH PHỐ HỒ CHÍ MINH – CHI NHÁNH GIA ĐỊNH – PHÒNG GIAO DỊCH NAM SÀI GÒN | O120: https://drive.google.com/open?id=16QJLHghsRBKPh1rWSFi9ZZ0IT3-4qmOD | P120: https://drive.google.com/open?id=1UYaDws5tqwrllIoPgSPpPTzSsxJfHOm7 | Q120: https://drive.google.com/open?id=13m23uLAStHyxZqDD5PTUP137-UARmYlm | R120: THE IMPACT OF BANK GUARANTEE ACTIVITIES ON RISK AND PERFORMANCE OF VIETNAMESE COMMERCIAL BANKS | S120: https://drive.google.com/open?id=1zV0AxzFWbckwNf0kiz2DTMLGHOlco-wW | T120: https://drive.google.com/open?id=110H8X-dw2HSEOhomYFYPOzL6C3Gqrfcs | U120: https://drive.google.com/open?id=15cuhP7X0kFiEFjHfzu6A2QaGrxHJQz5l
A121: 46078.586 | B121: ngocnd22414@st.uel.edu.vn | C121: Nguyễn Duy Ngọc | D121: K224142348 | E121: K22414 | F121: Nộp Báo cáo thực tập và Khóa luận tốt nghiệp | H121: Tiếng Việt | L121: Tiếng Việt | M121: Tiếng Việt | N121: Xây dựng hệ thống Chatbot tư vấn sản phẩm dịch vụ ngân hàng tích hợp AI cho tệp khách hàng cá nhân của Ngân hàng MBV | O121: https://drive.google.com/open?id=1UlLjmX6BriGlw_iurNNlMJ8lyZhZlwQp | P121: https://drive.google.com/open?id=1-lpECFek7Fi4mZZ7d2yurXBNdeatoj5j | Q121: https://drive.google.com/open?id=1iUtXqJVB40o8_2D_N1MFwy-nkPPTHleL | R121: Xây dựng hệ thống Chatbot tư vấn sản phẩm dịch vụ ngân hàng tích hợp AI cho tệp khách hàng cá nhân của Ngân hàng MBV | S121: https://drive.google.com/open?id=1RvKcqo8SySvvbr_jmQ3b5GjRG1FCT5Ac | T121: https://drive.google.com/open?id=1t5-pgW_hABSPnr8a7HZ4IYkNEp7OXIzt | U121: https://drive.google.com/open?id=1yD169K8t4wO1Xdligi8fcduKjaNp5sWf | V121: https://drive.google.com/open?id=1aE41IHUfgLFXxUzcxHF8y7ZaWU-6dMRZ | W121: https://drive.google.com/open?id=1y7TOegs3z_T7eIDnSdP-ssisxEsS-w7Y
A122: 46078.787 | B122: linhvg22404c@st.uel.edu.vn | C122: Vũ Gia Linh | D122: K224040572 | E122: K22404C | F122: Nộp Báo cáo thực tập và Khóa luận tốt nghiệp | H122: Tiếng Anh | L122: Tiếng Anh | M122: Tiếng Anh | N122: Factors affecting financial distress risk measured by Altman Z-score: Evidence from manufacturing firms listed on the Ho Chi Minh Stock Exchange | O122: https://drive.google.com/open?id=1K9rlE9_aoGuK_-lfK9OA8eSSCxyVgcI3 | P122: https://drive.google.com/open?id=1wq2sKRTipdTr4m9r4GDhixXUTaN05Npx | Q122: https://drive.google.com/open?id=18cv45otgWX0UzKH6ubkONSU0WTqCL9U_ | R122: Factors affecting the financial distress risk of listed manufacturing firms on the Ho Chi Minh Stock Exchange | S122: https://drive.google.com/open?id=10JEcyG5CApihiJNYJ3SjlXq_aenQQdqA | T122: https://drive.google.com/open?id=1YMA-p1cH3cRS7DoNnLfM-gS3zWxQa93_ | U122: https://drive.google.com/open?id=1IBA-s2nyAvO29ZqaCpVOZGS780cVF996 | V122: https://drive.google.com/open?id=1tBlBanfye4TNBESciWvi3zelC-fJNu68
A123: 46079.023 | B123: tinbvh22414@st.uel.edu.vn | C123: Bùi Việt Hoàng Tín | D123: K224141696 | E123: K22414 | F123: Nộp Báo cáo thực tập và Khóa luận tốt nghiệp | H123: Tiếng Anh | L123: Tiếng Anh | M123: Tiếng Anh | N123: FACTORS AFFECTING GOLD PRICES AND PREDICTING FUTURE GOLD PRICES | O123: https://drive.google.com/open?id=1KdqSSsR2mJ3MioMUCKI6jrObJcNC4JrN | P123: https://drive.google.com/open?id=1brJY3N6cXIDK61DiLfuk7LeYd0-4w57L | Q123: https://drive.google.com/open?id=1yZ-6xLd0DeHWozgsnfMgai7HDBRm0xLW | R123: PREDICTING FUTURE GOLD PRICES AND SUGGESTING SUITABLE DERIVATIVE CONTRACTS | S123: https://drive.google.com/open?id=1FoCgeNRKbjFBZPtmu64Kn7oA-ZlEd7eR | T123: https://drive.google.com/open?id=1J_TORVxap7GBA_AwRZRpg-RFm-7C5ADs | U123: https://drive.google.com/open?id=1_lYRQYawl2JmM5cwZtMDxoq7d1lfyz4n | V123: https://drive.google.com/open?id=1uW2jHkRMavj2CNm9ayc1VOAhCNsEfw_T
A124: 46079.549 | B124: khuongph22414c@st.uel.edu.vn | C124: Phạm Hữu Khương | D124: K224141725 | E124: K22414C | F124: Nộp Báo cáo thực tập và Khóa luận tốt nghiệp | H124: Tiếng Anh | L124: Tiếng Anh | M124: Tiếng Anh | N124: ASSESSING THE OPERATIONAL PERFORMANCE OF HO CHI MINH CITY DEVELOPMENT JOINT STOCK COMMERCIAL BANK (HDBANK) USING THE CAMELS MODEL | O124: https://drive.google.com/open?id=1h38jvDJtjSI6oGyoUyeBOOi8wxdoMcuy | P124: https://drive.google.com/open?id=1nIWx94UqSY_6cwwhyu4Gj5EdBs-dNW_I | Q124: https://drive.google.com/open?id=1l6pfdefEagvukaL1D_gKLZenwFghcIS1 | R124: APPLYING THE DEEP LEARNING MODEL (LSTM, GRU) IN BITCOIN'S VOLATILITY FORECASTING AND RISK MEASUREMENT (VAR) | S124: https://drive.google.com/open?id=11b_GyBPkt4aVlZCigPrVOxSvf481_Qzi | T124: https://drive.google.com/open?id=1T2LdJWbwQ66_vThWW9HK66xSTHT4Xsgg | U124: https://drive.google.com/open?id=1RQ8OgjPyWIloqkxoc-Hbklr7PEv5nmUJ | V124: https://drive.google.com/open?id=1_U7KBemuZk5WZCbdiVQS2XWQVE3Czd46
A125: 46079.89 | B125: minhvn22404a@st.uel.edu.vn | C125: Vũ Nhật Minh | D125: K224040481 | E125: K22404 | F125: Nộp Báo cáo thực tập và Khóa luận tốt nghiệp | H125: Tiếng Anh | L125: Tiếng Anh | M125: Tiếng Anh | N125: AN ANALYSIS OF LENDING ACTIVITIES UNDER THE ENTRUSTED LENDING MODEL AT VINH THANH TRANSACTION OFFICE OF THE VIETNAM BANK FOR SOCIAL POLICIES | O125: https://drive.google.com/open?id=1vFqfqkqPanRcAZDgO2uSpqwtah68n5Y3 | P125: https://drive.google.com/open?id=1l0NCZO7CCzlPVntDbJUMIJyxlLwMpjnz | Q125: https://drive.google.com/open?id=1jCo6juEgdP1BHgypou3GFNK86S2kGsPR | R125: BANK–FINTECH COOPERATION, OWNERSHIP STRUCTURE, AND OVERALL BANK RISK: EMPIRICAL EVIDENCE FROM VIETNAM | S125: https://drive.google.com/open?id=1b6wAb3ttgtJQQNJuhGHJB_5qG8r9AqtX | T125: https://drive.google.com/open?id=19Ygd-wIugzhfAIcSMQkmmQNQASYxIKzc | U125: https://drive.google.com/open?id=1ot7SVp75D0zQFPpknUPDnWIUkpRw5Ihx | V125: https://drive.google.com/open?id=1WQEE_M4lO3fVKOltWKhBSQkyUDSI5vtR | W125: https://drive.google.com/open?id=17hyHFLQZYFsGy29Y3_TFCrI8XljJYZOm
A126: 46079.919 | B126: longpdh22404ca@st.uel.edu.vn | C126: Phan Đức Hiển Long | D126: K224040611 | E126: K22404CA | F126: Nộp Báo cáo thực tập và Khóa luận tốt nghiệp | H126: Tiếng Anh | L126: Tiếng Anh | M126: Tiếng Anh | N126: CORPORATE FINANCIALIZATION AND FIXED INVESTMENT RATES: EVIDENCE ON THE MODERATING EFFECTS OF FINANCIAL CONSTRAINTS AND MONETARY POLICY IN VIETNAM | O126: https://drive.google.com/open?id=1Cq_mNciRZNSPjHd_RAWJs-GgfyfXoJK9 | P126: https://drive.google.com/open?id=1Pje4K0AmVeqIdRU8lNubhg3UtqpTskUX | Q126: https://drive.google.com/open?id=1rIOzm-is4ZxVw_l0QDmvk6lT5KejVU5V | R126: CORPORATE FINANCIALIZATION AND FIXED INVESTMENT RATES: EVIDENCE ON THE MODERATING EFFECTS OF FINANCIAL CONSTRAINTS AND MONETARY POLICY IN VIETNAM | S126: https://drive.google.com/open?id=14m5-s4KWxTaiN7ms3OOXgIhhEQQqp-RI | T126: https://drive.google.com/open?id=1R0DdOOr_n4WscETSU6Ty10I0et601u7r | U126: https://drive.google.com/open?id=1ITJV2AkhvbptLlbSPuoZvJm_vMqP_1jQ
A127: 46079.935 | B127: linhpa22414@st.uel.edu.vn | C127: Phan Ánh Linh | D127: K224141672 | E127: K22414 | F127: Nộp Báo cáo thực tập và Khóa luận tốt nghiệp | H127: Tiếng Anh | L127: Tiếng Anh | M127: Tiếng Việt | N127: Application of Deep Learning Models in Forecasting Stock Trend Reversal Points: A Case Study at KAFI Securities Corporation | O127: https://drive.google.com/open?id=1MLhDKeYEz_oddqgx5S5oz6ozpTk9IveL | P127: https://drive.google.com/open?id=1BjIQ2aQIx20SKBdgBp63UdsvctVp9qUv | Q127: https://drive.google.com/open?id=1XPWiFBJutctu0r8FMIsx5W7QveZshjwj | R127: Ứng dụng mô hình học sâu lai LSTM-GRU trong dự báo điểm đảo chiều xu hướng cổ phiếu: Thực nghiệm tại thị trường chứng khoán Việt Nam | S127: https://drive.google.com/open?id=1apeGzQjqsRX5_mRKHRLphzoZ5xItuB0T | T127: https://drive.google.com/open?id=1c3xKZHPVNn6WdQ1ZW2_9f5JgWG-mBp-d | U127: https://drive.google.com/open?id=1d4e1w1Wnde-C0nw6TxMZXsDy9v9JuifF | V127: https://drive.google.com/open?id=1xD4GnQ_DwxqjLUaJxYF8fFY8w7cJ7T4M
A128: 46079.947 | B128: nhuhq22414@st.uel.edu.vn | C128: Huỳnh Quế Nhu | D128: K224141683 | E128: K224141683 | F128: Nộp Báo cáo thực tập và Khóa luận tốt nghiệp | H128: Tiếng Việt | L128: Tiếng Việt | M128: Tiếng Việt | N128: Xây dựng Agent Chatbot hỗ trợ Nhân viên Chăm sóc Khách hàng | O128: https://drive.google.com/open?id=1hRqSbp4lbhnsBOStTvimXuQVxZ3P9kPE | P128: https://drive.google.com/open?id=1NP9PTScPLps9_NtfUPnBe5-d2VBc6v08 | Q128: https://drive.google.com/open?id=1rZs5wTNqJLJM04GxrAOdk6_J0tugCpJb | R128: Xây dựng trợ lý hỗ trợ nghiệp vụ ngân hàng dựa trên mô hình RAG và kỹ thuật OCR trong xử lý văn bản | S128: https://drive.google.com/open?id=1-CkXnJchq4dIj2pgPHRfaPhDXGfLlDB_ | T128: https://drive.google.com/open?id=1VJOXEsJap6q2G9l9pnpPFcVjZ5iY3lmF | U128: https://drive.google.com/open?id=1rQYle3avXXgsmohbqXQdMo2Tafuw4siy
A129: 46080.008 | B129: thaohtt22404ca@st.uel.edu.vn | C129: Huỳnh Thị Thanh Thảo | D129: K224040623 | E129: K22404CA | F129: Nộp Báo cáo thực tập và Khóa luận tốt nghiệp | H129: Tiếng Anh | L129: Tiếng Anh | M129: Tiếng Anh | N129: ECONOMIC POLICY UNCERTAINTY AND CORPORATE CASH HOLDINGS: EVIDENCE FROM VIETNAMESE NON-FINANCIAL LISTED FIRM | O129: https://drive.google.com/open?id=1KUbWWRi5HdYIXs3hF_WPRqGxfK97CUW7 | P129: https://drive.google.com/open?id=1QWyfMe9-2Yw_d5k0e_trAyCbBhF0St6W | Q129: https://drive.google.com/open?id=1KivUsWLoJLToDIofd98zRktgO3G1ypF_ | R129: ECONOMIC POLICY UNCERTAINTY AND CORPORATE CASH HOLDINGS: EVIDENCE FROM VIETNAMESE NON-FINANCIAL LISTED FIRM | S129: https://drive.google.com/open?id=1GCzdV9VoSgQuVtz80IXTmJgiOSezGoF0 | T129: https://drive.google.com/open?id=10ZzFlVTxL7Y8SOcNk8CGbkjtQMLBoVyi | U129: https://drive.google.com/open?id=1SKY1-J0MB8tMrNO_BLS3MotISjmE-3ez | V129: https://drive.google.com/open?id=1JYI0AkYczb12UstO1ABPw-5VFUxW8fhn
A130: 46080.028 | B130: ngahtt22414@st.uel.edu.vn | C130: Huỳnh Thị Thanh Nga | D130: K224141675 | E130: K22414 | F130: Nộp Báo cáo thực tập và Khóa luận tốt nghiệp | H130: Tiếng Anh | L130: Tiếng Anh | M130: Tiếng Việt | N130: Application of Clustering Algorithms to the VN30 Stock Basket | O130: https://drive.google.com/open?id=1Kjdhvdv_31tSlcoELmrZbCIw1JqoZ5L8 | P130: https://drive.google.com/open?id=1tvPZtgVdqyzF4tUBy6q6tORQC-npp6WN | Q130: https://drive.google.com/open?id=1_TocPymyK03gJrLnkxY1WfHKs79Y3u4G | R130: Xây dựng và so sánh hiệu quả danh mục đầu tư theo mô hình Markowitz và Downside risk trên rổ cổ phiếu VN100 kết hợp kỹ thuật phân cụm | S130: https://drive.google.com/open?id=1HBe6sKVWo57SYNJmGwuMlghonFnmX4hz | T130: https://drive.google.com/open?id=1eO0nM4Ow5C1_Vb6v2-DApEUygeBJrq8r | U130: https://drive.google.com/open?id=1VsNvtPUkM0VfGL8x_pbdCKipe-CAwbwd | V130: https://drive.google.com/open?id=1CBMtWKZzH6HVYhF9vHuwlEhq2dRPom53
A131: 46080.145 | B131: ngannbk22414@st.uel.edu.vn | C131: Nguyễn Bùi Kim Ngân | D131: K224141677 | E131: K22414 | F131: Nộp Báo cáo thực tập và Khóa luận tốt nghiệp | H131: Tiếng Việt | L131: Tiếng Việt | M131: Tiếng Việt | N131: SỬ DỤNG MÁY HỌC DỰ ĐOÁN RỦI RO GIAN LẬN BÁO CÁO TÀI CHÍNH | O131: https://drive.google.com/open?id=1GbQkuj5jqUOmK-HROkbFAqzCQy78qV0k | P131: https://drive.google.com/open?id=1FOBj-CJS_SFfIrg2n6_UXowvXyYthhtQ | Q131: https://drive.google.com/open?id=1KdDjoilKw-DA-egkuNSE2L59MZDKAjBA | R131: SỬ DỤNG MÁY HỌC DỰ ĐOÁN RỦI RO GIAN LẬN BÁO CÁO TÀI CHÍNH | S131: https://drive.google.com/open?id=1x6N9A5xvj3l1952kvKryUl6h8W4FJ96l | T131: https://drive.google.com/open?id=1RGztSfMTytFn7nu9Od7sVqan9VrhPsvP | U131: https://drive.google.com/open?id=1MWfb7ytxGKfDpJdZDJ7snm7-mt6DeBrK | V131: https://drive.google.com/open?id=1wPD3zN-2pyvg_yrhCNT0Y6ysJcsCy1OO
A132: 46080.342 | B132: haiptd22414c@st.uel.edu.vn | C132: Phạm Thị Duyên Hải | D132: K224141720 | E132: K22414C | F132: Nộp Báo cáo thực tập và Khóa luận tốt nghiệp | H132: Tiếng Anh | L132: Tiếng Anh | M132: Tiếng Việt | N132: FINANCIAL PERFORMANCE AND OPPORTUNITY COST OF ESG-INTEGRATED PORTFOLIOS IN THE VIETNAM STOCK MARKET: AN APPROACH USING THE MARKOWITZ MODEL AND THE NSGA-II ALGORITHM | O132: https://drive.google.com/open?id=1qGk98rQ3khmqNE_adec0gpK31tPJt8kL | P132: https://drive.google.com/open?id=1fU4FeL8ShvpbnSTnUPWQwJFRUvB3IHd3 | Q132: https://drive.google.com/open?id=16-xOibueHCR2LpvsiZthEqQ36ugyVZuM | R132: PHÂN TÍCH HIỆU SUẤT TÀI CHÍNH VÀ CHI PHÍ CƠ HỘI CỦA DANH MỤC ĐẦU TƯ TÍCH HỢP TIÊU CHÍ ESG TẠI THỊ TRƯỜNG CHỨNG KHOÁN VIỆT NAM: TIẾP CẬN TỪ MÔ HÌNH MARKOWITZ VÀ THUẬT TOÁN NSGA-II | S132: https://drive.google.com/open?id=1xSfqh-DHR1Rawo8iMrafNTP9XhVOIfBZ | T132: https://drive.google.com/open?id=1KYC_-GVYf9AY--ccGxP5fJPNcyL1d49P | U132: https://drive.google.com/open?id=1sBH4U539CsU4R91SLQV138bzQ890RZ9B | V132: https://drive.google.com/open?id=1foJXo5vyJyZCXNtdlXHLZjjNg_TwoUqd
A133: 46080.388 | B133: duongmd22404c@st.uel.edu.vn | C133: Mai Đức Dương | D133: K224040565 | E133: K22404C | F133: Nộp Báo cáo thực tập và Khóa luận tốt nghiệp | H133: Tiếng Việt | L133: Tiếng Việt | M133: Tiếng Việt | N133: TÁC ĐỘNG CỦA ĐA DẠNG HÓA NGUỒN VỐN ĐẾN LỢI NHUẬN VÀ RỦI RO CỦA CÁC NGÂN HÀNG THƯƠNG MẠI TẠI VIỆT NAM. | O133: https://drive.google.com/open?id=1856Q8WWFFxfP8g7-tsfxljOcDqBUrYSo | P133: https://drive.google.com/open?id=16TAzlpGz82euNV0RFnQDkq_DFMXwNUlH | Q133: https://drive.google.com/open?id=187IFV9QFG8b4cFl3fGsuxjgquLu6CqcM | R133: TÁC ĐỘNG CỦA ĐA DẠNG HÓA NGUỒN VỐN ĐẾN LỢI NHUẬN VÀ RỦI RO CỦA CÁC NGÂN HÀNG THƯƠNG MẠI TẠI VIỆT NAM. | S133: https://drive.google.com/open?id=1_4WoNPmeGOdzuEQ5tydrLhD2UoON2KFv | T133: https://drive.google.com/open?id=1VPP7NhXpD7CXszUkbpX5i9_i9-BMqPVG | U133: https://drive.google.com/open?id=1EPNhUl4O4yR8oI9faa2k4qzYIpY7uFVJ | V133: https://drive.google.com/open?id=1BvsqiOgrESwb3DnRjhzC0xoNhdLDea7P
A134: 46080.41 | B134: toanpnx22414@st.uel.edu.vn | C134: Phan Nguyễn Xuân Toàn | D134: K224141699 | E134: K22414 | F134: Nộp Báo cáo thực tập và Khóa luận tốt nghiệp | H134: Tiếng Việt | L134: Tiếng Việt | M134: Tiếng Việt | N134: HOẠT ĐỘNG CỦA BỘ PHẬN KINH DOANH TẠI CÔNG TY TRÁCH NHIỆM HỮU HẠN MỘT THÀNH VIÊN THƯƠNG MẠI DỊCH VỤ XUẤT NHẬP KHẨU NHẬT MỸ | O134: https://drive.google.com/open?id=1BMWzPLbc2kuqbs6nfc0I3CyP8W0FaeOM | P134: https://drive.google.com/open?id=1eEHEOgyQwAkpnOFsOhVsvYwYESHzJ7Vj | Q134: https://drive.google.com/open?id=17PVZ2u7ns_goO5NfXBNoQO-8lKOtHQTY | R134: THIẾT KẾ VÀ TRIỂN KHAI HỆ THỐNG GIAO DỊCH ĐỊNH LƯỢNG THÍCH NGHI (ADAPTIVE) TRÊN THỊ TRƯỜNG TIỀN MÃ HÓA ỨNG DỤNG BỘ LỌC KALMAN VÀ TỐI ƯU HÓA DANH MỤC THEO KELLY CRITERION | S134: https://drive.google.com/open?id=1nfvXbXBBOl55YDqEI_K3x-gNOV88_xgM | T134: https://drive.google.com/open?id=1lwOP_mrSq1s2GMWzTBodQADxIirLGyqH | U134: https://drive.google.com/open?id=1WtN9DGNOJWmV5jprpHk0Hp3HfwfopWiy
A135: 46080.412 | B135: nhyvhu22404ca@st.uel.edu.vn | C135: Võ Hoàng Uyên Nhy | D135: K22404619 | E135: K22404CA | F135: Nộp Báo cáo thực tập và Khóa luận tốt nghiệp | H135: Tiếng Anh | L135: Tiếng Anh | M135: Tiếng Anh | N135: The impact of Agency Cost on Overinvestment and the Moderating Role of Free Cash Flow: Evidence in Vietnam Non-financial listed companies | O135: https://drive.google.com/open?id=1dqhgcS1zXIflOrXsmk3VKr3VWfieqii8 | P135: https://drive.google.com/open?id=1C2P2hf0V-cTK7IjQ5JUFe0Snd8kZluHk | Q135: https://drive.google.com/open?id=1caUCkfIJd3-NASLYcHL9fPJ0jlYXowWd | R135: The impact of Agency Cost on Overinvestment and the Moderating Role of Free Cash Flow: Evidence in Vietnam Non-financial listed companies | S135: https://drive.google.com/open?id=1wgnNPwwir_WOuP4_yGlPuyEJpI854wIZ | T135: https://drive.google.com/open?id=1pcDE6Ohuz8ad8CSwW9CBVypj8semxzKK | U135: https://drive.google.com/open?id=1KSW7hLtpiOQ1qi4fgVxTQnodY41_YtRU
A136: 46080.414 | B136: thutna22404c@st.uel.edu.vn | C136: Trần Nguyễn Anh Thư | D136: K224040588 | E136: K22404C | F136: Nộp Báo cáo thực tập và Khóa luận tốt nghiệp | H136: Tiếng Anh | L136: Tiếng Anh | M136: Tiếng Việt | N136: ANALYSIS OF INDIVIDUAL CUSTOMER LENDING ACTIVITIES AT THE VIETNAM BANK FOR AGRICULTURE AND RURAL DEVELOPMENT | O136: https://drive.google.com/open?id=1X3sB_oLKEJQhf_Mkqpqp-BdeKCJ2Ie-v | P136: https://drive.google.com/open?id=1SsSI51UTy7OiOI6gEfzbjvVpapB1JBuB | Q136: https://drive.google.com/open?id=1hdYuwZZ9VK_HNUexm8NuZameSkNlhGVE | R136: PHÂN TÍCH CÁC YẾU TỐ ẢNH HƯỞNG ĐẾN NỢ XẤU TẠI CÁC NGÂN HÀNG THƯƠNG MẠI VIỆT NAM GIAI ĐOẠN 2014 - 2024 | S136: https://drive.google.com/open?id=1-fSe6ljPODfmDnuw0i9YLGHJuwBMowKW | T136: https://drive.google.com/open?id=1kuch92MH67O90sGFYLWAJS1ayM9kxLQa | U136: https://drive.google.com/open?id=1XMnQDn5kp4i7xZPaNh-FSBIVvG80Vws9 | V136: https://drive.google.com/open?id=1z1AhKmQcGeKUtuKtyn0EVKI_6MNf_Sp_
A137: 46080.43 | B137: nhihtn22414@st.uel.edu.vn | C137: Huỳnh Thị Ngọc Nhi | D137: K224141680 | E137: K22414 | F137: Nộp Báo cáo thực tập và Khóa luận tốt nghiệp | H137: Tiếng Việt | L137: Tiếng Việt | M137: Tiếng Việt | N137: ỨNG DỤNG MACHINE LEARNING TRONG XÂY DỰNG HỆ THỐNG DỰ BÁO RỦI RO CỔ PHIẾU TRÊN THỊ TRƯỜNG CHỨNG KHOÁN VIỆT NAM | O137: https://drive.google.com/open?id=1O2QGou6feFBaLvpDL53oCTcf3hIx0BK9 | P137: https://drive.google.com/open?id=1UZ0UgdUXIs6dQodb-RCcT9dkdSXnZo8_ | Q137: https://drive.google.com/open?id=1S1aP9MNRxraI0Wqe-6fa3C_h6y1Ybksb | R137: ỨNG DỤNG MACHINE LEARNING TRONG XÂY DỰNG HỆ THỐNG DỰ BÁO RỦI RO CỔ PHIẾU TRÊN THỊ TRƯỜNG CHỨNG KHOÁN VIỆT NAM | S137: https://drive.google.com/open?id=1pV3dCYZAj-pE5bgCdYuZjTNK9r2yHBLF | T137: https://drive.google.com/open?id=1W8MQWV4sanwhYD4NafoB-J7swZrvDuWW | U137: https://drive.google.com/open?id=1UTADVLOpFqBMJR13M3GIHYLz68beUkyu | V137: https://drive.google.com/open?id=1gV5fvJlvJtiqJ9kXdWw8uAtxTaoIPpPX
A138: 46080.448 | B138: quynhhnn22414@st.uel.edu.vn | C138: Hứa Nguyễn Như Quỳnh | D138: K224141687 | E138: K22414 | F138: Nộp Báo cáo thực tập và Khóa luận tốt nghiệp | H138: Tiếng Anh | L138: Tiếng Anh | M138: Tiếng Việt | N138: MACHINE LEARNING – BASED ESTIMATION OF OPTIMAL CORPORATE CASH HOLDING FOR NON-FINANCIAL FIRMS IN VIETNAM | O138: https://drive.google.com/open?id=15AVWGF0I_ywFNXJzkJHYeK3ymkBulseE | P138: https://drive.google.com/open?id=1ne0wMLKGInRhVCnAJGYszBCSJsWdaGtM | Q138: https://drive.google.com/open?id=1UtN_BuOY7kGce6qz6sjJbuMFyVz2Z9yy | R138: ỨNG DỤNG HỌC MÁY TRONG XÁC ĐỊNH TỶ LỆ NẮM GIỮ TIỀN MẶT TỐI ƯU CỦA DOANH NGHIỆP PHI TÀI CHÍNH TẠI VIỆT NAM | S138: https://drive.google.com/open?id=1IHmCXj6UpzuYT5Tf4zUozICgocSzpAV- | T138: https://drive.google.com/open?id=1ZNE3Q8QO5Lt80cjNExoNwJTK7kHSTPQK | U138: https://drive.google.com/open?id=1Q5gyEZfKzPBc5ZpfxbJO8DLThEJcbhWY | V138: https://drive.google.com/open?id=1w5NbhxQ4Y6HEr6t2h2MX4UMNz_bSmaVN
A139: 46080.475 | B139: huongly11052004@gmail.com | C139: Bùi Hương Ly | D139: K224040573 | E139: K22404C | F139: Nộp Báo cáo thực tập và Khóa luận tốt nghiệp | H139: Tiếng Anh | L139: Tiếng Anh | M139: Tiếng Anh | N139: Analysis of factors affecting the issuance of green bonds in developing countries | O139: https://drive.google.com/open?id=1mKvYKRkaD_6LgFXFWfElOye2zeFeAf8F | P139: https://drive.google.com/open?id=1DJ67IZK9fbkroKFZfxHfzWwJry6OlMZc | Q139: https://drive.google.com/open?id=1lK5a1AvKPLqanKH_ycr0id4qESA8lyFy | R139: Analysis of factors affecting the issuance of green bonds in developing countries | S139: https://drive.google.com/open?id=14rZm4z7f6_rVmj3r_6voMl_4U8rtox5F | T139: https://drive.google.com/open?id=1Gv4S7HuIAS7YFM08pRlXEbQoAhJabRo3 | U139: https://drive.google.com/open?id=1vkWRD-FF5tvoYjw78YgKJqhEArop8JJM | V139: https://drive.google.com/open?id=1WN9FMXcEch3XtjPFCAulZI0JXYDLivcs
A140: 46080.479 | B140: huyvb22404b@st.uel.edu.vn | C140: Võ Bảo Huy | D140: K224040524 | E140: K22404 | F140: Nộp Báo cáo thực tập và Khóa luận tốt nghiệp | H140: Tiếng Việt | L140: Tiếng Việt | M140: Tiếng Việt | N140: TÍNH LAN TỎA GIỮA CÁC TÀI SẢN DEFI, TIỀN MÃ HÓA, CỔ PHIẾU VÀ TÀI SẢN TRÚ ẨN AN TOÀN | O140: https://drive.google.com/open?id=1cTOiSEPwzk0syQ-NXgLQHz0WQSNLLc6X | P140: https://drive.google.com/open?id=1zxtJnmXIZDDwwI-6dKayZl89lfv7I6p4 | Q140: https://drive.google.com/open?id=1j90coO--xBBbO1M6WnEQRC7haG5fPAZy | R140: TÍNH LAN TỎA GIỮA CÁC TÀI SẢN DEFI, TIỀN MÃ HÓA, CỔ PHIẾU VÀ TÀI SẢN TRÚ ẨN AN TOÀN | S140: https://drive.google.com/open?id=10lpHY1hjMRfvFeUJEwOX4In0mDiuXT3J | T140: https://drive.google.com/open?id=1lqSr7hotTE5eTp9mKVBsZe0V9TAtCz87 | U140: https://drive.google.com/open?id=1ew9hYnVDuazZ4MgYuhKpx8-ovo51tl_o
A141: 46080.479 | B141: kiennh22414@st.uel.edu.vn | C141: Nguyễn Hữu Kiên | D141: K224141670 | E141: K22414 | F141: Nộp Báo cáo thực tập và Khóa luận tốt nghiệp | H141: Tiếng Anh | L141: Tiếng Anh | M141: Tiếng Anh | N141: Unveiling Hidden Financial Statement Fraud Through Weak Supervision and Dynamic Ensemble Selection: Evidence from Vietnam | O141: https://drive.google.com/open?id=1a-F88-3rhsEyyPjZ5Cdn0p-ae2jxJzk3 | P141: https://drive.google.com/open?id=1MRFIvT2a7MbpVW9iWmNZPjjKo6Z_NFHo | Q141: https://drive.google.com/open?id=1hTiZVmtz1BIzOjXP90AS0HPLW9K2ezdT | R141: Unveiling Hidden Financial Statement Fraud Through Weak Supervision and Dynamic Ensemble Selection: Evidence from Vietnam | S141: https://drive.google.com/open?id=1XohfkH1kyZdLJBcurOVOABNzd9VZckoM | T141: https://drive.google.com/open?id=1AxVTTjqBcIHDaIqg2DHdY_DNTLUa7CZ5 | U141: https://drive.google.com/open?id=1gaU5GJhiohPJ6vwiM1PvUN99B7Bn-94s | V141: https://drive.google.com/open?id=1yAe2sD1cqBcWaV0Lm7DEmLIiyizeAO8m
A142: 46080.479 | B142: trinm22404ca@st.uel.edu.vn | C142: Nguyễn Minh Trí | D142: K224040626 | E142: K22404CA | F142: Nộp Báo cáo thực tập và Khóa luận tốt nghiệp | H142: Tiếng Anh | L142: Tiếng Anh | M142: Tiếng Anh | N142: CASH-FLOW VOLATILITY AND FIRM LEVERAGE: MULTI-MEASURE EVIDENCE FROM VIETNAM’S LISTED NON-FINANCIAL FIRMS | O142: https://drive.google.com/open?id=1TuU7-9V8ZnXcYqlKxMJMTa61STtcMv_T | P142: https://drive.google.com/open?id=1qP2kBahmzpZEXRrgJJTWQLRQLAe0IPrA | Q142: https://drive.google.com/open?id=12WZbrcWvJeN7Dda77548IP-RmCj7OcXq | R142: CASH-FLOW VOLATILITY AND FIRM LEVERAGE: MULTI-MEASURE EVIDENCE FROM VIETNAM’S LISTED NON-FINANCIAL FIRMS | S142: https://drive.google.com/open?id=1gj0XTcKScoi3VbTJQb61Kdfhp66i-Kbn | T142: https://drive.google.com/open?id=1BIXksgy_Q9vgje3vPnDJv-qGyxAZR6Xd | U142: https://drive.google.com/open?id=1LNI6b4ktxsZzBTtpoqDqjV8xkCHdXJYL | V142: https://drive.google.com/open?id=1Ok-VdvWDlv7pFaDiLIizN1izbYt3F68w
A143: 46080.499 | B143: nhatvyho04@gmail.com | C143: Hồ Nguyễn Nhật Vy | D143: K224141709 | E143: K22414 | F143: Nộp Báo cáo thực tập và Khóa luận tốt nghiệp | H143: Tiếng Anh | L143: Tiếng Anh | M143: Tiếng Việt | N143: BUILDING STOCK TRADING SYSTEM: COMPARING TRADITIONAL TECHNICAL INDICATORS WITH MACHINE LEARNING FOR TRADING SIGNAL GENERATION | O143: https://drive.google.com/open?id=17m0KfdZXqUUUl9GK087cBC0EYQ7_NaxY | P143: https://drive.google.com/open?id=1FUs6mNzfUD3uNRtui8OTiyLz62bCxCsQ | Q143: https://drive.google.com/open?id=1hdIp_z_on1rF6kBAOldgAodt6TO01WaA | R143: XÂY DỰNG HỆ THỐNG GIAO DỊCH CỔ PHIẾU: SO SÁNH DỰ BÁO TÍN HIỆU GIAO DỊCH: PHƯƠNG PHÁP KỸ THUẬT TRUYỀN THỐNG VÀ MACHINE LEARNING | S143: https://drive.google.com/open?id=1PxZ3CQdJ6MRHVAhJxcILeCY7uISOQ9sx | T143: https://drive.google.com/open?id=1tk3deYnlBT_HQvyVtnWPQhx0VnzLw-kW | U143: https://drive.google.com/open?id=1w_th_o_oe1e9BQ4ktSyCKPPYP1bB4l8j | V143: https://drive.google.com/open?id=1tum6Kd_DrW-48EL4cRjW1SFoo-t_mtkA
A144: 46080.503 | B144: chilp22414@st.uel.edu.vn | C144: Lê Phúc Chí | D144: K224141652 | E144: K22414 | F144: Nộp Báo cáo thực tập và Khóa luận tốt nghiệp | H144: Tiếng Việt | L144: Tiếng Việt | M144: Tiếng Việt | N144: PHÂN TÍCH CHẤT LƯỢNG DỊCH VỤ KHÁCH HÀNG TẠI NGÂN HÀNG THƯƠNG MẠI CỔ PHẦN SÀI GÒN – HÀ NỘI – CHI NHÁNH QUẢNG NGÃI | O144: https://drive.google.com/open?id=1Du5K4AR_-OV5I0XdOGeWWY1N1y4MqxSD | P144: https://drive.google.com/open?id=1tXRBO_-jJcFXyb4HfjTbL2UvXus1gBy_ | Q144: https://drive.google.com/open?id=1cwc9foRx38U2OOaSqjE9TTQJpJUR4djW | R144: ỨNG DỤNG MÔ HÌNH HỌC SÂU VÀ HỆ THỐNG TRUY XUẤT THÔNG TIN ĐA CHỈ MỤC TRONG TƯ VẤN ĐẦU TƯ | S144: https://drive.google.com/open?id=1jc7fXPv1wf52g4ApMQpNbwU67t9CZQbi | T144: https://drive.google.com/open?id=1SYeFmtmRykFwc-pi5hsOEnlYvWqTKBIB | U144: https://drive.google.com/open?id=1FJgp55cUD7GB_Zh0Hj2CLxe9d54wRIvf | V144: https://drive.google.com/open?id=1emqedl2UEuxo5dzjZ7EUstQuMBccP_Qb
A145: 46080.528 | B145: khangpvd22414@st.uel.edu.vn | C145: Phan Vũ Đình Khang | D145: K224141668 | E145: K22414 | F145: Nộp Báo cáo thực tập và Khóa luận tốt nghiệp | H145: Tiếng Việt | L145: Tiếng Việt | M145: Tiếng Việt | N145: XÂY DỰNG HỆ THỐNG HỖ TRỢ QUYẾT ĐỊNH ĐẦU TƯ CHỨNG KHOÁN DỰA TRÊN MACHINE LEARNING, TỐI ƯU DANH MỤC THEO MARKOWITZ VÀ CHATBOT SỬ DỤNG MÔ HÌNH NGÔN NGỮ LỚN | O145: https://drive.google.com/open?id=1Yydyi4DgM9JB8k4WYKpKmUuokDuhxgSZ | P145: https://drive.google.com/open?id=1POTSd8KRPk892pkuttvy3UVpfAtFlAwf | Q145: https://drive.google.com/open?id=1yXwxtcn2TSosQTcyGwWeRRE0_lCau0SJ | R145: XÂY DỰNG HỆ THỐNG HỖ TRỢ QUYẾT ĐỊNH ĐẦU TƯ CHỨNG KHOÁN DỰA TRÊN MACHINE LEARNING, TỐI ƯU DANH MỤC THEO MARKOWITZ VÀ CHATBOT SỬ DỤNG MÔ HÌNH NGÔN NGỮ LỚN | S145: https://drive.google.com/open?id=1lGSvce6eokP8gde93QUuRwi_6C08vTCI | T145: https://drive.google.com/open?id=1iGYCMu1VvjzMptAvGw8G67q-Jc7vwTFv | U145: https://drive.google.com/open?id=1U3CnEa6ocFvdc8GHJVYyNGYQtbzw-W8U | V145: https://drive.google.com/open?id=19usFsYWjPQJXbuF8xQcnqahwXwxLIFDW
A146: 46080.54 | B146: trangnth22404a@st.uel.edu.vn | C146: Nguyễn Thị Huyền Trang | D146: K224040503 | E146: K22404 | F146: Nộp Báo cáo thực tập và Khóa luận tốt nghiệp | H146: Tiếng Việt | L146: Tiếng Việt | M146: Tiếng Việt | N146: ẢNH HƯỞNG CỦA NỢ XẤU ĐẾN KHẢ NĂNG SINH LỜI CỦA CÁC NGÂN HÀNG THƯƠNG MẠI VIỆT NAM | O146: https://drive.google.com/open?id=1kGS2UfMW4YwWBWHHWgz84TahRH_405Dc | P146: https://drive.google.com/open?id=1lIBbvy7zZAFYjIci8_JwV4AJICHWQF25 | Q146: https://drive.google.com/open?id=1hPd-y0QRyP7xAS-Ua-vkhwZN1TUpFtAI | R146: ẢNH HƯỞNG CỦA NỢ XẤU ĐẾN KHẢ NĂNG SINH LỜI CỦA CÁC NGÂN HÀNG THƯƠNG MẠI VIỆT NAM | S146: https://drive.google.com/open?id=1xltPUoWnClLWrv2nWIgqT_Aw1VBJxBLB | T146: https://drive.google.com/open?id=1SNM4D0O4WnYwmkuTkTN5VCsW2C0cWmBM | U146: https://drive.google.com/open?id=1cOInpL22aN1zqpejWt5Rz5RJmWVP8b9A
A147: 46080.547 | B147: hadn22414@st.uel.edu.vn | C147: Đào Ngọc Hà | D147: K224141658 | E147: K22414 | F147: Nộp Báo cáo thực tập và Khóa luận tốt nghiệp | H147: Tiếng Việt | L147: Tiếng Việt | M147: Tiếng Việt | N147: ỨNG DỤNG HỌC MÁY TRONG DỰ BÁO RỦI RO QUẢN TRỊ LỢI NHUẬN VÀ TÁC ĐỘNG ĐẾN TỶ SUẤT SINH LỜI CỔ PHIẾU: BẰNG CHỨNG THỰC NGHIỆM TẠI VIỆT NAM | O147: https://drive.google.com/open?id=1bRmRcOoyot2eNBXY4xcJjG9itcztWplK | P147: https://drive.google.com/open?id=1N-metQOioBkML6eHKGqkjOa-ojxspUaw | Q147: https://drive.google.com/open?id=1UtSbpdL0wgV7fYMMRFGRvdpYQqAWiXGn | R147: ỨNG DỤNG HỌC MÁY TRONG DỰ BÁO RỦI RO QUẢN TRỊ LỢI NHUẬN VÀ TÁC ĐỘNG ĐẾN TỶ SUẤT SINH LỜI CỔ PHIẾU: BẰNG CHỨNG THỰC NGHIỆM TẠI VIỆT NAM | S147: https://drive.google.com/open?id=1153IDWCNz6trk9W6EzfQ2m3DdjqONwc1 | T147: https://drive.google.com/open?id=10UiWBXmtXE6rN1vZae6BNOE4nnwOV4P9 | U147: https://drive.google.com/open?id=1sLcI2HtyjXJSjXc-km5CZooJ1hbszcx5 | V147: https://drive.google.com/open?id=1VFwLWPENj83jC1zsdzhw3kSg_M2KEelZ
A148: 46080.548 | B148: quynhmn22414@st.uel.edu.vn | C148: Mai Như Quỳnh | D148: K224141688 | E148: K22414 | F148: Nộp Báo cáo thực tập và Khóa luận tốt nghiệp | H148: Tiếng Việt | L148: Tiếng Việt | M148: Tiếng Việt | N148: Xếp hạng tín nhiệm các Ngân hàng thương mại tại Việt Nam dựa trên chỉ số tài chính tổng hợp | O148: https://drive.google.com/open?id=1jX-4KaRAtsygnkcFdI_zbYTxjI4hAoHV | P148: https://drive.google.com/open?id=1GCGMDJf8Nawi7L4r0390eIF5MEyTD17o | Q148: https://drive.google.com/open?id=1MR6Xehd9yJupvdOpSpMTs_Nfote25Hda | R148: Xếp hạng tín nhiệm các Ngân hàng thương mại tại Việt Nam dựa trên chỉ số tài chính tổng hợp | S148: https://drive.google.com/open?id=1Eh72Ph2M1E1oyxl12YcWeHNOexQk04dD | T148: https://drive.google.com/open?id=1-mXPqR0BOmaZwqXMfMy1MvUJ7ZoJp7VF | U148: https://drive.google.com/open?id=1oE3_zoS4AASoCgR4CmnkuyUvMot1MB2g | V148: https://drive.google.com/open?id=1vk7iVXK4oTHRGQoO6Pw0R49Clq_9MYsO
A149: 46080.551 | B149: tramnnt22414c@st.uel.edu.vn | C149: Nguyễn Ngọc Thảo Trâm | D149: K224141741 | E149: 414C | F149: Nộp Báo cáo thực tập và Khóa luận tốt nghiệp | H149: Tiếng Anh | L149: Tiếng Anh | M149: Tiếng Anh | N149: APPLICATION OF MACHINE LEARNING IN BREAKOUT SIGNAL IDENTIFICATION IN THE VIETNAMESE STOCK MARKET | O149: https://drive.google.com/open?id=1QrmTPSqdJ7-b-afzBFfSZSES4mQ4fuzF | P149: https://drive.google.com/open?id=12SSXRqShHzQxlToSS9ggufQz1OLWAqet | Q149: https://drive.google.com/open?id=1gnHRtxvnFb5EhOlF_MKmIUfnjyxb6znk | R149: APPLICATION OF MACHINE LEARNING IN BREAKOUT SIGNAL IDENTIFICATION IN THE VIETNAMESE STOCK MARKET | S149: https://drive.google.com/open?id=12cFSDH0GuX9HjaeSIOjZeugd06MdvNM8 | T149: https://drive.google.com/open?id=1RUsP3lf_PIf8K92_Sf-uef0JrX0FzhPk | U149: https://drive.google.com/open?id=1H9pMCTQ3YQ0IoaI6G8LvRqpqB4VajsU0
A150: 46080.552 | B150: nguyenddh22404c@st.uel.edu.vn | C150: Đinh Đỗ Hạnh Nguyên | D150: K224040578 | E150: K22404C | F150: Nộp Báo cáo thực tập và Khóa luận tốt nghiệp | H150: Tiếng Anh | L150: Tiếng Anh | M150: Tiếng Anh | N150: THE IMPACT OF CAPITAL STRUCTURE ON PROFITABILITY: A CASE STUDY OF VIETNAMESE NON – FINANCIAL LISTED COMPANIES | O150: https://drive.google.com/open?id=1mLHOl0k_jH9DZv1QaQPdVLLOqHT__zd_ | P150: https://drive.google.com/open?id=1tzdiUNyM9R5UmezcOyUZWyhMOJ1OXSZf | Q150: https://drive.google.com/open?id=14BueM2JPAWozHYKykmq84vh7X6-tNJFU | R150: THE IMPACT OF CAPITAL STRUCTURE ON PROFITABILITY: A CASE STUDY OF VIETNAMESE NON – FINANCIAL LISTED COMPANIES | S150: https://drive.google.com/open?id=1nEhyjOkz0VE0PBQIhqFTJpv1fKyUfA56 | T150: https://drive.google.com/open?id=16-X_PSjs7JIlHm8uxtM_p7IdlbKdl69a | U150: https://drive.google.com/open?id=1SjYXA8vBAtqhSoQB5vBlHx1Ut35nOy6o
A151: 46080.559 | B151: thanhmc22404a@st.uel.edu.vn | C151: Mai Công Thanh | D151: K224040496 | E151: K22404 | F151: Nộp Báo cáo thực tập và Khóa luận tốt nghiệp | H151: Tiếng Anh | L151: Tiếng Anh | M151: Tiếng Anh | N151: FINTECH PARTNERSHIPS AND THE PERFORMANCE OF VIETNAMESE COMMERCIAL BANKS: EVIDENCE ON THE ROLE OF CEO GENDER | O151: https://drive.google.com/open?id=1Nd5nggmZWYpCISXzVPp4HxV7W7AErtPs | P151: https://drive.google.com/open?id=1RzWPPha3_M2DmNIyDrNjqQICYCwhXj2H | Q151: https://drive.google.com/open?id=1kTWt5tWYpqueLEaUuuH9ExeoaKGnw0Tt | R151: THE IMPACT OF BANK-FINTECH COOPERATION ON THE PERFORMANCE OF TRADITIONAL COMMERCIAL BANKS IN VIETNAM: THE MODERATING ROLE OF CEO CHARACTERISTICS | S151: https://drive.google.com/open?id=1w0gYi1WcKDjZDrOpTeDJPi8WuJN5DOLY | T151: https://drive.google.com/open?id=1INN_8HLDZA_E5yBd1V43olBLNB_wbXg_ | U151: https://drive.google.com/open?id=1c6fabf-BBpQ7C7ChMP61eHyQl52MRqDv | V151: https://drive.google.com/open?id=12IcXMaMTsWSKeN5AsZz26ePXIPq5MNcU
A152: 46080.62 | B152: tiennq22404ca@st.uel.edu.vn | C152: Ngô Quang Tiến | D152: K224040624 | E152: K22404CA | F152: Nộp Báo cáo thực tập và Khóa luận tốt nghiệp | H152: Tiếng Anh | L152: Tiếng Anh | M152: Tiếng Anh | N152: ANALYSIS OF FINANCIAL MANAGEMENT EFFICIENCY OF HO CHI MINH CITY DEVELOPMENT JOINT STOCK COMMECIAL BANK (HDBANK) USING THE CAMELS FRAMEWORK DURING THE PERIOD 2019 – 2023 | O152: https://drive.google.com/open?id=1MFZGl7XMlI44-QYpHzglpCtoExUefhQd | P152: https://drive.google.com/open?id=1GrHgtiuGMFVeBOLpCK6CmQIfigbDe2oZ | Q152: https://drive.google.com/open?id=1h_TO-sTgcFptcf50OXTslG2EfVTnWSB4 | R152: ANALYSIS OF FINANCIAL MANAGEMENT EFFICIENCY OF HO CHI MINH CITY DEVELOPMENT JOINT STOCK COMMECIAL BANK (HDBANK) USING THE CAMELS FRAMEWORK DURING THE PERIOD 2019 – 2023 | S152: https://drive.google.com/open?id=1IZUczFmSsSUx3cFTANtXrp3D_qMwm_9P | T152: https://drive.google.com/open?id=1G054BX5vZlNLCG-TAWB89PBRP1XdIkde | U152: https://drive.google.com/open?id=10KpeldYPf4sJpud9ge7TWANnBWQH8bwK
A153: 46080.63 | B153: nhinty22404ca@st.uel.edu.vn | C153: Nguyễn Thị Yến Nhi | D153: K224040617 | E153: K22404CA | F153: Nộp Báo cáo thực tập và Khóa luận tốt nghiệp | H153: Tiếng Anh | L153: Tiếng Anh | M153: Tiếng Anh | N153: Financial Determinants Of Corporate Cash Holdings: Evidence From Non-Financial Listed Companies In Vietnam | O153: https://drive.google.com/open?id=15DE4ZDiUrX2Yh0qnS6mae8EIl_6JRhlZ | P153: https://drive.google.com/open?id=1MhUnV9MtNjlLmgXuyUrIMZLZnfRH5TvG | Q153: https://drive.google.com/open?id=1JvUxqipLGRDzkgSeYKYh9142XUxwR3mz | R153: Financial Determinants Of Corporate Cash Holdings: Evidence From Non-Financial Listed Companies In Vietnam | S153: https://drive.google.com/open?id=1Rwo5UibdDKr23FYYs5uFNi0kccDucLfJ | T153: https://drive.google.com/open?id=15XhpoL6FG4YGwaGAz25RtvyoaYiLnysp | U153: https://drive.google.com/open?id=1MfWRRsZzZqRjRiU5J6Akt859NdTVSw06 | V153: https://drive.google.com/open?id=1FpikhrrgeakMA1jsqRLSHvHCUhNsl2o3
A154: 46080.634 | B154: linhpg22414@st.uel.edu.vn | C154: Phạm Gia Linh | D154: K224141673 | E154: K22414 | F154: Nộp Báo cáo thực tập và Khóa luận tốt nghiệp | H154: Tiếng Việt | L154: Tiếng Việt | M154: Tiếng Việt | N154: DỰ BÁO TÌNH TRẠNG KIỆT QUỆ TÀI CHÍNH CỦA CÁC DOANH NGHIỆP SẢN XUẤT VIỆT NAM | O154: https://drive.google.com/open?id=1uRkJoL8a427wRXKLculD4eqPuSKEKN7S | P154: https://drive.google.com/open?id=1FA9m-ZC85a101ZrFUkIi2_XLadbFGbB2 | Q154: https://drive.google.com/open?id=1wwwobvHURW1OuA9Svdor_ihBk0_vqV3F | R154: DỰ BÁO TÌNH TRẠNG KIỆT QUỆ TÀI CHÍNH CỦA CÁC DOANH NGHIỆP SẢN XUẤT VIỆT NAM | S154: https://drive.google.com/open?id=1MMO2klqiwJmVx71SU3BM3tUGI3JYt4N6 | T154: https://drive.google.com/open?id=18c7u_or8pO5n6YHqBse2nhgqnbkgaIq0 | U154: https://drive.google.com/open?id=1rNRpMNXiZIcH7bXRVDrbgTdfDrFu198F | V154: https://drive.google.com/open?id=1dReAwzubtvA1aM2eVHwqdU-GcDKZbst4
A155: 46080.634 | B155: duynq22414c@st.uel.edu.vn | C155: Nguyễn Quang Duy | D155: K224141716 | E155: K22414C | F155: Nộp Báo cáo thực tập và Khóa luận tốt nghiệp | H155: Tiếng Việt | L155: Tiếng Việt | M155: Tiếng Việt | N155: Các yếu tố ảnh hưởng đến hành vi sử dụng và duy trì thanh toán số tại Việt Nam: Tiếp cận kết hợp phân tích định lượng và khai phá dữ liệu cảm xúc. | R155: Các yếu tố ảnh hưởng đến hành vi sử dụng và duy trì thanh toán số tại Việt Nam: Tiếp cận kết hợp phân tích định lượng và khai phá dữ liệu cảm xúc. | S155: https://drive.google.com/open?id=1EW521o6EsqDPKN4Ls3xmI5PWrzCECI8r | T155: https://drive.google.com/open?id=1njvmG4_yFT_PxWQEx74dVbsfPKsawp2r | U155: https://drive.google.com/open?id=1BGcY_84iIfOD-LDrayg9hlSzUAZQPejs | V155: https://drive.google.com/open?id=13dM8Jgv_WKqJWF6vFfUqOB9izDPx4iT8
A156: 46080.636 | B156: vanptd22414@st.uel.edu.vn | C156: Phạm Thị Điệp Vân | D156: K224141708 | E156: K22414 | F156: Nộp Báo cáo thực tập và Khóa luận tốt nghiệp | H156: Tiếng Việt | L156: Tiếng Việt | M156: Tiếng Việt | N156: PHÂN TÍCH VÀ ỨNG DỤNG HỌC MÁY TRONG CẢNH BÁO SỚM RỦI RO TÀI CHÍNH CỦA CÁC DOANH NGHIỆP PHI TÀI CHÍNH NIÊM YẾT TẠI VIỆT NAM | O156: https://drive.google.com/open?id=1C11FbRgWuRhvRLn0A-GJP71ivs78Nuln | P156: https://drive.google.com/open?id=1rznn3NDPrQrgrAcDtCH0D5xxMSEq083g | Q156: https://drive.google.com/open?id=1ck4ueyFOzvWD5YlSQrTG8a1zMr0Xd9lg | R156: PHÂN TÍCH VÀ ỨNG DỤNG HỌC MÁY TRONG CẢNH BÁO SỚM RỦI RO TÀI CHÍNH CỦA CÁC DOANH NGHIỆP PHI TÀI CHÍNH NIÊM YẾT TẠI VIỆT NAM | S156: https://drive.google.com/open?id=1ik8rS8-FKwXAote9J5tcBc2yA80_AfRp | T156: https://drive.google.com/open?id=1VeJNlV_NkR2K-yCn7sqXIiVDRaLovyQ7 | U156: https://drive.google.com/open?id=1t4W2DmEesY7z3Tqr2toaONyeH4hfV1Zb | V156: https://drive.google.com/open?id=113l9gmlaKPrLByxtFxLaMA3khi9h_tHL
A157: 46080.643 | B157: mylha22404ca@st.uel.edu.vn | C157: Lâm Huỳnh Ái My | D157: k224040613 | E157: K22404CA | F157: Nộp Báo cáo thực tập và Khóa luận tốt nghiệp | H157: Tiếng Anh | L157: Tiếng Anh | M157: Tiếng Anh | N157: AN ANALYSIS OF LENDING ACTIVITIES FOR INDIVIDUAL CUSTOMERS AT VIETNAM JOINT STOCK COMMERCIAL BANK FOR INDUSTRY AND TRADE - NAM SAI GON BRANCH | O157: https://drive.google.com/open?id=1lpz0HdRvb8NV3OCSIrNZurGjEFagzL52 | P157: https://drive.google.com/open?id=16uLZJ3LGRSA-b2veqxJByic3IXhf1g16 | Q157: https://drive.google.com/open?id=1sl_yva5_KwOuMYsJX1ARYwDzq4rlovLE | R157: FACTORS AFFECTING THE FINANCIAL PERFORMANCE OF COMMERCIAL BANKS IN VIETNAM | S157: https://drive.google.com/open?id=1mbOmRU9UhnMj1e3Ac0UBN7MiyAPrul9H | T157: https://drive.google.com/open?id=1GT-uxLYPudOJ-mK7Uzgu157fiUgjih8p | U157: https://drive.google.com/open?id=1f9uojzFUBga16paETrwmlx-wGowbbVF6 | V157: https://drive.google.com/open?id=1JtolidBIUGBixWrAz_kT1xWktdV-JBQ5
A158: 46080.649 | B158: giaodnq22404ca@st.uel.edu.vn | C158: Đoàn Ngọc Quỳnh Giao | D158: K224040603 | E158: K22404CA | F158: Nộp Báo cáo thực tập và Khóa luận tốt nghiệp | H158: Tiếng Anh | L158: Tiếng Anh | M158: Tiếng Anh | N158: THE IMPACT OF ESG DISCLOSURE ON THE COST OF DEBT- THE MODERATING EFFECT OF AGENCY COSTS: EVIDENCE FROM VNX50 FIRMS IN VIETNAM | O158: https://drive.google.com/open?id=1XgeKvYKiEQ9qDnQwQNJB1o5QAjTOlzW7 | P158: https://drive.google.com/open?id=1jwCIfiRG1PaFpXBOlfzCB-idxThmtQoY | Q158: https://drive.google.com/open?id=1lc7a2obXdIsBaGGxvJP4NhfonvjjAH7f | R158: THE IMPACT OF ESG DISCLOSURE ON THE COST OF DEBT- THE MODERATING EFFECT OF AGENCY COSTS: EVIDENCE FROM VNX50 FIRMS IN VIETNAM | S158: https://drive.google.com/open?id=1FtRwF6YaiwM030qsAMkx-ETnQDK9dG9o | T158: https://drive.google.com/open?id=1AGCuvHP1Q6-XOLF4trIzhhT5b6UvDNrb | U158: https://drive.google.com/open?id=16NNo68FlXd88aK4LrnAR5FAT7g7Y_D9Z | V158: https://drive.google.com/open?id=1uGaZIX-WB7wzcelM4yG10IsvhPfE0qFw
A159: 46080.65 | B159: trangpt22404ca@st.uel.edu.vn | C159: Phạm Thu Trang | D159: K224040625 | E159: K22404CA | F159: Nộp Báo cáo thực tập và Khóa luận tốt nghiệp | H159: Tiếng Anh | L159: Tiếng Anh | M159: Tiếng Anh | N159: The Impact of Financial Leverage on Firm Value of HOSE-Listed Manufacturing Companies (2016–2024) | O159: https://drive.google.com/open?id=1K2NfBDFrHh4cN-5QuF7hJUIYRpARfO73 | P159: https://drive.google.com/open?id=1rgW6qbdPhUwlnND7SzI9iUioHz0sQLSm | Q159: https://drive.google.com/open?id=1hj4IJfbW8PqtVZ4ksSq5HayAhdtUJbhe | R159: The Impact of Financial Leverage on Firm Value of HOSE-Listed Manufacturing Companies (2016–2024) | S159: https://drive.google.com/open?id=1Vz5BNY90QzJDn0TAS3F6VG7YZJ-njYP4 | T159: https://drive.google.com/open?id=1Td9BnicvMI19o756U06BofN2KnVzo6iu | U159: https://drive.google.com/open?id=1wDVBpFNNtbwga3K9WnHT7TMKS4eEWTRk | V159: https://drive.google.com/open?id=1cx_WMwcybjZYxR0Bz0j9MfQ-SlTReg61
A160: 46080.668 | B160: quynhnn22404a@st.uel.edu.vn | C160: Nguyễn Ngọc Quỳnh | D160: K224040493 | E160: K22404 | F160: Nộp Báo cáo thực tập và Khóa luận tốt nghiệp | H160: Tiếng Việt | L160: Tiếng Việt | M160: Tiếng Việt | N160: Các yếu tố tác động đến biên lãi ròng của các ngân hàng quy mô vừa và nhỏ tại Việt Nam giai đoạn 2014-2024 | O160: https://drive.google.com/open?id=11yGhiDuEpewyFuPpEFaX4AjR2P_isdQG | P160: https://drive.google.com/open?id=12tui8HUKjdP38BQeDSoSsFkEE4NEeqGN | Q160: https://drive.google.com/open?id=1OouxOWNbfUSAE8JqwRDRXpPN4id4fPJ3 | R160: ẢNH HƯỞNG CỦA CÁC NHÂN TỐ VĨ MÔ VÀ CÁC NHÂN TỐ NỘI TẠI ĐẾN BIÊN LÃI RÒNG CỦA CÁC NGÂN HÀNG THƯƠNG MẠI QUY MÔ VỪA VÀ NHỎ TẠI VIỆT NAM TRONG GIAI ĐOẠN 2014-2024 | S160: https://drive.google.com/open?id=1OEpYckDJnZy6-xFaEjecrWYk0rZZr-F5 | T160: https://drive.google.com/open?id=1L8r8ppUS8S5-DrYEa5168cWLieUMaWuq | U160: https://drive.google.com/open?id=1fXFGkkYkeAFnDWvMCDSdqYbdS41YGTtW
A161: 46080.671 | B161: hungnp22404c@st.uel.edu.vn | C161: Nguyễn Phúc Hưng | D161: K224040568 | E161: K22404C | F161: Nộp Báo cáo thực tập và Khóa luận tốt nghiệp | H161: Tiếng Anh | L161: Tiếng Anh | M161: Tiếng Anh | N161: THE MODERATING ROLE OF DIGITAL BANKING ON THE RELATIONSHIP BETWEEN INCOME DIVERSIFICATION AND BANK PERFORMANCE: EVIDENCE FROM VIETNAMESE COMMERCIAL BANK | O161: https://drive.google.com/open?id=1QAFhz2ElYbbHTQ8W_8HXKb0J8ASAE87W | P161: https://drive.google.com/open?id=1LfEkdO37csNNcUwmkOmFCP-nxfqm4Y52 | Q161: https://drive.google.com/open?id=1mavV4_jGLtedbiDa3zq8Rjlnj_S2J7rR | R161: THE MODERATING ROLE OF DIGITAL BANKING ON THE RELATIONSHIP BETWEEN INCOME DIVERSIFICATION AND BANK PERFORMANCE: EVIDENCE FROM VIETNAMESE COMMERCIAL BANK | S161: https://drive.google.com/open?id=14rWPLJmTJKqMD8KSlWNXGrSZ3njUmrwh | T161: https://drive.google.com/open?id=1OldC04FdmM2csIvv1gn5hwt0N5DAv9X4 | U161: https://drive.google.com/open?id=1Kmx1ZJDTqCrFG_WqUqUovGe-OhQPKMSP
A162: 46080.679 | B162: yenlhp22414@st.uel.edu.vn | C162: Lê Hoàng Phi Yến | D162: K224141710 | E162: K22414 | F162: Nộp Báo cáo thực tập và Khóa luận tốt nghiệp | H162: Tiếng Việt | L162: Tiếng Việt | M162: Tiếng Việt | N162: So sánh và phân tích khả năng dự báo đòn bẩy tài chính giữa các mô hình Học máy và mô hình Kinh tế lượng truyền thống đối với các doanh nghiệp phi tài chính niêm yết tại Việt Nam | O162: https://drive.google.com/open?id=11eK_eDZNyE3fMVssAzG1H_2ueaOlRrXj | P162: https://drive.google.com/open?id=1t9JO3J6Mn9uw2nfXtUbgcJUIaEDfpfd4 | Q162: https://drive.google.com/open?id=1k3VHvLUuHzO55cmt1ogWMSYWU_5RRv-y | R162: Dự báo tỷ lệ đòn bẩy tài chính: So sánh và phân tích khả năng dự báo giữa các mô hình Học máy và mô hình Kinh tế lượng truyền thống đối với các doanh nghiệp phi tài chính được niêm yết tại Việt Nam | S162: https://drive.google.com/open?id=1_dzaRlymbqO_J7lNRGkF7Ga1qICe0WQq | T162: https://drive.google.com/open?id=1fGWpO8klza-k8mrSA1mvjYhQO_F6W6pG | U162: https://drive.google.com/open?id=19oB0eka7RXUNohXYLxjFiR6mTsgtLyBY
A163: 46080.682 | B163: uyenntl22404ca@st.uel.edu.vn | C163: Nguyễn Thị Lan Uyên | D163: K224040627 | E163: K22404CA | F163: Nộp Báo cáo thực tập và Khóa luận tốt nghiệp | H163: Tiếng Anh | L163: Tiếng Anh | M163: Tiếng Anh | N163: PREMIER CUSTOMER LENDING ACTIVITIES AT THE JOINT STOCK COMMERCIAL BANK FOR INVESTMENT AND DEVELOPMENT OF VIETNAM – DONG SAI GON BRANCH | O163: https://drive.google.com/open?id=1-0vUWckh88BfTtiq8acH-dITcfR-YSTw | P163: https://drive.google.com/open?id=15uOIgqJj4AkXCWpZy64A0igbBuIeEZNf | Q163: https://drive.google.com/open?id=1bPtn0mPHPKTMvuJ-Dv6x52EW0ZPgUjt- | R163: THE IMPACT OF ESG INFORMATION DISCLOSURE ON THE LIQUIDITY RISK OF COMMERCIAL BANKS IN VIETNAM | S163: https://drive.google.com/open?id=1UpXYj3H39zDtCwq-P6wIyVFpU2fPcQo2 | T163: https://drive.google.com/open?id=1zEZFt3QIFXlg6RqJors6v931eZGjTeG8 | U163: https://drive.google.com/open?id=1Pf2ZQ6KZKQrQt08dsb2iOJkgYf3_W2J3
A164: 46080.682 | B164: binhnv22404c@st.uel.edu.vn | C164: Nguyễn Vũ Bình | D164: K224040564 | E164: K22404C | F164: Nộp Báo cáo thực tập và Khóa luận tốt nghiệp | H164: Tiếng Anh | L164: Tiếng Anh | M164: Tiếng Anh | N164: The impact of capital structure on liquidity of Vietnamese commercial banks: Evidence during 2019-2025 | O164: https://drive.google.com/open?id=1gKnD7l2C7Hmg2IEABOsCGhK-eH6YIyzD | P164: https://drive.google.com/open?id=1LrKKuKXl-4OtdYaopu_RkAtzSHv5z7XW | Q164: https://drive.google.com/open?id=1mMSNihYsEb94hD2XLPqXJubWyhBTMpra | R164: The impact of capital structure on liquidity of Vietnamese commercial banks: Evidence during 2019-2025 | S164: https://drive.google.com/open?id=18Epq500tcInZOdyxjts7YvFMq-JZkXks | T164: https://drive.google.com/open?id=18W0G8EIy_YLVPx8v9TgJCfE1YdC6_umm | U164: https://drive.google.com/open?id=1PGAU9B_kEZgwE_-dsI4Wd5SVGQud_2Gy | V164: https://drive.google.com/open?id=15NoC7VNe9Z6njqvWCuFxaAcAt7_AbdnB
